Workbook
Name EvM_em: #REF!
Name EvM_eva: #REF!
Name PEI: #REF!

Sheet Monitor
A1: año | B1: mes | C1: fecha | D1: fecha_reg | E1: saldo_total (miles de $) | F1: saldo_irregular (miles de $) | G1: tasa_mora | H1: Sector_1_dígito | I1: id | J1: Nombre
A2: =LEFT(D2,4) -> 2024 | B2: =RIGHT(D2,2) -> 02 | C2: =DATE(A2,B2,1) -> 45323 | D2: 202402 | E2: 1453023432 | F2: 20365428 | G2: =F2/E2 -> 0.014015898 | H2: Agricultura, ganadería y silvicultura | I2: 11 | J2: Cultivos temporales
A3: =LEFT(D3,4) -> 2024 | B3: =RIGHT(D3,2) -> 02 | C3: =DATE(A3,B3,1) -> 45323 | D3: 202402 | E3: 136438571 | F3: 8366793 | G3: =F3/E3 -> 0.061322784 | H3: Agricultura, ganadería y silvicultura | I3: 12 | J3: Cultivos perennes
A4: =LEFT(D4,4) -> 2024 | B4: =RIGHT(D4,2) -> 02 | C4: =DATE(A4,B4,1) -> 45323 | D4: 202402 | E4: 61962058 | F4: 184058 | G4: =F4/E4 -> 0.0029704953 | H4: Agricultura, ganadería y silvicultura | I4: 13 | J4: Producción de semillas y de otras formas de propagación de cultivos agrícolas
A5: =LEFT(D5,4) -> 2024 | B5: =RIGHT(D5,2) -> 02 | C5: =DATE(A5,B5,1) -> 45323 | D5: 202402 | E5: 622363442 | F5: 5116624 | G5: =F5/E5 -> 0.0082212798 | H5: Agricultura, ganadería y silvicultura | I5: 14 | J5: Cría de animales
A6: =LEFT(D6,4) -> 2024 | B6: =RIGHT(D6,2) -> 02 | C6: =DATE(A6,B6,1) -> 45323 | D6: 202402 | E6: 174846840 | F6: 5952704 | G6: =F6/E6 -> 0.034045248 | H6: Agricultura, ganadería y silvicultura | I6: 16 | J6: Servicios de apoyo agrícolas y pecuarios
A7: =LEFT(D7,4) -> 2024 | B7: =RIGHT(D7,2) -> 02 | C7: =DATE(A7,B7,1) -> 45323 | D7: 202402 | E7: 49082 | F7: 0 | G7: =F7/E7 -> 0 | H7: Agricultura, ganadería y silvicultura | I7: 17 | J7: Caza, repoblación de animales de caza y servicios de apoyo
A8: =LEFT(D8,4) -> 2024 | B8: =RIGHT(D8,2) -> 02 | C8: =DATE(A8,B8,1) -> 45323 | D8: 202402 | E8: 386818 | F8: 5485 | G8: =F8/E8 -> 0.014179795 | H8: Agricultura, ganadería y silvicultura | I8: 21 | J8: Silvicultura
A9: =LEFT(D9,4) -> 2024 | B9: =RIGHT(D9,2) -> 02 | C9: =DATE(A9,B9,1) -> 45323 | D9: 202402 | E9: 6172746 | F9: 35502 | G9: =F9/E9 -> 0.0057514111 | H9: Agricultura, ganadería y silvicultura | I9: 22 | J9: Extracción de productos forestales
A10: =LEFT(D10,4) -> 2024 | B10: =RIGHT(D10,2) -> 02 | C10: =DATE(A10,B10,1) -> 45323 | D10: 202402 | E10: 926227 | F10: 10110 | G10: =F10/E10 -> 0.010915251 | H10: Agricultura, ganadería y silvicultura | I10: 24 | J10: Servicios de apoyo a la silvicultura
A11: =LEFT(D11,4) -> 2024 | B11: =RIGHT(D11,2) -> 02 | C11: =DATE(A11,B11,1) -> 45323 | D11: 202402 | E11: 15757632 | F11: 4086 | G11: =F11/E11 -> 0.00025930292 | H11: Pesca | I11: 31 | J11: Pesca y servicios de apoyo
A12: =LEFT(D12,4) -> 2024 | B12: =RIGHT(D12,2) -> 02 | C12: =DATE(A12,B12,1) -> 45323 | D12: 202402 | E12: 1529425 | F12: 302 | G12: =F12/E12 -> 0.00019745983 | H12: Pesca | I12: 32 | J12: Explotación de criaderos de peces, granjas piscícolas y otros frutos acuáticos (acuicultura)
A13: =LEFT(D13,4) -> 2024 | B13: =RIGHT(D13,2) -> 02 | C13: =DATE(A13,B13,1) -> 45323 | D13: 202402 | E13: 75135 | F13: 202 | G13: =F13/E13 -> 0.002688494 | H13: Minería, petróleo y gas | I13: 51 | J13: Extracción y aglomeración de carbón
... A5903: =LEFT(D5903,4) -> 2026 | B5903: =RIGHT(D5903,2) -> 03 | C5903: =DATE(A5903,B5903,1) -> 46082 | D5903: 202603 | E5903: 370373796 | F5903: 70362207 | G5903: =F5903/E5903 -> 0.1899762 | H5903: Otras actividades de servicios comunitarios, sociales y personales | I5903: 999 | J5903: Otros sectores

Sheet Mar26
A1: fecha | B1: actividad | C1: saldo_total (miles de $) | D1: saldo_irregular (miles de $)
A2: 202404 | B2: 11 | C2: 1603723382 | D2: 28879052 | E2: =D2/C2 -> 0.018007502
A3: 202404 | B3: 12 | C3: 167427736 | D3: 8228388 | E3: =D3/C3 -> 0.049145907
A4: 202404 | B4: 13 | C4: 92579005 | D4: 263408 | E4: =D4/C4 -> 0.0028452239
A5: 202404 | B5: 14 | C5: 712800684 | D5: 5908685 | E5: =D5/C5 -> 0.008289393
A6: 202404 | B6: 16 | C6: 208757565 | D6: 6412536 | E6: =D6/C6 -> 0.030717622
A7: 202404 | B7: 17 | C7: 77021 | D7: 0 | E7: =D7/C7 -> 0
A8: 202404 | B8: 21 | C8: 509483 | D8: 6728 | E8: =D8/C8 -> 0.013205544
A9: 202404 | B9: 22 | C9: 6750328 | D9: 34460 | E9: =D9/C9 -> 0.0051049371
A10: 202404 | B10: 24 | C10: 1218690 | D10: 8155 | E10: =D10/C10 -> 0.0066916115
A11: 202404 | B11: 31 | C11: 22542262 | D11: 4809 | E11: =D11/C11 -> 0.00021333263
A12: 202404 | B12: 32 | C12: 3217761 | D12: 302 | E12: =D12/C12 -> 9.3854081e-05
A13: 202404 | B13: 51 | C13: 83038 | D13: 32 | E13: =D13/C13 -> 0.00038536574
... A5449: 202603 | B5449: 999 | C5449: 370373796 | D5449: 70362207 | E5449: =D5449/C5449 -> 0.1899762

Sheet SJ
C6: Saldo de crédito en millones de pesos | E6: Total | F6: Irregular | G6: Tasa
C7: =_xlfn.XLOOKUP(D7,Monitor!$I$5450:$I$5676,Monitor!$J$5450:$J$5676) -> Fabricación de acumuladores, pilas y baterías primarias | D7: 272 | E7: 3072.573 | F7: 3013.162 | G7: =F7/E7 -> 0.98066409
C8: =_xlfn.XLOOKUP(D8,Monitor!$I$5450:$I$5676,Monitor!$J$5450:$J$5676) -> Impresión y servicios relacionados con la impresión | D8: 181 | E8: 1808.792 | F8: 765.669 | G8: =F8/E8 -> 0.42330406
C9: =_xlfn.XLOOKUP(D9,Monitor!$I$5450:$I$5676,Monitor!$J$5450:$J$5676) -> Fabricación de productos elaborados de metal ncp | D9: 259 | E9: 5394.072 | F9: 220.428 | G9: =F9/E9 -> 0.040864861
C10: =_xlfn.XLOOKUP(D10,Monitor!$I$5450:$I$5676,Monitor!$J$5450:$J$5676) -> Reparación y mantenimiento de máquinas y equipo | D10: 331 | E10: 63.715 | F10: 49.57 | G10: =F10/E10 -> 0.77799576
C11: =_xlfn.XLOOKUP(D11,Monitor!$I$5450:$I$5676,Monitor!$J$5450:$J$5676) -> Elaboración de bebidas | D11: 110 | E11: 8279.491 | F11: 32.71 | G11: =F11/E11 -> 0.003950726
C12: =_xlfn.XLOOKUP(D12,Monitor!$I$5450:$I$5676,Monitor!$J$5450:$J$5676) -> Fabricación de productos químicos ncp | D12: 202 | E12: 8500.375 | F12: 17.629 | G12: =F12/E12 -> 0.0020739085
C13: =_xlfn.XLOOKUP(D13,Monitor!$I$5450:$I$5676,Monitor!$J$5450:$J$5676) -> Elaboración de productos alimenticios ncp | D13: 107 | E13: 1548.334 | F13: 16.77 | G13: =F13/E13 -> 0.010830996
C14: =_xlfn.XLOOKUP(D14,Monitor!$I$5450:$I$5676,Monitor!$J$5450:$J$5676) -> Fabricación de maquinaria y equipo de uso especial | D14: 282 | E14: 6717.486 | F14: 15.964 | G14: =F14/E14 -> 0.0023764843 | J14: 3072573.0 | K14: 3013162.0
C15: =_xlfn.XLOOKUP(D15,Monitor!$I$5450:$I$5676,Monitor!$J$5450:$J$5676) -> Fabricación de productos de madera, corcho, paja y materiales trenzables | D15: 162 | E15: 1008.921 | F15: 13.206 | G15: =F15/E15 -> 0.013089231
C16: =_xlfn.XLOOKUP(D16,Monitor!$I$5450:$I$5676,Monitor!$J$5450:$J$5676) -> Fabricación de productos metálicos para uso estructural, tanques, depósitos y generadores de vapor | D16: 251 | E16: 2328.818 | F16: 10.287 | G16: =F16/E16 -> 0.0044172623
C17: =_xlfn.XLOOKUP(D17,Monitor!$I$5450:$I$5676,Monitor!$J$5450:$J$5676) -> Industrias manufactureras ncp | D17: 329 | E17: 147.179 | F17: 8.989 | G17: =F17/E17 -> 0.061075289
C18: =_xlfn.XLOOKUP(D18,Monitor!$I$5450:$I$5676,Monitor!$J$5450:$J$5676) -> Fabricación de productos farmaceúticos, sustancias químicas medicinales y productos botánicos de uso farmaceútico | D18: 210 | E18: 21975.12 | F18: 7.168 | G18: =F18/E18 -> 0.00032618707
C19: =_xlfn.XLOOKUP(D19,Monitor!$I$5450:$I$5676,Monitor!$J$5450:$J$5676) -> Preparación de frutas, hortalizas y legumbres | D19: 103 | E19: 16009.004 | F19: 7.025 | G19: =F19/E19 -> 0.00043881556
C20: =_xlfn.XLOOKUP(D20,Monitor!$I$5450:$I$5676,Monitor!$J$5450:$J$5676) -> Fabricación de equipos y productos informáticos | D20: 262 | E20: 8.442 | F20: 5.623 | G20: =F20/E20 -> 0.66607439
C21: =_xlfn.XLOOKUP(D21,Monitor!$I$5450:$I$5676,Monitor!$J$5450:$J$5676) -> Fabricación de soportes ópticos y magnéticos | D21: 268 | E21: 26.877 | F21: 2.328 | G21: =F21/E21 -> 0.08661681
C22: =_xlfn.XLOOKUP(D22,Monitor!$I$5450:$I$5676,Monitor!$J$5450:$J$5676) -> Fabricación de partes, piezas y accesorios para vehículos automotores y sus motores | D22: 293 | E22: 436.942 | F22: 1.711 | G22: =F22/E22 -> 0.0039158515
C23: =_xlfn.XLOOKUP(D23,Monitor!$I$5450:$I$5676,Monitor!$J$5450:$J$5676) -> Producción y procesamiento de carne y productos cárnicos, excepto pescado | D23: 101 | E23: 288.974 | F23: 1.306 | G23: =F23/E23 -> 0.0045194377
C24: =_xlfn.XLOOKUP(D24,Monitor!$I$5450:$I$5676,Monitor!$J$5450:$J$5676) -> Fabricación de productos minerales no metálicos ncp | D24: 239 | E24: 5001.325 | F24: 0.926 | G24: =F24/E24 -> 0.00018515094
C25: =_xlfn.XLOOKUP(D25,Monitor!$I$5450:$I$5676,Monitor!$J$5450:$J$5676) -> Elaboración de productos de molinería, almidones y productos derivados del almidón | D25: 106 | E25: 40.353 | F25: 0.57 | G25: =F25/E25 -> 0.014125344
C26: =_xlfn.XLOOKUP(D26,Monitor!$I$5450:$I$5676,Monitor!$J$5450:$J$5676) -> Fabricación de productos textiles ncp | D26: 139 | E26: 1098.485 | F26: 0.452 | G26: =F26/E26 -> 0.00041147581
I30: 129044664 | J30: 540002751
I31: 1743122520 | J31: 71522700
I32: 89476298422
I33: =I31/I32 -> 0.019481388
I35: =I30/I31 -> 0.074030748 | J35: =J31/J30 -> 0.13244877
F43: Saldo total: 540002751.0 Mora total: 71522700.0 Tasa: 13.24 %

Sheet MZA
C4: Saldo de crédito en millones de pesos | E4: Total | F4: Irregular | G4: Tasa
C5: =_xlfn.XLOOKUP(D5,Monitor!$I$5450:$I$5676,Monitor!$J$5450:$J$5676) -> Elaboración de bebidas | D5: 110 | E5: 316953.28 | F5: 44463.501 | G5: =F5/E5 -> 0.14028409
C6: =_xlfn.XLOOKUP(D6,Monitor!$I$5450:$I$5676,Monitor!$J$5450:$J$5676) -> Fabricación de motores, generadores y transformadores eléctricos y aparatos de distribución y control de la energía eléctrica | D6: 271 | E6: 22800.423 | F6: 22277.473 | G6: =F6/E6 -> 0.97706402
C7: =_xlfn.XLOOKUP(D7,Monitor!$I$5450:$I$5676,Monitor!$J$5450:$J$5676) -> Fabricación de aparatos de uso doméstico ncp | D7: 275 | E7: 3465.35 | F7: 1095.259 | G7: =F7/E7 -> 0.31606014
C8: =_xlfn.XLOOKUP(D8,Monitor!$I$5450:$I$5676,Monitor!$J$5450:$J$5676) -> Preparación de frutas, hortalizas y legumbres | D8: 103 | E8: 27985.575 | F8: 1035.224 | G8: =F8/E8 -> 0.036991343
C9: =_xlfn.XLOOKUP(D9,Monitor!$I$5450:$I$5676,Monitor!$J$5450:$J$5676) -> Fabricación de productos elaborados de metal ncp | D9: 259 | E9: 8269.848 | F9: 572.588 | G9: =F9/E9 -> 0.069238032
C10: =_xlfn.XLOOKUP(D10,Monitor!$I$5450:$I$5676,Monitor!$J$5450:$J$5676) -> Fabricación de productos de madera, corcho, paja y materiales trenzables | D10: 162 | E10: 4092.312 | F10: 433.453 | G10: =F10/E10 -> 0.10591885
C11: =_xlfn.XLOOKUP(D11,Monitor!$I$5450:$I$5676,Monitor!$J$5450:$J$5676) -> Fabricación de productos farmaceúticos, sustancias químicas medicinales y productos botánicos de uso farmaceútico | D11: 210 | E11: 1704.466 | F11: 311.606 | G11: =F11/E11 -> 0.18281738
C12: =_xlfn.XLOOKUP(D12,Monitor!$I$5450:$I$5676,Monitor!$J$5450:$J$5676) -> Industrias manufactureras ncp | D12: 329 | E12: 1174.478 | F12: 267.193 | G12: =F12/E12 -> 0.22749937
C13: =_xlfn.XLOOKUP(D13,Monitor!$I$5450:$I$5676,Monitor!$J$5450:$J$5676) -> Producción y procesamiento de carne y productos cárnicos, excepto pescado | D13: 101 | E13: 9439.266 | F13: 220.094 | G13: =F13/E13 -> 0.023316855
C14: =_xlfn.XLOOKUP(D14,Monitor!$I$5450:$I$5676,Monitor!$J$5450:$J$5676) -> Fabricación de maquinaria y equipo de uso especial | D14: 282 | E14: 17349.277 | F14: 167.305 | G14: =F14/E14 -> 0.0096433413
C15: =_xlfn.XLOOKUP(D15,Monitor!$I$5450:$I$5676,Monitor!$J$5450:$J$5676) -> Elaboración de productos alimenticios ncp | D15: 107 | E15: 4616.641 | F15: 151.873 | G15: =F15/E15 -> 0.032896862
C16: =_xlfn.XLOOKUP(D16,Monitor!$I$5450:$I$5676,Monitor!$J$5450:$J$5676) -> Fabricación de muebles y colchones | D16: 310 | E16: 1709.109 | F16: 89.831 | G16: =F16/E16 -> 0.052560135
... C24: =_xlfn.XLOOKUP(D24,Monitor!$I$5450:$I$5676,Monitor!$J$5450:$J$5676) -> Instalación de maquinaria y equipos industriales | D24: 332 | E24: 508.474 | F24: 22.887 | G24: =F24/E24 -> 0.045011151

Sheet Indice
B1: Hoja | C1: Link
B2: Calidad de cartera | C2: https://www.bcra.gob.ar/archivos/Pdfs/PublicacionesEstadisticas/informes/InfBanc_Anexo.xlsx
B3: Calidad de cartera (Lineas) | C3: https://www.bcra.gob.ar/archivos/Pdfs/PublicacionesEstadisticas/informes/InfBanc_Anexo.xlsx
B4: Cheques rechazados | C4: https://www.bcra.gob.ar/informe-de-pagos-minoristas/
B5: Monitor | C5: Con estos datos, extraídos del la CENDEU (Central de Deudores de BCRA), se construyen las tablas dinamicas para poder armar los graficos y series históricas
B6: Solo Sectores
B7: Graficos

Sheet Calidad de Cartera
A1: Calidad de Cartera Crediticia
A3: Sistema financiero
A4: En porcentaje | B4: 37591 | C4: 37956 | D4: 38322 | E4: 38687 | F4: 39052 | G4: 39417 | H4: 39783 | I4: 40148 | J4: 40179 | K4: 40210 | L4: 40238 | M4: 40269 | N4: 40299 | O4: 40330 | P4: 40360 | Q4: 40391 | R4: 40422 | S4: 40452 | T4: 40483 | U4: 40513 | V4: 40544 | W4: 40575 | X4: 40603 | Y4: 40634 | Z4: 40664 | AA4: 40695 | AB4: 40725 | AC4: 40756 | AD4: 40787 | AE4: 40817 | AF4: 40848 | AG4: 40878 | AH4: 40909 | AI4: 40940 | AJ4: 40969 | AK4: 41000 | AL4: 41030 | AM4: 41061 | AN4: 41091 | AO4: 41122 | AP4: 41153 | AQ4: 41183 | AR4: 41214 | AS4: 41244 | AT4: 41275 | AU4: 41306 | AV4: 41334 | AW4: 41365 | AX4: 41395 | AY4: 41426 | AZ4: 41456 | BA4: 41487 | BB4: 41518 | BC4: 41548 | BD4: 41579 | BE4: 41609 | BF4: 41640 | BG4: 41671 | BH4: 41699 | BI4: 41730 | BJ4: 41760 | BK4: 41791 | BL4: 41821 | BM4: 41852 | BN4: 41883 | BO4: 41913 | BP4: 41944 | BQ4: 41974 | BR4: 42005 | BS4: 42036 | BT4: 42064 | BU4: 42095 | BV4: 42125 | BW4: 42156 | BX4: 42186 | BY4: 42217 | BZ4: 42248 | CA4: 42278 | CB4: 42309 | CC4: 42339 | CD4: 42370 | CE4: 42401 | CF4: 42430 | CG4: 42461 | CH4: 42491 | CI4: 42522 | CJ4: 42552 | CK4: 42583 | CL4: 42614 | CM4: 42644 | CN4: 42675 | CO4: 42705 | CP4: 42736 | CQ4: 42767 | CR4: 42795 | CS4: 42826 | CT4: 42856 | CU4: 42887 | CV4: 42917 | CW4: 42948 | CX4: 42979 | CY4: 43009 | CZ4: 43040 | DA4: 43070 | DB4: 43101 | DC4: 43132 | DD4: 43160 | DE4: 43191 | DF4: 43221 | DG4: 43252 | DH4: 43282 | DI4: 43313 | DJ4: 43344 | DK4: 43374 | DL4: 43405 | DM4: 43435 | DN4: 43466 | DO4: 43497 | DP4: 43525 | DQ4: 43556 | DR4: 43586 | DS4: 43617 | DT4: 43647 | DU4: 43678 | DV4: 43709 | DW4: 43739 | DX4: 43770 | DY4: 43800 | DZ4: 43831 | EA4: 43862 | EB4: 43891 | EC4: 43922 | ED4: 43952 | EE4: 43983 | EF4: 44013 | EG4: 44044 | EH4: 44075 | EI4: 44105 | EJ4: 44136 | EK4: 44166 | EL4: 44197 | EM4: 44228 | EN4: 44256 | EO4: 44287 | EP4: 44317 | EQ4: 44348 | ER4: 44378 | ES4: 44409 | ET4: 44440 | EU4: 44470 | EV4: 44501 | EW4: 44531 | EX4: 44562 | EY4: 44593 | EZ4: 44621 | FA4: 44652 | FB4: 44682 | FC4: 44713 | FD4: 44743 | FE4: 44774 | FF4: 44805 | FG4: 44835 | FH4: 44866 | FI4: 44896 | FJ4: 44927 | FK4: 44958 | FL4: 44986 | FM4: 45017 | FN4: 45047 | FO4: 45078 | FP4: 45108 | FQ4: 45139 | FR4: 45170 | FS4: 45200 | FT4: 45231 | FU4: 45261 | FV4: 45292 | FW4: 45323 | FX4: 45352 | FY4: 45383 | FZ4: 45413 | GA4: 45444 | GB4: 45474 | GC4: 45505 | GD4: 45536 | GE4: 45566 | GF4: 45597 | GG4: 45627 | GH4: 45658 | GI4: 45689 | GJ4: 45717 | GK4: 45748 | GL4: 45778 | GM4: 45809 | GN4: 45839 | GO4: 45870 | GP4: 45901 | GQ4: 45931 | GR4: 45962 | GS4: 45992 | GT4: 46023 | GU4: 46054
A5: Cartera irregular total | B5: 18.088446 | C5: 17.70293 | D5: 10.685333 | E5: 5.1808434 | F5: 3.3907142 | G5: 2.7268475 | H5: 2.679206 | I5: 2.9819582 | J5: 3.0053087 | K5: 2.9031719 | L5: 2.8029277 | M5: 2.6862036 | N5: 2.645191 | O5: 2.4758288 | P5: 2.4329131 | Q5: 2.3587915 | R5: 2.1790951 | S5: 2.0868576 | T5: 1.9827663 | U5: 1.8439958 | V5: 1.7719505 | W5: 1.7049496 | X5: 1.6292849 | Y5: 1.5768273 | Z5: 1.5409429 | AA5: 1.4621717 | AB5: 1.4115999 | AC5: 1.3710009 | AD5: 1.2593854 | AE5: 1.2560386 | AF5: 1.2206176 | AG5: 1.227708 | AH5: 1.3011171 | AI5: 1.3340316 | AJ5: 1.3633645 | AK5: 1.4401407 | AL5: 1.5157052 | AM5: 1.4666915 | AN5: 1.5083234 | AO5: 1.5300937 | AP5: 1.5177816 | AQ5: 1.5697867 | AR5: 1.5502236 | AS5: 1.5367359 | AT5: 1.5834257 | AU5: 1.646368 | AV5: 1.6184521 | AW5: 1.6771206 | AX5: 1.7032666 | AY5: 1.699406 | AZ5: 1.6845671 | BA5: 1.6694359 | BB5: 1.6232721 | BC5: 1.6025339 | BD5: 1.560999 | BE5: 1.5337287 | BF5: 1.5649294 | BG5: 1.5992335 | BH5: 1.6476336 | BI5: 1.7055161 | BJ5: 1.8116337 | BK5: 1.7928942 | BL5: 1.8128119 | BM5: 1.8626924 | BN5: 1.8114161 | BO5: 1.8250771 | BP5: 1.8274452 | BQ5: 1.7925587 | BR5: 1.8127613 | BS5: 1.8102539 | BT5: 1.7807497 | BU5: 1.8442048 | BV5: 1.8250296 | BW5: 1.7541396 | BX5: 1.7154597 | BY5: 1.6746478 | BZ5: 1.6149292 | CA5: 1.5478835 | CB5: 1.5921206 | CC5: 1.5742013 | CD5: 1.6367133 | CE5: 1.6534374 | CF5: 1.6455892 | CG5: 1.6679204 | CH5: 1.6927177 | CI5: 1.7203216 | CJ5: 1.748702 | CK5: 1.8006627 | CL5: 1.7512855 | CM5: 1.7607589 | CN5: 1.7037473 | CO5: 1.7002775 | CP5: 1.7719349 | CQ5: 1.7871076 | CR5: 1.8192552 | CS5: 1.8473039 | CT5: 1.8869664 | CU5: 1.894586 | CV5: 1.8368429 | CW5: 1.7923907 | CX5: 1.7376704 | CY5: 1.7415992 | CZ5: 1.778564 | DA5: 1.7347993 | DB5: 1.8051381 | DC5: 1.8284657 | DD5: 1.8765495 | DE5: 1.9132269 | DF5: 2.0440632 | DG5: 2.0274354 | DH5: 2.1533016 | DI5: 2.1242783 | DJ5: 2.1995886 | DK5: 2.4765806 | DL5: 2.7161855 | DM5: 2.9577855 | DN5: 3.3666436 | DO5: 3.9520404 | DP5: 4.1434187 | DQ5: 4.2695428 | DR5: 4.575215 | DS5: 4.6459697 | DT5: 4.7550432 | DU5: 4.7594988 | DV5: 4.8516383 | DW5: 4.8752019 | DX5: 5.0594861 | DY5: 5.7029147 | DZ5: 5.9736012 | EA5: 6.0958475 | EB5: 5.2659882 | EC5: 5.2325564 | ED5: 5.19981 | EE5: 5.0132049 | EF5: 5.0508861 | EG5: 4.8808033 | EH5: 4.7961359 | EI5: 4.5283915 | EJ5: 4.3996765 | EK5: 4.150064 | EL5: 4.1136937 | EM5: 4.0218794 | EN5: 4.1233251 | EO5: 4.3878877 | EP5: 4.4850959 | EQ5: 5.0439308 | ER5: 5.5656807 | ES5: 5.2928818 | ET5: 5.0152028 | EU5: 4.8740832 | EV5: 4.551054 | EW5: 4.2921129 | EX5: 4.3263639 | EY5: 4.1489638 | EZ5: 3.866044 | FA5: 3.5420084 | FB5: 3.35231 | FC5: 3.2056702 | FD5: 3.1172651 | FE5: 3.1227188 | FF5: 3.0845204 | FG5: 3.0675259 | FH5: 3.0142734 | FI5: 3.0940134 | FJ5: 3.1740153 | FK5: 3.1528107 | FL5: 3.1458493 | FM5: 3.0266417 | FN5: 2.9970731 | FO5: 2.9754087 | FP5: 3.0022394 | FQ5: 3.0793214 | FR5: 2.9494669 | FS5: 2.7191557 | FT5: 2.6006328 | FU5: 3.5490485 | FV5: 3.4126484 | FW5: 2.0218946 | FX5: 1.9585484 | FY5: 1.92439 | FZ5: 1.9048722 | GA5: 1.8222641 | GB5: 1.7291376 | GC5: 1.6478676 | GD5: 1.6080224 | GE5: 1.5252289 | GF5: 1.5336122 | GG5: 1.564008 | GH5: 1.6481877 | GI5: 1.7816297 | GJ5: 1.9626867 | GK5: 2.1782306 | GL5: 2.5494297 | GM5: 2.850967 | GN5: 3.1286348 | GO5: 3.6318047 | GP5: 3.9921831 | GQ5: 4.3798525 | GR5: 5.008001 | GS5: 5.294553 | GT5: 6.0591085 | GU5: 6.395112
A6: Previsiones / Cartera irregular | B6: 72.270763 | C6: 76.788327 | D6: 97.759951 | E6: 115.31339 | F6: 108.17852 | G6: 115.19579 | H6: 117.04632 | I6: 115.3269 | J6: 115.15886 | K6: 117.61995 | L6: 119.0673 | M6: 121.19235 | N6: 121.47004 | O6: 124.98434 | P6: 126.17244 | Q6: 130.81154 | R6: 135.29829 | S6: 138.32157 | T6: 141.56583 | U6: 147.74462 | V6: 150.53951 | W6: 154.82997 | X6: 158.24564 | Y6: 161.15801 | Z6: 161.65161 | AA6: 160.34521 | AB6: 164.97356 | AC6: 168.946 | AD6: 175.19774 | AE6: 177.28423 | AF6: 176.89603 | AG6: 176.08623 | AH6: 168.91532 | AI6: 164.69015 | AJ6: 162.69404 | AK6: 155.39399 | AL6: 149.2576 | AM6: 152.48573 | AN6: 148.94317 | AO6: 148.09233 | AP6: 147.81145 | AQ6: 143.18261 | AR6: 144.10979 | AS6: 144.3804 | AT6: 141.57902 | AU6: 138.11138 | AV6: 139.79168 | AW6: 134.08932 | AX6: 134.20281 | AY6: 133.87237 | AZ6: 135.86318 | BA6: 136.86515 | BB6: 138.41332 | BC6: 140.23252 | BD6: 141.54104 | BE6: 150.45524 | BF6: 153.31181 | BG6: 152.27221 | BH6: 149.04766 | BI6: 145.51384 | BJ6: 140.50042 | BK6: 140.49648 | BL6: 140.16748 | BM6: 139.11368 | BN6: 141.46045 | BO6: 141.88689 | BP6: 141.75302 | BQ6: 141.57322 | BR6: 140.60265 | BS6: 140.82805 | BT6: 140.94875 | BU6: 138.01336 | BV6: 138.59055 | BW6: 140.79923 | BX6: 143.0766 | BY6: 143.77508 | BZ6: 147.93382 | CA6: 151.27386 | CB6: 146.47401 | CC6: 150.18076 | CD6: 145.91075 | CE6: 145.83199 | CF6: 145.81699 | CG6: 146.81735 | CH6: 144.86578 | CI6: 140.90479 | CJ6: 139.71086 | CK6: 138.97308 | CL6: 141.62963 | CM6: 140.1933 | CN6: 143.01482 | CO6: 139.82263 | CP6: 136.87095 | CQ6: 136.56027 | CR6: 134.88133 | CS6: 135.52175 | CT6: 133.14691 | CU6: 132.78889 | CV6: 135.29897 | CW6: 137.83411 | CX6: 143.0162 | CY6: 143.09769 | CZ6: 140.74224 | DA6: 150.60742 | DB6: 136.58321 | DC6: 136.49471 | DD6: 135.04673 | DE6: 132.55741 | DF6: 126.33482 | DG6: 127.00138 | DH6: 124.68627 | DI6: 125.25722 | DJ6: 125.65736 | DK6: 120.61404 | DL6: 126.72323 | DM6: 121.1963 | DN6: 112.55315 | DO6: 91.120475 | DP6: 92.698061 | DQ6: 93.198537 | DR6: 90.903015 | DS6: 92.947907 | DT6: 92.272053 | DU6: 91.35275 | DV6: 94.419715 | DW6: 95.004131 | DX6: 94.221402 | DY6: 94.126243 | DZ6: 83.653489 | EA6: 83.390561 | EB6: 96.104312 | EC6: 100.67183 | ED6: 106.85381 | EE6: 110.60866 | EF6: 110.9899 | EG6: 112.15689 | EH6: 114.97992 | EI6: 119.80676 | EJ6: 126.31111 | EK6: 136.32399 | EL6: 136.52038 | EM6: 139.61664 | EN6: 133.67819 | EO6: 126.19275 | EP6: 123.59209 | EQ6: 109.87846 | ER6: 101.37187 | ES6: 104.82337 | ET6: 106.89086 | EU6: 107.57543 | EV6: 108.26263 | EW6: 110.04569 | EX6: 108.34777 | EY6: 110.51869 | EZ6: 112.8924 | FA6: 115.25591 | FB6: 117.04515 | FC6: 116.46505 | FD6: 116.97783 | FE6: 115.80003 | FF6: 125.12489 | FG6: 123.25338 | FH6: 126.81522 | FI6: 128.4185 | FJ6: 124.89327 | FK6: 124.74532 | FL6: 123.67452 | FM6: 125.05776 | FN6: 125.94603 | FO6: 124.51039 | FP6: 122.55162 | FQ6: 122.05141 | FR6: 120.69621 | FS6: 126.36418 | FT6: 128.71412 | FU6: 140.37707 | FV6: 136.47839 | FW6: 167.50127 | FX6: 175.1256 | FY6: 155.19121 | FZ6: 149.68542 | GA6: 152.11122 | GB6: 153.39066 | GC6: 160.84806 | GD6: 163.20099 | GE6: 171.91549 | GF6: 165.3661 | GG6: 158.99064 | GH6: 156.46598 | GI6: 148.7123 | GJ6: 143.06962 | GK6: 137.37817 | GL6: 126.64772 | GM6: 117.10571 | GN6: 113.05354 | GO6: 107.05969 | GP6: 102.57048 | GQ6: 101.30331 | GR6: 97.676426 | GS6: 93.672113 | GT6: 89.342267 | GU6: 90.140566
A7: (Cartera irregular - Previsiones) / Financiaciones | B7: 5.0157883 | C7: 4.1091462 | D7: 0.23935665 | E7: -0.79336297 | F7: -0.27731026 | G7: -0.41436597 | H7: -0.45670591 | I7: -0.45704184 | J7: -0.45557064 | K7: -0.51153734 | L7: -0.53444272 | M7: -0.56926972 | N7: -0.5679237 | O7: -0.61856938 | P7: -0.63675266 | Q7: -0.72677996 | R7: -0.76918341 | S7: -0.79971669 | T7: -0.82415323 | U7: -0.88040875 | V7: -0.89553514 | W7: -0.93482336 | X7: -0.94898737 | Y7: -0.96435613 | Z7: -0.95001609 | AA7: -0.88235056 | AB7: -0.91716667 | AC7: -0.94525027 | AD7: -0.94702939 | AE7: -0.97071968 | AF7: -0.93860651 | AG7: -0.93411676 | AH7: -0.89666902 | AI7: -0.86298708 | AJ7: -0.8547482 | AK7: -0.79775138 | AL7: -0.74660003 | AM7: -0.76980378 | AN7: -0.73822131 | AO7: -0.73585772 | AP7: -0.72567345 | AQ7: -0.67787484 | AR7: -0.68380038 | AS7: -0.68200959 | AT7: -0.65837284 | AU7: -0.62745358 | AV7: -0.64400929 | AW7: -0.571719 | AX7: -0.58256499 | AY7: -0.57562912 | AZ7: -0.60413934 | BA7: -0.61544009 | BB7: -0.62355264 | BC7: -0.64473974 | BD7: -0.64845529 | BE7: -0.77384649 | BF7: -0.83429222 | BG7: -0.83595474 | BH7: -0.80812582 | BI7: -0.77624587 | BJ7: -0.73371927 | BK7: -0.72605905 | BL7: -0.7281608 | BM7: -0.72856755 | BN7: -0.75102133 | BO7: -0.76446804 | BP7: -0.76301353 | BQ7: -0.74522442 | BR7: -0.73602915 | BS7: -0.73909127 | BT7: -0.72919469 | BU7: -0.70104418 | BV7: -0.70428892 | BW7: -0.71567549 | BX7: -0.73896167 | BY7: -0.73307845 | BZ7: -0.77409725 | CA7: -0.79365954 | CB7: -0.73992232 | CC7: -0.78994621 | CD7: -0.75142737 | CE7: -0.75780321 | CF7: -0.75395939 | CG7: -0.78087605 | CH7: -0.75945105 | CI7: -0.70369401 | CJ7: -0.6944246 | CK7: -0.70177372 | CL7: -0.72905376 | CM7: -0.70770711 | CN7: -0.73286389 | CO7: -0.6770953 | CP7: -0.65332922 | CQ7: -0.65337138 | CR7: -0.6345804 | CS7: -0.65619469 | CT7: -0.62547107 | CU7: -0.62121376 | CV7: -0.64838655 | CW7: -0.67813501 | CX7: -0.74747984 | CY7: -0.75058903 | CZ7: -0.72462684 | DA7: -0.87793711 | DB7: -0.66037752 | DC7: -0.66729321 | DD7: -0.65766918 | DE7: -0.62289714 | DF7: -0.53830027 | DG7: -0.54743549 | DH7: -0.53156979 | DI7: -0.5365336 | DJ7: -0.56435636 | DK7: -0.5105232 | DL7: -0.72585246 | DM7: -0.62694106 | DN7: -0.42261979 | DO7: 0.35092242 | DP7: 0.30254993 | DQ7: 0.29039137 | DR7: 0.41620663 | DS7: 0.32763812 | DT7: 0.36746721 | DU7: 0.41156577 | DV7: 0.27073525 | DW7: 0.24355871 | DX7: 0.29236736 | DY7: 0.33497537 | DZ7: 0.97647538 | EA7: 1.0124861 | EB7: 0.20514646 | EC7: -0.035154048 | ED7: -0.35638492 | EE7: -0.53183398 | EF7: -0.55508733 | EG7: -0.59335412 | EH7: -0.71845737 | EI7: -0.89692743 | EJ7: -1.1576036 | EK7: -1.5074689 | EL7: -1.5023365 | EM7: -1.5933333 | EN7: -1.3886613 | EO7: -1.1493084 | EP7: -1.0581279 | EQ7: -0.49826262 | ER7: -0.076354015 | ES7: -0.2552953 | ET7: -0.34559061 | EU7: -0.36923289 | EV7: -0.37603669 | EW7: -0.43117238 | EX7: -0.36115502 | EY7: -0.43641658 | EZ7: -0.49842588 | FA7: -0.54036576 | FB7: -0.57140634 | FC7: -0.52781523 | FD7: -0.52924389 | FE7: -0.49339057 | FF7: -0.77498235 | FG7: -0.71330353 | FH7: -0.80828396 | FI7: -0.8792723 | FJ7: -0.79011606 | FK7: -0.78017301 | FL7: -0.74476468 | FM7: -0.75840846 | FN7: -0.77762139 | FO7: -0.72928427 | FP7: -0.67705362 | FQ7: -0.67903381 | FR7: -0.61042786 | FS7: -0.71688305 | FT7: -0.74674875 | FU7: -1.4330018 | FV7: -1.2448792 | FW7: -1.3648046 | FX7: -1.4713712 | FY7: -1.062094 | FZ7: -0.9464437 | GA7: -0.94960405 | GB7: -0.92319793 | GC7: -1.0026955 | GD7: -1.016286 | GE7: -1.0968758 | GF7: -1.0024625 | GG7: -0.9226183 | GH7: -0.93066528 | GI7: -0.86787282 | GJ7: -0.84532175 | GK7: -0.81418276 | GL7: -0.67936486 | GM7: -0.48767819 | GN7: -0.40839759 | GO7: -0.2563941 | GP7: -0.10261845 | GQ7: -0.057082967 | GR7: 0.1163646 | GS7: 0.33503335 | GT7: 0.6457636 | GU7: 0.63052182
A8: (Cartera irregular - Previsiones) / PN | B8: 18.155828 | C8: 13.263905 | D8: 0.77563013 | E8: -2.5793981 | F8: -0.90810523 | G8: -1.5534313 | H8: -1.7855542 | I8: -1.6622871 | J8: -1.6454062 | K8: -1.8395793 | L8: -1.9250425 | M8: -2.1484935 | N8: -2.2256698 | O8: -2.439986 | P8: -2.4857613 | Q8: -2.8518986 | R8: -3.0582667 | S8: -3.1938917 | T8: -3.3204855 | U8: -3.6295845 | V8: -3.6934363 | W8: -3.9008653 | X8: -4.0933571 | Y8: -4.276603 | Z8: -4.2731031 | AA8: -4.0949609 | AB8: -4.3225458 | AC8: -4.5001578 | AD8: -4.6379077 | AE8: -4.7419079 | AF8: -4.6215014 | AG8: -4.5612043 | AH8: -4.3191684 | AI8: -4.1495789 | AJ8: -4.0724164 | AK8: -3.7847582 | AL8: -3.5337451 | AM8: -3.652851 | AN8: -3.4879892 | AO8: -3.483699 | AP8: -3.4171909 | AQ8: -3.2179259 | AR8: -3.2681239 | AS8: -3.3531731 | AT8: -3.1901126 | AU8: -2.9892563 | AV8: -3.0594075 | AW8: -2.7165752 | AX8: -2.773238 | AY8: -2.7802084 | AZ8: -2.8947248 | BA8: -2.9554289 | BB8: -2.9944254 | BC8: -3.0718347 | BD8: -3.1031241 | BE8: -3.719245 | BF8: -3.7737975 | BG8: -3.7012666 | BH8: -3.5197463 | BI8: -3.3528057 | BJ8: -3.1073755 | BK8: -3.0824866 | BL8: -3.0303351 | BM8: -2.9891261 | BN8: -3.072861 | BO8: -3.1106203 | BP8: -3.0978171 | BQ8: -3.0625498 | BR8: -2.9565389 | BS8: -2.933456 | BT8: -2.9190091 | BU8: -2.829735 | BV8: -2.8575596 | BW8: -2.9461362 | BX8: -3.0050227 | BY8: -2.9855808 | BZ8: -3.1279047 | CA8: -3.2233055 | CB8: -3.0344959 | CC8: -3.2734718 | CD8: -3.0518708 | CE8: -3.0068602 | CF8: -2.9520965 | CG8: -3.1033314 | CH8: -2.9870015 | CI8: -2.7454759 | CJ8: -2.6804816 | CK8: -2.7072544 | CL8: -2.8301893 | CM8: -2.7622954 | CN8: -2.9104243 | CO8: -2.73678 | CP8: -2.6296495 | CQ8: -2.604343 | CR8: -2.5168174 | CS8: -2.6384976 | CT8: -2.5381914 | CU8: -2.5219293 | CV8: -2.637491 | CW8: -2.7971931 | CX8: -3.1455836 | CY8: -3.2096777 | CZ8: -3.1434759 | DA8: -3.901756 | DB8: -2.6411703 | DC8: -2.6638942 | DD8: -2.7100779 | DE8: -2.6211338 | DF8: -2.357568 | DG8: -2.4170975 | DH8: -2.3202212 | DI8: -2.4472688 | DJ8: -2.5079617 | DK8: -2.1506147 | DL8: -3.097009 | DM8: -2.5135165 | DN8: -1.6316128 | DO8: 1.3261962 | DP8: 1.1608334 | DQ8: 1.1371315 | DR8: 1.6058431 | DS8: 1.2148387 | DT8: 1.3303854 | DU8: 1.6251907 | DV8: 0.98286332 | DW8: 0.87913015 | DX8: 1.0164831 | DY8: 1.1160921 | DZ8: 2.5487306 | EA8: 2.610645 | EB8: 0.53016198 | EC8: -0.09088994 | ED8: -0.90329582 | EE8: -1.3394827 | EF8: -1.3720278 | EG8: -1.4227712 | EH8: -1.7016898 | EI8: -2.1189693 | EJ8: -2.7193459 | EK8: -3.4979153 | EL8: -3.3794801 | EM8: -3.5128082 | EN8: -2.9873801 | EO8: -2.445161 | EP8: -2.2183326 | EQ8: -1.0396283 | ER8: -0.15685482 | ES8: -0.51844549 | ET8: -0.70041549 | EU8: -0.75296572 | EV8: -0.78120958 | EW8: -0.89768477 | EX8: -0.72465323 | EY8: -0.8638254 | EZ8: -0.96263939 | FA8: -1.0263318 | FB8: -1.0825994 | FC8: -1.0128146 | FD8: -0.97765007 | FE8: -0.87695804 | FF8: -1.3155988 | FG8: -1.1901395 | FH8: -1.3357691 | FI8: -1.4137409 | FJ8: -1.2273244 | FK8: -1.186243 | FL8: -1.1410038 | FM8: -1.2091581 | FN8: -1.2190275 | FO8: -1.1313418 | FP8: -1.0256725 | FQ8: -1.0031907 | FR8: -0.86186786 | FS8: -1.0027617 | FT8: -0.94813896 | FU8: -1.5549217 | FV8: -1.2395338 | FW8: -1.2773354 | FX8: -1.3378303 | FY8: -0.94476588 | FZ8: -0.94424879 | GA8: -1.023251 | GB8: -1.059917 | GC8: -1.2134973 | GD8: -1.3109138 | GE8: -1.5210765 | GF8: -1.4504104 | GG8: -1.4378671 | GH8: -1.4731239 | GI8: -1.430536 | GJ8: -1.4589261 | GK8: -1.4471746 | GL8: -1.2587833 | GM8: -0.9679346 | GN8: -0.84336999 | GO8: -0.54891117 | GP8: -0.22659579 | GQ8: -0.12102287 | GR8: 0.24882098 | GS8: 0.72518682 | GT8: 1.3709465 | GU8: 1.3124861
A9: Al sector privado no financiero | B9: 38.63356 | C9: 33.483545 | D9: 18.556685 | E9: 7.6066468 | F9: 4.4565435 | G9: 3.2418579 | H9: 3.1083847 | I9: 3.4668283 | J9: 3.509483 | K9: 3.4146482 | L9: 3.2835899 | M9: 3.1331575 | N9: 3.0736082 | O9: 2.8863323 | P9: 2.8307834 | Q9: 2.7431277 | R9: 2.5277204 | S9: 2.4126157 | T9: 2.2823394 | U9: 2.1170229 | V9: 2.0371113 | W9: 1.9558797 | X9: 1.8639643 | Y9: 1.8002323 | Z9: 1.7508362 | AA9: 1.6780152 | AB9: 1.6130688 | AC9: 1.5577688 | AD9: 1.4287378 | AE9: 1.4209001 | AF9: 1.3898258 | AG9: 1.3955984 | AH9: 1.4728128 | AI9: 1.5166172 | AJ9: 1.5496389 | AK9: 1.6364738 | AL9: 1.721243 | AM9: 1.6623538 | AN9: 1.7162556 | AO9: 1.7341852 | AP9: 1.7189325 | AQ9: 1.7747571 | AR9: 1.7470838 | AS9: 1.7345487 | AT9: 1.7853027 | AU9: 1.8516412 | AV9: 1.8192052 | AW9: 1.8842359 | AX9: 1.9182132 | AY9: 1.9107199 | AZ9: 1.8979216 | BA9: 1.8783169 | BB9: 1.8235728 | BC9: 1.7975155 | BD9: 1.7582741 | BE9: 1.7325824 | BF9: 1.7601537 | BG9: 1.8020389 | BH9: 1.8536536 | BI9: 1.9181711 | BJ9: 2.0374395 | BK9: 2.0157531 | BL9: 2.0338288 | BM9: 2.0878134 | BN9: 2.026998 | BO9: 2.0343603 | BP9: 2.0286348 | BQ9: 1.9900644 | BR9: 2.0142078 | BS9: 1.9997715 | BT9: 1.9920657 | BU9: 2.0578168 | BV9: 2.0333923 | BW9: 1.9466594 | BX9: 1.8882499 | BY9: 1.8347257 | BZ9: 1.7653617 | CA9: 1.6863372 | CB9: 1.7289317 | CC9: 1.7368418 | CD9: 1.782455 | CE9: 1.812754 | CF9: 1.8338873 | CG9: 1.8595552 | CH9: 1.8822242 | CI9: 1.9107531 | CJ9: 1.9391266 | CK9: 1.9130597 | CL9: 1.8623928 | CM9: 1.8666758 | CN9: 1.8067305 | CO9: 1.8366055 | CP9: 1.9120598 | CQ9: 1.9180292 | CR9: 1.9487884 | CS9: 1.9755795 | CT9: 2.0140822 | CU9: 2.0240679 | CV9: 1.9595064 | CW9: 1.9087358 | CX9: 1.848241 | CY9: 1.8475357 | CZ9: 1.8849939 | DA9: 1.8303637 | DB9: 1.8963376 | DC9: 1.9189478 | DD9: 1.9677041 | DE9: 2.0100927 | DF9: 2.1568379 | DG9: 2.13709 | DH9: 2.2701761 | DI9: 2.2349427 | DJ9: 2.3109625 | DK9: 2.6022475 | DL9: 2.8518179 | DM9: 3.1085722 | DN9: 3.5350704 | DO9: 3.841028 | DP9: 4.0341718 | DQ9: 4.1713657 | DR9: 4.4775706 | DS9: 4.5354028 | DT9: 4.6705323 | DU9: 4.7032178 | DV9: 4.7966873 | DW9: 4.8754897 | DX9: 5.0433739 | DY9: 5.7484931 | DZ9: 6.0259373 | EA9: 6.15756 | EB9: 5.2899583 | EC9: 5.2020482 | ED9: 5.16438 | EE9: 4.9761603 | EF9: 5.0113657 | EG9: 4.7936434 | EH9: 4.5206801 | EI9: 4.2436141 | EJ9: 4.1253113 | EK9: 3.8612578 | EL9: 3.8472391 | EM9: 3.7620254 | EN9: 3.8704053 | EO9: 4.1632586 | EP9: 4.265936 | EQ9: 4.8626399 | ER9: 5.4190134 | ES9: 5.3236128 | ET9: 5.0384599 | EU9: 4.8950536 | EV9: 4.5863671 | EW9: 4.325365 | EX9: 4.3361336 | EY9: 4.1951623 | EZ9: 3.8971939 | FA9: 3.5641141 | FB9: 3.3692355 | FC9: 3.2268929 | FD9: 3.1265686 | FE9: 3.1383325 | FF9: 3.1054381 | FG9: 3.0885359 | FH9: 3.034209 | FI9: 3.1348352 | FJ9: 3.2085158 | FK9: 3.1899723 | FL9: 3.1889828 | FM9: 3.0692125 | FN9: 3.0400146 | FO9: 3.0450177 | FP9: 3.0608923 | FQ9: 3.1518446 | FR9: 3.0214517 | FS9: 2.8153592 | FT9: 2.6547149 | FU9: 3.6544321 | FV9: 3.5133412 | FW9: 1.914109 | FX9: 1.8637448 | FY9: 1.8393846 | FZ9: 1.8406615 | GA9: 1.7714306 | GB9: 1.6781996 | GC9: 1.6048736 | GD9: 1.57237 | GE9: 1.4942636 | GF9: 1.5053276 | GG9: 1.5429641 | GH9: 1.6303242 | GI9: 1.7733252 | GJ9: 1.9658225 | GK9: 2.1881766 | GL9: 2.5806095 | GM9: 2.9094545 | GN9: 3.1871426 | GO9: 3.7218179 | GP9: 4.1560916 | GQ9: 4.5476633 | GR9: 5.2256542 | GS9: 5.546394 | GT9: 6.3506802 | GU9: 6.7064499
A10: Previsiones / Cartera irregular | B10: 73.835066 | C10: 79.037687 | D10: 96.900905 | E10: 114.84857 | F10: 107.60644 | G10: 114.43452 | H10: 116.37087 | I10: 111.76157 | J10: 111.94667 | K10: 114.41764 | L10: 115.871 | M10: 117.98686 | N10: 117.55463 | O10: 120.88558 | P10: 122.0713 | Q10: 126.4298 | R10: 130.74371 | S10: 133.69657 | T10: 136.84794 | U10: 142.77998 | V10: 145.46414 | W10: 149.66915 | X10: 152.90501 | Y10: 155.79452 | Z10: 156.29417 | AA10: 154.95863 | AB10: 159.37768 | AC10: 163.36076 | AD10: 169.29334 | AE10: 171.49446 | AF10: 171.82015 | AG10: 171.15996 | AH10: 163.77164 | AI10: 159.73189 | AJ10: 157.89429 | AK10: 150.94703 | AL10: 145.18982 | AM10: 148.30629 | AN10: 144.99016 | AO10: 144.25848 | AP10: 144.00911 | AQ10: 139.61977 | AR10: 140.65041 | AS10: 140.96235 | AT10: 138.33303 | AU10: 134.9404 | AV10: 136.66968 | AW10: 133.30689 | AX10: 131.26903 | AY10: 131.01016 | AZ10: 133.07738 | BA10: 134.11195 | BB10: 135.63627 | BC10: 137.51608 | BD10: 138.7897 | BE10: 147.75928 | BF10: 150.66325 | BG10: 149.67779 | BH10: 146.60735 | BI10: 143.13853 | BJ10: 138.26274 | BK10: 138.31798 | BL10: 138.03675 | BM10: 137.07232 | BN10: 139.43213 | BO10: 139.91987 | BP10: 139.82902 | BQ10: 139.66192 | BR10: 138.72328 | BS10: 139.00423 | BT10: 139.153 | BU10: 136.34444 | BV10: 136.90745 | BW10: 139.04175 | BX10: 141.35285 | BY10: 142.52613 | BZ10: 146.11678 | CA10: 149.4142 | CB10: 144.67362 | CC10: 148.43797 | CD10: 145.50082 | CE10: 145.53242 | CF10: 144.1459 | CG10: 141.27311 | CH10: 139.34979 | CI10: 136.7083 | CJ10: 136.08383 | CK10: 136.02252 | CL10: 137.38096 | CM10: 136.56089 | CN10: 139.53883 | CO10: 136.93275 | CP10: 134.43032 | CQ10: 134.54915 | CR10: 131.91753 | CS10: 133.31502 | CT10: 131.24024 | CU10: 130.97441 | CV10: 133.529 | CW10: 136.1545 | CX10: 139.99281 | CY10: 139.9439 | CZ10: 137.68733 | DA10: 138.84958 | DB10: 135.63491 | DC10: 135.56698 | DD10: 134.19043 | DE10: 131.63911 | DF10: 125.39281 | DG10: 126.05815 | DH10: 123.76682 | DI10: 124.34706 | DJ10: 124.7783 | DK10: 119.83457 | DL10: 126.0636 | DM10: 120.57718 | DN10: 112.01989 | DO10: 98.076277 | DP10: 99.242305 | DQ10: 99.554972 | DR10: 96.705057 | DS10: 98.911012 | DT10: 97.968775 | DU10: 96.404118 | DV10: 99.795133 | DW10: 100.2915 | DX10: 99.330788 | DY10: 98.549104 | DZ10: 87.366575 | EA10: 86.929389 | EB10: 100.97221 | EC10: 105.76266 | ED10: 112.22641 | EE10: 116.29065 | EF10: 116.47204 | EG10: 118.70968 | EH10: 126.78725 | EI10: 132.46495 | EJ10: 139.83357 | EK10: 151.28614 | EL10: 151.74035 | EM10: 155.49458 | EN10: 148.28083 | EO10: 138.7824 | EP10: 135.30749 | EQ10: 118.80883 | ER10: 108.66681 | ES10: 108.35053 | ET10: 110.63473 | EU10: 111.32415 | EV10: 112.1128 | EW10: 114.04322 | EX10: 112.27395 | EY10: 113.78469 | EZ10: 116.32788 | FA10: 118.76628 | FB10: 120.78972 | FC10: 120.1602 | FD10: 120.5714 | FE10: 119.37667 | FF10: 128.8709 | FG10: 126.76561 | FH10: 130.25016 | FI10: 131.09007 | FJ10: 127.46978 | FK10: 127.23451 | FL10: 125.81004 | FM10: 127.04044 | FN10: 127.84899 | FO10: 126.22638 | FP10: 124.13972 | FQ10: 123.32209 | FR10: 121.76794 | FS10: 127.87901 | FT10: 129.5287 | FU10: 140.97879 | FV10: 137.09144 | FW10: 183.04407 | FX10: 190.23332 | FY10: 167.3801 | FZ10: 160.19268 | GA10: 161.57018 | GB10: 162.9712 | GC10: 170.16977 | GD10: 172.01026 | GE10: 180.89559 | GF10: 173.34064 | GG10: 165.80627 | GH10: 162.84002 | GI10: 153.78276 | GJ10: 147.42528 | GK10: 141.13974 | GL10: 129.28881 | GM10: 118.87431 | GN10: 114.65894 | GO10: 108.05924 | GP10: 101.91645 | GQ10: 100.93839 | GR10: 97.223239 | GS10: 93.257916 | GT10: 89.203483 | GU10: 90.007191
A11: (Cartera irregular - Previsiones) / Financiaciones | B11: 10.108446 | C11: 7.0189256 | D11: 0.57508928 | E11: -1.1294786 | F11: -0.3389841 | G11: -0.46794653 | H11: -0.50886956 | I11: -0.40775348 | J11: -0.41926639 | K11: -0.49231158 | L11: -0.52113851 | M11: -0.56355651 | N11: -0.53956049 | O11: -0.6028273 | P11: -0.6247908 | Q11: -0.72500322 | R11: -0.77711505 | S11: -0.81296873 | T11: -0.84099512 | U11: -0.90566203 | V11: -0.92615514 | W11: -0.97146882 | X11: -0.98613041 | Y11: -1.0044309 | Z11: -0.98561876 | AA11: -0.92221418 | AB11: -0.95780288 | AC11: -0.98701409 | AD11: -0.99002014 | AE11: -1.0158649 | AF11: -0.99817503 | AG11: -0.99310722 | AH11: -0.93923684 | AI11: -0.90590411 | AJ11: -0.89715239 | AK11: -0.83373484 | AL11: -0.7778267 | AM11: -0.80302147 | AN11: -0.7721462 | AO11: -0.76752393 | AP11: -0.75648688 | AQ11: -0.70315474 | AR11: -0.71019674 | AS11: -0.71051197 | AT11: -0.68436057 | AU11: -0.64697082 | AV11: -0.66709675 | AW11: -0.62758037 | AX11: -0.59980668 | AY11: -0.59251728 | AZ11: -0.62778264 | BA11: -0.64073056 | BB11: -0.64985337 | BC11: -0.67435739 | BD11: -0.6820292 | BE11: -0.82746882 | BF11: -0.89175112 | BG11: -0.89521308 | BH11: -0.86393882 | BI11: -0.8274708 | BJ11: -0.77958012 | BK11: -0.77239588 | BL11: -0.77360248 | BM11: -0.7740008 | BN11: -0.79928847 | BO11: -0.81211407 | BP11: -0.80798533 | BQ11: -0.78929774 | BR11: -0.77996728 | BS11: -0.77999549 | BT11: -0.77995356 | BU11: -0.74790205 | BV11: -0.75047316 | BW11: -0.76000982 | BX11: -0.78084524 | BY11: -0.7802379 | BZ11: -0.81412804 | CA11: -0.83329007 | CB11: -0.77237629 | CC11: -0.84129086 | CD11: -0.81103171 | CE11: -0.82539072 | CF11: -0.80958613 | CG11: -0.76749625 | CH11: -0.74065118 | CI11: -0.701405 | CJ11: -0.69971108 | CK11: -0.6891324 | CL11: -0.69618023 | CM11: -0.68247322 | CN11: -0.71436004 | CO11: -0.67830899 | CP11: -0.65832831 | CQ11: -0.66266274 | CR11: -0.62200517 | CS11: -0.65816479 | CT11: -0.62920422 | CU11: -0.62694318 | CV11: -0.65700296 | CW11: -0.6900939 | CX11: -0.73916349 | CY11: -0.73797776 | CZ11: -0.71040381 | DA11: -0.71108861 | DB11: -0.67575817 | DC11: -0.68251179 | DD11: -0.67276658 | DE11: -0.63597548 | DF11: -0.54768174 | DG11: -0.55688608 | DH11: -0.53954871 | DI11: -0.54414294 | DJ11: -0.57261721 | DK11: -0.51614465 | DL11: -0.74328631 | DM11: -0.63965646 | DN11: -0.42491154 | DO11: 0.073890742 | DP11: 0.030566722 | DQ11: 0.018563726 | DR11: 0.14753342 | DS11: 0.049389994 | DT11: 0.094869041 | DU11: 0.16912215 | DV11: 0.009826835 | DW11: -0.01421202 | DX11: 0.033750862 | DY11: 0.083404631 | DZ11: 0.76128229 | EA11: 0.80483071 | EB11: -0.051429257 | EC11: -0.29977649 | ED11: -0.63141815 | EE11: -0.81064863 | EF11: -0.82547424 | EG11: -0.89687515 | EH11: -1.2109657 | EI11: -1.3776872 | EJ11: -1.643259 | EK11: -1.98029 | EL11: -1.9905748 | EM11: -2.0877203 | EN11: -1.8686639 | EO11: -1.6146116 | EP11: -1.506195 | EQ11: -0.91460591 | ER11: -0.46965552 | ES11: -0.44454986 | ET11: -0.53582675 | EU11: -0.55432326 | EV11: -0.55553747 | EW11: -0.60742046 | EX11: -0.53221506 | EY11: -0.57829027 | EZ11: -0.63632925 | FA11: -0.66885159 | FB11: -0.70045473 | FC11: -0.650548 | FD11: -0.64317904 | FE11: -0.60810438 | FF11: -0.89656805 | FG11: -0.82666548 | FH11: -0.91785296 | FI11: -0.97462261 | FJ11: -0.88137231 | FK11: -0.86877319 | FL11: -0.82307781 | FM11: -0.8299286 | FN11: -0.84661324 | FO11: -0.79859789 | FP11: -0.73889073 | FQ11: -0.73507606 | FR11: -0.6577079 | FS11: -0.78489438 | FT11: -0.78390286 | FU11: -1.4975421 | FV11: -1.3031489 | FW11: -1.589554 | FX11: -1.6817188 | FY11: -1.2393793 | FZ11: -1.1079434 | GA11: -1.090673 | GB11: -1.0567825 | GC11: -1.126136 | GD11: -1.1322677 | GE11: -1.2087935 | GF11: -1.1040168 | GG11: -1.0153671 | GH11: -1.024496 | GI11: -0.95374327 | GJ11: -0.93229689 | GK11: -0.90021008 | GL11: -0.7558299 | GM11: -0.54913936 | GN11: -0.46720126 | GO11: -0.29995012 | GP11: -0.079649402 | GQ11: -0.042674985 | GR11: 0.14510394 | GS11: 0.37394253 | GT11: 0.68565224 | GU11: 0.6701627
A12: (Cartera irregular - Previsiones) / PN | B12: 16.634448 | C12: 11.53376 | D12: 1.0641854 | E12: -2.4893468 | F12: -0.84209778 | G12: -1.4714229 | H12: -1.711562 | I12: -1.2731333 | J12: -1.2937752 | K12: -1.5010794 | L12: -1.5975861 | M12: -1.8177849 | N12: -1.8136579 | O12: -2.0324217 | P12: -2.0883288 | Q12: -2.4424971 | R12: -2.6593351 | S12: -2.8038148 | T12: -2.9386097 | U12: -3.2476264 | V12: -3.3178174 | W12: -3.5285993 | X12: -3.7124945 | Y12: -3.8957328 | Z12: -3.8959782 | AA12: -3.7238968 | AB12: -3.9444238 | AC12: -4.1295671 | AD12: -4.2672066 | AE12: -4.3802008 | AF12: -4.3100521 | AG12: -4.2597234 | AH12: -3.9914072 | AI12: -3.8265913 | AJ12: -3.7559373 | AK12: -3.4767493 | AL12: -3.238211 | AM12: -3.3580377 | AN12: -3.2026893 | AO12: -3.2025232 | AP12: -3.1421667 | AQ12: -2.9496763 | AR12: -3.0078872 | AS12: -3.0921232 | AT12: -2.9371292 | AU12: -2.7381949 | AV12: -2.8156949 | AW12: -2.6521047 | AX12: -2.5334219 | AY12: -2.543465 | AZ12: -2.6679708 | BA12: -2.7328059 | BB12: -2.776007 | BC12: -2.8624914 | BD12: -2.8956678 | BE12: -3.5182176 | BF12: -3.5840596 | BG12: -3.5154309 | BH12: -3.3422396 | BI12: -3.17565 | BJ12: -2.9344319 | BK12: -2.9154019 | BL12: -2.8683006 | BM12: -2.8319051 | BN12: -2.9212832 | BO12: -2.9632294 | BP12: -2.9538301 | BQ12: -2.9205903 | BR12: -2.818579 | BS12: -2.8013157 | BT12: -2.7899365 | BU12: -2.704619 | BV12: -2.7320537 | BW12: -2.8183146 | BX12: -2.8836291 | BY12: -2.8994552 | BZ12: -3.0083858 | CA12: -3.105416 | CB12: -2.9160567 | CC12: -3.1590618 | CD12: -2.9976295 | CE12: -2.9594059 | CF12: -2.8439076 | CG12: -2.7353547 | CH12: -2.6193284 | CI12: -2.4634127 | CJ12: -2.4352746 | CK12: -2.5019169 | CL12: -2.5402182 | CM12: -2.512293 | CN12: -2.6748512 | CO12: -2.5378219 | CP12: -2.4552624 | CQ12: -2.4607643 | CR12: -2.3026719 | CS12: -2.4742917 | CT12: -2.3919197 | CU12: -2.3821062 | CV12: -2.5049748 | CW12: -2.6727328 | CX12: -2.9241901 | CY12: -2.9745002 | CZ12: -2.9074953 | DA12: -2.9939978 | DB12: -2.5708985 | DC12: -2.5943959 | DD12: -2.640776 | DE12: -2.547 | DF12: -2.2730758 | DG12: -2.3325043 | DH12: -2.2336634 | DI12: -2.3589492 | DJ12: -2.4219083 | DK12: -2.0691953 | DL12: -3.020434 | DM12: -2.4400031 | DN12: -1.5622465 | DO12: 0.2657395 | DP12: 0.11203664 | DQ12: 0.069379083 | DR12: 0.544759 | DS12: 0.17569493 | DT12: 0.32825812 | DU12: 0.63823773 | DV12: 0.034025696 | DW12: -0.048432775 | DX12: 0.1113224 | DY12: 0.2625902 | DZ12: 1.8789586 | EA12: 1.9617781 | EB12: -0.12560312 | EC12: -0.74050843 | ED12: -1.5311351 | EE12: -1.9526105 | EF12: -1.9543288 | EG12: -2.063167 | EH12: -2.7519157 | EI12: -3.129523 | EJ12: -3.7063377 | EK12: -4.4329799 | EL12: -4.2930816 | EM12: -4.4073286 | EN12: -3.8525448 | EO12: -3.2831899 | EP12: -3.0239343 | EQ12: -1.8266006 | ER12: -0.9222044 | ES12: -0.86619794 | ET12: -1.0421597 | EU12: -1.0853921 | EV12: -1.103271 | EW12: -1.207957 | EX12: -1.0258371 | EY12: -1.0969676 | EZ12: -1.1797018 | FA12: -1.2197196 | FB12: -1.2756629 | FC12: -1.1986292 | FD12: -1.145318 | FE12: -1.0409048 | FF12: -1.4638344 | FG12: -1.328278 | FH12: -1.4624294 | FI12: -1.510424 | FJ12: -1.3246289 | FK12: -1.2780292 | FL12: -1.2195196 | FM12: -1.2807061 | FN12: -1.2855279 | FO12: -1.190817 | FP12: -1.0812036 | FQ12: -1.0467935 | FR12: -0.89471679 | FS12: -1.0427271 | FT12: -0.96303636 | FU12: -1.5655692 | FV12: -1.2507503 | FW12: -1.4323723 | FX12: -1.472784 | FY12: -1.0619784 | FZ12: -1.0613653 | GA12: -1.127361 | GB12: -1.1686421 | GC12: -1.3108303 | GD12: -1.4043207 | GE12: -1.6115834 | GF12: -1.5382149 | GG12: -1.52392 | GH12: -1.5618558 | GI12: -1.5134209 | GJ12: -1.5487473 | GK12: -1.5405566 | GL12: -1.3463125 | GM12: -1.0437008 | GN12: -0.92628956 | GO12: -0.61590891 | GP12: -0.16871903 | GQ12: -0.087036555 | GR12: 0.2970586 | GS12: 0.77196596 | GT12: 1.387712 | GU12: 1.329267
A13: Fuente: BCRA
A18: Bancos privados
A19: En porcentaje | B19: 37591 | C19: 37956 | D19: 38322 | E19: 38687 | F19: 39052 | G19: 39417 | H19: 39783 | I19: 40148 | J19: 40179 | K19: 40210 | L19: 40238 | M19: 40269 | N19: 40299 | O19: 40330 | P19: 40360 | Q19: 40391 | R19: 40422 | S19: 40452 | T19: 40483 | U19: 40513 | V19: 40544 | W19: 40575 | X19: 40603 | Y19: 40634 | Z19: 40664 | AA19: 40695 | AB19: 40725 | AC19: 40756 | AD19: 40787 | AE19: 40817 | AF19: 40848 | AG19: 40878 | AH19: 40909 | AI19: 40940 | AJ19: 40969 | AK19: 41000 | AL19: 41030 | AM19: 41061 | AN19: 41091 | AO19: 41122 | AP19: 41153 | AQ19: 41183 | AR19: 41214 | AS19: 41244 | AT19: 41275 | AU19: 41306 | AV19: 41334 | AW19: 41365 | AX19: 41395 | AY19: 41426 | AZ19: 41456 | BA19: 41487 | BB19: 41518 | BC19: 41548 | BD19: 41579 | BE19: 41609 | BF19: 41640 | BG19: 41671 | BH19: 41699 | BI19: 41730 | BJ19: 41760 | BK19: 41791 | BL19: 41821 | BM19: 41852 | BN19: 41883 | BO19: 41913 | BP19: 41944 | BQ19: 41974 | BR19: 42005 | BS19: 42036 | BT19: 42064 | BU19: 42095 | BV19: 42125 | BW19: 42156 | BX19: 42186 | BY19: 42217 | BZ19: 42248 | CA19: 42278 | CB19: 42309 | CC19: 42339 | CD19: 42370 | CE19: 42401 | CF19: 42430 | CG19: 42461 | CH19: 42491 | CI19: 42522 | CJ19: 42552 | CK19: 42583 | CL19: 42614 | CM19: 42644 | CN19: 42675 | CO19: 42705 | CP19: 42736 | CQ19: 42767 | CR19: 42795 | CS19: 42826 | CT19: 42856 | CU19: 42887 | CV19: 42917 | CW19: 42948 | CX19: 42979 | CY19: 43009 | CZ19: 43040 | DA19: 43070 | DB19: 43101 | DC19: 43132 | DD19: 43160 | DE19: 43191 | DF19: 43221 | DG19: 43252 | DH19: 43282 | DI19: 43313 | DJ19: 43344 | DK19: 43374 | DL19: 43405 | DM19: 43435 | DN19: 43466 | DO19: 43497 | DP19: 43525 | DQ19: 43556 | DR19: 43586 | DS19: 43617 | DT19: 43647 | DU19: 43678 | DV19: 43709 | DW19: 43739 | DX19: 43770 | DY19: 43800 | DZ19: 43831 | EA19: 43862 | EB19: 43891 | EC19: 43922 | ED19: 43952 | EE19: 43983 | EF19: 44013 | EG19: 44044 | EH19: 44075 | EI19: 44105 | EJ19: 44136 | EK19: 44166 | EL19: 44197 | EM19: 44228 | EN19: 44256 | EO19: 44287 | EP19: 44317 | EQ19: 44348 | ER19: 44378 | ES19: 44409 | ET19: 44440 | EU19: 44470 | EV19: 44501 | EW19: 44531 | EX19: 44562 | EY19: 44593 | EZ19: 44621 | FA19: 44652 | FB19: 44682 | FC19: 44713 | FD19: 44743 | FE19: 44774 | FF19: 44805 | FG19: 44835 | FH19: 44866 | FI19: 44896 | FJ19: 44927 | FK19: 44958 | FL19: 44986 | FM19: 45017 | FN19: 45047 | FO19: 45078 | FP19: 45108 | FQ19: 45139 | FR19: 45170 | FS19: 45200 | FT19: 45231 | FU19: 45261 | FV19: 45292 | FW19: 45323 | FX19: 45352 | FY19: 45383 | FZ19: 45413 | GA19: 45444 | GB19: 45474 | GC19: 45505 | GD19: 45536 | GE19: 45566 | GF19: 45597 | GG19: 45627 | GH19: 45658 | GI19: 45689 | GJ19: 45717 | GK19: 45748 | GL19: 45778 | GM19: 45809 | GN19: 45839 | GO19: 45870 | GP19: 45901 | GQ19: 45931 | GR19: 45962 | GS19: 45992 | GT19: 46023 | GU19: 46054
A20: Cartera irregular total | B20: 19.800766 | C20: 15.70533 | D20: 8.8706643 | E20: 4.4307483 | F20: 2.9167146 | G20: 2.2025977 | H20: 2.5301599 | I20: 3.0927384 | J20: 3.1738511 | K20: 3.1020812 | L20: 2.9538762 | M20: 2.8204168 | N20: 2.7202349 | O20: 2.6261991 | P20: 2.588311 | Q20: 2.5043414 | R20: 2.2801886 | S20: 2.2053333 | T20: 2.0842876 | U20: 1.9074514 | V20: 1.807094 | W20: 1.7508555 | X20: 1.6642421 | Y20: 1.6169071 | Z20: 1.5799472 | AA20: 1.5178769 | AB20: 1.4502558 | AC20: 1.4148043 | AD20: 1.3224862 | AE20: 1.3251476 | AF20: 1.3073411 | AG20: 1.3332553 | AH20: 1.4236265 | AI20: 1.4873077 | AJ20: 1.5122605 | AK20: 1.6256052 | AL20: 1.7215818 | AM20: 1.6278712 | AN20: 1.6930727 | AO20: 1.7325294 | AP20: 1.6699798 | AQ20: 1.755611 | AR20: 1.7221305 | AS20: 1.7080054 | AT20: 1.7884589 | AU20: 1.8735504 | AV20: 1.8091671 | AW20: 1.8566453 | AX20: 1.8977721 | AY20: 1.886866 | AZ20: 1.8955634 | BA20: 1.8886275 | BB20: 1.8215028 | BC20: 1.8029236 | BD20: 1.7401956 | BE20: 1.6369839 | BF20: 1.6830225 | BG20: 1.7568438 | BH20: 1.7925409 | BI20: 1.8762533 | BJ20: 1.9936861 | BK20: 1.9546532 | BL20: 1.9460999 | BM20: 2.0087139 | BN20: 1.9383547 | BO20: 1.9633765 | BP20: 1.9686875 | BQ20: 1.853791 | BR20: 1.8817273 | BS20: 1.8601897 | BT20: 1.8454521 | BU20: 1.9229652 | BV20: 1.8856158 | BW20: 1.7687556 | BX20: 1.7334064 | BY20: 1.6708413 | BZ20: 1.6339986 | CA20: 1.56768 | CB20: 1.5425604 | CC20: 1.485105 | CD20: 1.5303095 | CE20: 1.5479501 | CF20: 1.5451247 | CG20: 1.5852847 | CH20: 1.5997731 | CI20: 1.6093658 | CJ20: 1.6094871 | CK20: 1.6301997 | CL20: 1.5760346 | CM20: 1.5979629 | CN20: 1.5601704 | CO20: 1.5080251 | CP20: 1.5969689 | CQ20: 1.6610633 | CR20: 1.7027313 | CS20: 1.7816063 | CT20: 1.800751 | CU20: 1.814342 | CV20: 1.7456136 | CW20: 1.71402 | CX20: 1.6691125 | CY20: 1.7035114 | CZ20: 1.7576801 | DA20: 1.7166548 | DB20: 1.8073982 | DC20: 1.8432753 | DD20: 1.9312842 | DE20: 1.9492752 | DF20: 2.0827037 | DG20: 2.0574106 | DH20: 2.2340174 | DI20: 2.1756702 | DJ20: 2.2648176 | DK20: 2.7041809 | DL20: 2.9569647 | DM20: 3.0245732 | DN20: 3.3827182 | DO20: 3.6994372 | DP20: 3.8395135 | DQ20: 3.9518682 | DR20: 4.1418993 | DS20: 4.1878882 | DT20: 4.2923843 | DU20: 4.2208759 | DV20: 4.2514444 | DW20: 4.2827416 | DX20: 4.4874638 | DY20: 4.3115847 | DZ20: 4.6264977 | EA20: 4.7448273 | EB20: 3.7715623 | EC20: 3.622657 | ED20: 3.571831 | EE20: 3.2477866 | EF20: 3.1677877 | EG20: 2.9326878 | EH20: 2.7040148 | EI20: 2.4479526 | EJ20: 2.3483201 | EK20: 2.1786372 | EL20: 2.125663 | EM20: 2.0379657 | EN20: 2.2254916 | EO20: 2.6230938 | EP20: 2.7794053 | EQ20: 3.1840411 | ER20: 3.7114563 | ES20: 3.6524709 | ET20: 3.3906951 | EU20: 3.2639234 | EV20: 2.9835603 | EW20: 2.76103 | EX20: 2.7988598 | EY20: 2.6883978 | EZ20: 2.3841468 | FA20: 2.1906862 | FB20: 1.9854994 | FC20: 1.8425227 | FD20: 1.7440293 | FE20: 1.7285594 | FF20: 1.6943616 | FG20: 1.7102555 | FH20: 1.6827499 | FI20: 1.7605935 | FJ20: 1.8471079 | FK20: 1.8310158 | FL20: 1.8714771 | FM20: 1.8138808 | FN20: 1.7845041 | FO20: 1.7428663 | FP20: 1.7915985 | FQ20: 1.7221326 | FR20: 1.6892004 | FS20: 1.6088791 | FT20: 1.5265913 | FU20: 1.5448219 | FV20: 1.503632 | FW20: 1.4277124 | FX20: 1.3940211 | FY20: 1.4042004 | FZ20: 1.4686032 | GA20: 1.4110553 | GB20: 1.4286428 | GC20: 1.4192137 | GD20: 1.4166821 | GE20: 1.3582005 | GF20: 1.3620323 | GG20: 1.4909082 | GH20: 1.5947045 | GI20: 1.7541036 | GJ20: 1.9395867 | GK20: 2.1749846 | GL20: 2.5422819 | GM20: 2.8979518 | GN20: 3.1765856 | GO20: 3.7741098 | GP20: 4.1238194 | GQ20: 4.4727158 | GR20: 5.1109467 | GS20: 5.2835929 | GT20: 6.0622371 | GU20: 6.5198641
A21: Previsiones / Cartera irregular | B21: 71.261521 | C21: 73.047582 | D21: 89.231906 | E21: 102.68403 | F21: 114.17863 | G21: 123.38365 | H21: 118.5399 | I21: 115.90954 | J21: 114.74935 | K21: 116.4322 | L21: 117.93875 | M21: 119.8608 | N21: 120.89489 | O21: 122.35057 | P21: 123.58846 | Q21: 125.26338 | R21: 130.21808 | S21: 131.93552 | T21: 135.42119 | U21: 143.51961 | V21: 147.39811 | W21: 150.03808 | X21: 153.51516 | Y21: 156.51626 | Z21: 156.81266 | AA21: 154.92154 | AB21: 160.93094 | AC21: 164.95454 | AD21: 169.29361 | AE21: 171.52135 | AF21: 170.98686 | AG21: 168.27855 | AH21: 160.73847 | AI21: 155.08759 | AJ21: 154.54676 | AK21: 145.9736 | AL21: 140.54754 | AM21: 146.33198 | AN21: 142.84965 | AO21: 141.58311 | AP21: 144.56353 | AQ21: 138.71789 | AR21: 139.82809 | AS21: 140.01251 | AT21: 136.54971 | AU21: 132.08211 | AV21: 135.20045 | AW21: 133.58743 | AX21: 130.57527 | AY21: 130.14327 | AZ21: 132.01384 | BA21: 132.47502 | BB21: 134.37611 | BC21: 135.42574 | BD21: 138.03936 | BE21: 145.97725 | BF21: 149.22239 | BG21: 145.79653 | BH21: 143.68559 | BI21: 139.81506 | BJ21: 135.56904 | BK21: 135.786 | BL21: 137.60701 | BM21: 136.8085 | BN21: 138.9552 | BO21: 139.03655 | BP21: 138.44682 | BQ21: 141.55572 | BR21: 140.66616 | BS21: 141.30371 | BT21: 141.61938 | BU21: 138.56787 | BV21: 139.10489 | BW21: 143.32612 | BX21: 145.34188 | BY21: 145.79273 | BZ21: 149.48687 | CA21: 153.03357 | CB21: 152.93594 | CC21: 156.39974 | CD21: 153.72456 | CE21: 153.07591 | CF21: 151.78427 | CG21: 147.08614 | CH21: 145.62337 | CI21: 143.58308 | CJ21: 144.61332 | CK21: 145.1998 | CL21: 146.55371 | CM21: 144.86359 | CN21: 146.11616 | CO21: 145.01538 | CP21: 140.91191 | CQ21: 138.42727 | CR21: 134.28664 | CS21: 133.48913 | CT21: 131.81714 | CU21: 130.61426 | CV21: 133.10221 | CW21: 135.03668 | CX21: 138.31177 | CY21: 136.54388 | CZ21: 133.25602 | DA21: 132.37517 | DB21: 128.4684 | DC21: 127.49021 | DD21: 125.03324 | DE21: 123.39414 | DF21: 118.74089 | DG21: 119.25439 | DH21: 116.51069 | DI21: 118.7933 | DJ21: 119.60984 | DK21: 111.47029 | DL21: 105.04396 | DM21: 105.58002 | DN21: 102.73387 | DO21: 100.08408 | DP21: 102.50939 | DQ21: 102.8613 | DR21: 104.56277 | DS21: 107.37346 | DT21: 107.17185 | DU21: 105.60246 | DV21: 110.6218 | DW21: 113.0048 | DX21: 111.665 | DY21: 117.20888 | DZ21: 105.54707 | EA21: 104.4477 | EB21: 128.1244 | EC21: 136.51098 | ED21: 147.60787 | EE21: 157.94882 | EF21: 165.22711 | EG21: 173.77117 | EH21: 190.95721 | EI21: 205.76555 | EJ21: 211.50486 | EK21: 239.02028 | EL21: 244.19297 | EM21: 251.98362 | EN21: 223.71643 | EO21: 191.98385 | EP21: 180.67111 | EQ21: 156.8805 | ER21: 136.95245 | ES21: 136.01781 | ET21: 141.82747 | EU21: 144.50121 | EV21: 146.92035 | EW21: 151.67679 | EX21: 146.26594 | EY21: 148.78117 | EZ21: 157.16286 | FA21: 162.84774 | FB21: 169.68388 | FC21: 169.75859 | FD21: 173.14964 | FE21: 173.92757 | FF21: 180.2214 | FG21: 170.95021 | FH21: 180.62744 | FI21: 179.28201 | FJ21: 169.19723 | FK21: 170.25532 | FL21: 166.45465 | FM21: 166.91811 | FN21: 167.67368 | FO21: 168.86267 | FP21: 162.00058 | FQ21: 167.00502 | FR21: 162.26269 | FS21: 173.03344 | FT21: 179.20746 | FU21: 185.25023 | FV21: 181.7432 | FW21: 189.12343 | FX21: 186.43626 | FY21: 188.36921 | FZ21: 171.26515 | GA21: 173.2499 | GB21: 171.02425 | GC21: 177.97204 | GD21: 178.26177 | GE21: 187.71262 | GF21: 196.31315 | GG21: 178.11725 | GH21: 175.015 | GI21: 162.98308 | GJ21: 156.69963 | GK21: 148.90254 | GL21: 136.69414 | GM21: 122.84868 | GN21: 118.91193 | GO21: 110.74695 | GP21: 105.27837 | GQ21: 104.31245 | GR21: 98.301166 | GS21: 95.700571 | GT21: 91.156531 | GU21: 90.968045
A22: (Cartera irregular - Previsiones) / Financiaciones | B22: 5.6904391 | C22: 4.2329662 | D22: 0.95520146 | E22: -0.1189226 | F22: -0.41355019 | G22: -0.51504763 | H22: -0.46908903 | I22: -0.49204051 | J22: -0.46812244 | K22: -0.50974017 | L22: -0.52988857 | M22: -0.56015734 | N22: -0.56838998 | O22: -0.58697034 | P22: -0.61054274 | Q22: -0.63268127 | R22: -0.68902918 | S22: -0.70428475 | T22: -0.73827956 | U22: -0.83011538 | V22: -0.85652839 | W22: -0.87609457 | X22: -0.89062181 | Y22: -0.91381549 | Z22: -0.89761001 | AA22: -0.83364129 | AB22: -0.88365457 | AC22: -0.9189797 | AD22: -0.91639836 | AE22: -0.94776345 | AF22: -0.92804033 | AG22: -0.91032733 | AH22: -0.86468897 | AI22: -0.8193219 | AJ22: -0.82488916 | AK22: -0.74734925 | AL22: -0.6980591 | AM22: -0.75422501 | AN22: -0.72547581 | AO22: -0.72043969 | AP22: -0.74420201 | AQ22: -0.67973547 | AR22: -0.6858917 | AS22: -0.68341584 | AT22: -0.65367653 | AU22: -0.60107443 | AV22: -0.63683497 | AW22: -0.62359944 | AX22: -0.58024892 | AY22: -0.56876314 | AZ22: -0.60684259 | BA22: -0.61333218 | BB22: -0.62616187 | BC22: -0.6386991 | BD22: -0.66195932 | BE22: -0.75264015 | BF22: -0.82842398 | BG22: -0.80457353 | BH22: -0.78308205 | BI22: -0.74703145 | BJ22: -0.70913506 | BK22: -0.69949209 | BL22: -0.73187004 | BM22: -0.73937738 | BN22: -0.75508993 | BO22: -0.76643437 | BP22: -0.75689776 | BQ22: -0.77035614 | BR22: -0.76522626 | BS22: -0.76832729 | BT22: -0.76806574 | BU22: -0.74164666 | BV22: -0.73736798 | BW22: -0.76633317 | BX22: -0.78595901 | BY22: -0.76512389 | BZ22: -0.80861479 | CA22: -0.83139668 | CB22: -0.81656884 | CC22: -0.83759532 | CD22: -0.82215197 | CE22: -0.82158858 | CF22: -0.80013156 | CG22: -0.7464494 | CH22: -0.72987035 | CI22: -0.70141121 | CJ22: -0.71804567 | CK22: -0.73684707 | CL22: -0.73370266 | CM22: -0.71690351 | CN22: -0.71949068 | CO22: -0.67884319 | CP22: -0.65335044 | CQ22: -0.63830124 | CR22: -0.58380945 | CS22: -0.59664442 | CT22: -0.57294747 | CU22: -0.55544731 | CV22: -0.57783675 | CW22: -0.60053567 | CX22: -0.63946654 | CY22: -0.62252916 | CZ22: -0.58453445 | DA22: -0.55576999 | DB22: -0.51453737 | DC22: -0.50672032 | DD22: -0.483463 | DE22: -0.45601612 | DF22: -0.39031711 | DG22: -0.39614181 | DH22: -0.3688518 | DI22: -0.40888031 | DJ22: -0.44412706 | DK22: -0.3101775 | DL22: -0.14914813 | DM22: -0.16877178 | DN22: -0.092479185 | DO22: -0.0031105338 | DP22: -0.096348506 | DQ22: -0.11307468 | DR22: -0.18898513 | DS22: -0.30879242 | DT22: -0.30784324 | DU22: -0.23647301 | DV22: -0.45158006 | DW22: -0.55696186 | DX22: -0.52346283 | DY22: -0.74197532 | DZ22: -0.25663493 | EA22: -0.21103546 | EB22: -1.0607293 | EC22: -1.3226675 | ED22: -1.7004726 | EE22: -1.8820542 | EF22: -2.0662564 | EG22: -2.1634782 | EH22: -2.4594964 | EI22: -2.5890906 | EJ22: -2.6184911 | EK22: -3.0287477 | EL22: -3.0650566 | EM22: -3.097374 | EN22: -2.7532988 | EO22: -2.4128227 | EP22: -2.2421771 | EQ22: -1.8110986 | ER22: -1.3714739 | ES22: -1.3155401 | ET22: -1.418242 | EU22: -1.4524855 | EV22: -1.3998969 | EW22: -1.4268116 | EX22: -1.2949188 | EY22: -1.311432 | EZ22: -1.3628466 | FA22: -1.3767969 | FB22: -1.383573 | FC22: -1.2853179 | FD22: -1.2757512 | FE22: -1.277882 | FF22: -1.3592406 | FG22: -1.2134299 | FH22: -1.3567581 | FI22: -1.395834 | FJ22: -1.2781474 | FK22: -1.2863859 | FL22: -1.2436836 | FM22: -1.2138147 | FN22: -1.2076396 | FO22: -1.2001842 | FP22: -1.1108015 | FQ22: -1.1539153 | FR22: -1.0517416 | FS22: -1.1750198 | FT22: -1.2091742 | FU22: -1.3169642 | FV22: -1.2291169 | FW22: -1.2724262 | FX22: -1.2049397 | FY22: -1.2408807 | FZ22: -1.0466022 | GA22: -1.0335965 | GB22: -1.0146829 | GC22: -1.1065899 | GD22: -1.1087205 | GE22: -1.1913133 | GF22: -1.3118162 | GG22: -1.1646565 | GH22: -1.1962676 | GI22: -1.1047884 | GJ22: -1.0997384 | GK22: -1.0636226 | GL22: -0.93286852 | GM22: -0.66214369 | GN22: -0.60075378 | GO22: -0.40560181 | GP22: -0.21767051 | GQ22: -0.19288376 | GR22: 0.086826501 | GS22: 0.22716435 | GT22: 0.53611207 | GU22: 0.58887117
A23: (Cartera irregular - Previsiones) / PN | B23: 20.116931 | C23: 14.415951 | D23: 3.4123751 | E23: -0.41474088 | F23: -1.4385388 | G23: -2.0585914 | H23: -1.8507112 | I23: -1.7072037 | J23: -1.573621 | K23: -1.6988479 | L23: -1.7761469 | M23: -2.0222062 | N23: -2.1786631 | O23: -2.2729385 | P23: -2.3437808 | Q23: -2.4381963 | R23: -2.7049212 | S23: -2.7896687 | T23: -2.9547752 | U23: -3.4000164 | V23: -3.5142199 | W23: -3.6648584 | X23: -3.9682989 | Y23: -4.2278302 | Z23: -4.2362933 | AA23: -3.9990751 | AB23: -4.2716115 | AC23: -4.4919183 | AD23: -4.6198266 | AE23: -4.7516989 | AF23: -4.5869096 | AG23: -4.4406796 | AH23: -4.1553123 | AI23: -3.9014431 | AJ23: -3.8911414 | AK23: -3.4624385 | AL23: -3.2035364 | AM23: -3.468099 | AN23: -3.2892026 | AO23: -3.2956553 | AP23: -3.3849267 | AQ23: -3.111809 | AR23: -3.1630384 | AS23: -3.2372622 | AT23: -3.03906 | AU23: -2.7519195 | AV23: -2.9234577 | AW23: -2.8681492 | AX23: -2.6728897 | AY23: -2.6698837 | AZ23: -2.8140147 | BA23: -2.8578026 | BB23: -2.9160672 | BC23: -2.9539991 | BD23: -3.0656045 | BE23: -3.498143 | BF23: -3.6254723 | BG23: -3.4257373 | BH23: -3.299461 | BI23: -3.1231608 | BJ23: -2.9185566 | BK23: -2.9268163 | BL23: -3.0040623 | BM23: -3.002612 | BN23: -3.0711309 | BO23: -3.1020524 | BP23: -3.0858039 | BQ23: -3.1638538 | BR23: -3.0882882 | BS23: -3.1015376 | BT23: -3.100251 | BU23: -3.04517 | BV23: -3.0490188 | BW23: -3.2366274 | BX23: -3.2701592 | BY23: -3.2227442 | BZ23: -3.3851359 | CA23: -3.4763216 | CB23: -3.4638944 | CC23: -3.5821955 | CD23: -3.468879 | CE23: -3.4110427 | CF23: -3.2603171 | CG23: -3.1118106 | CH23: -3.01239 | CI23: -2.8724603 | CJ23: -2.9407943 | CK23: -3.1037114 | CL23: -3.1200818 | CM23: -3.0560715 | CN23: -3.1141967 | CO23: -3.0233649 | CP23: -2.8911613 | CQ23: -2.772642 | CR23: -2.5230783 | CS23: -2.6286711 | CT23: -2.5641279 | CU23: -2.4453353 | CV23: -2.5244678 | CW23: -2.6406691 | CX23: -2.8430397 | CY23: -2.785739 | CZ23: -2.6166057 | DA23: -2.4608123 | DB23: -2.1070411 | DC23: -2.0888628 | DD23: -1.973733 | DE23: -1.9501392 | DF23: -1.7403759 | DG23: -1.786922 | DH23: -1.6168632 | DI23: -1.9310659 | DJ23: -2.032099 | DK23: -1.3082586 | DL23: -0.62964382 | DM23: -0.67938108 | DN23: -0.3527183 | DO23: -0.011469743 | DP23: -0.35563853 | DQ23: -0.42040253 | DR23: -0.68187977 | DS23: -1.0585291 | DT23: -1.0360093 | DU23: -0.8637217 | DV23: -1.4889853 | DW23: -1.7884524 | DX23: -1.5932978 | DY23: -2.1272338 | DZ23: -0.58936128 | EA23: -0.47558705 | EB23: -2.4184208 | EC23: -3.0723705 | ED23: -3.8907066 | EE23: -4.2721835 | EF23: -4.5620606 | EG23: -4.6938774 | EH23: -5.2243054 | EI23: -5.4737117 | EJ23: -5.5393875 | EK23: -6.3081689 | EL23: -6.1554671 | EM23: -6.1013496 | EN23: -5.2762952 | EO23: -4.5665874 | EP23: -4.1990749 | EQ23: -3.3724703 | ER23: -2.4801666 | ES23: -2.3725178 | ET23: -2.5445876 | EU23: -2.6207603 | EV23: -2.5811308 | EW23: -2.6431999 | EX23: -2.3108813 | EY23: -2.3099339 | EZ23: -2.3279498 | FA23: -2.3278076 | FB23: -2.342838 | FC23: -2.2178846 | FD23: -2.1331118 | FE23: -2.0529123 | FF23: -2.0830447 | FG23: -1.8502678 | FH23: -2.0699207 | FI23: -2.0759436 | FJ23: -1.8465736 | FK23: -1.8226821 | FL23: -1.7915713 | FM23: -1.8510572 | FN23: -1.8271307 | FO23: -1.8018226 | FP23: -1.6199778 | FQ23: -1.6721303 | FR23: -1.4662195 | FS23: -1.620178 | FT23: -1.5032529 | FU23: -1.4568695 | FV23: -1.2639134 | FW23: -1.2623078 | FX23: -1.1765498 | FY23: -1.2041537 | FZ23: -1.1964772 | GA23: -1.2999687 | GB23: -1.3372898 | GC23: -1.5164016 | GD23: -1.6207741 | GE23: -1.8308611 | GF23: -2.1499643 | GG23: -2.0525579 | GH23: -2.1563394 | GI23: -2.054822 | GJ23: -2.1472269 | GK23: -2.1515259 | GL23: -1.9896541 | GM23: -1.5567428 | GN23: -1.4797945 | GO23: -1.0243865 | GP23: -0.57028964 | GQ23: -0.49140278 | GR23: 0.22375384 | GS23: 0.59530839 | GT23: 1.3573788 | GU23: 1.4378025
A24: Al sector privado no financiero | B24: 37.406255 | C24: 30.393157 | D24: 15.30508 | E24: 6.2798487 | F24: 3.5873805 | G24: 2.4735329 | H24: 2.8124526 | I24: 3.25193 | J24: 3.3390146 | K24: 3.2608204 | L24: 3.0998449 | M24: 2.9511731 | N24: 2.8432448 | O24: 2.7453573 | P24: 2.7052529 | Q24: 2.6166198 | R24: 2.3798414 | S24: 2.2993841 | T24: 2.1760137 | U24: 1.9911053 | V24: 1.8867762 | W24: 1.8254369 | X24: 1.7349915 | Y24: 1.6860504 | Z24: 1.6463552 | AA24: 1.5815257 | AB24: 1.5119732 | AC24: 1.4746466 | AD24: 1.3810244 | AE24: 1.3856785 | AF24: 1.3705568 | AG24: 1.396649 | AH24: 1.4868738 | AI24: 1.5552319 | AJ24: 1.5824392 | AK24: 1.6992707 | AL24: 1.7976166 | AM24: 1.7037225 | AN24: 1.767001 | AO24: 1.8073222 | AP24: 1.7443481 | AQ24: 1.8319962 | AR24: 1.7957808 | AS24: 1.7789097 | AT24: 1.86228 | AU24: 1.9491885 | AV24: 1.882302 | AW24: 1.9319048 | AX24: 1.9775868 | AY24: 1.969336 | AZ24: 1.9705632 | BA24: 1.9620758 | BB24: 1.8934208 | BC24: 1.8708555 | BD24: 1.8104228 | BE24: 1.7056827 | BF24: 1.7482757 | BG24: 1.8273176 | BH24: 1.8614199 | BI24: 1.9476384 | BJ24: 2.070283 | BK24: 2.0302245 | BL24: 2.0125168 | BM24: 2.075206 | BN24: 2.0031408 | BO24: 2.0219633 | BP24: 2.029573 | BQ24: 1.9084672 | BR24: 1.9376093 | BS24: 1.9116763 | BT24: 1.9004349 | BU24: 1.9779744 | BV24: 1.9421437 | BW24: 1.815518 | BX24: 1.7793529 | BY24: 1.7165308 | BZ24: 1.6775595 | CA24: 1.607929 | CB24: 1.5796087 | CC24: 1.5229132 | CD24: 1.5726126 | CE24: 1.5906765 | CF24: 1.5910164 | CG24: 1.6353168 | CH24: 1.6491485 | CI24: 1.6582736 | CJ24: 1.6602951 | CK24: 1.6833872 | CL24: 1.6313556 | CM24: 1.6494629 | CN24: 1.6122337 | CO24: 1.5631512 | CP24: 1.6549113 | CQ24: 1.7137096 | CR24: 1.7572048 | CS24: 1.8394262 | CT24: 1.8596552 | CU24: 1.8813269 | CV24: 1.8122894 | CW24: 1.7788608 | CX24: 1.7337055 | CY24: 1.7672559 | CZ24: 1.8264109 | DA24: 1.7825676 | DB24: 1.8674744 | DC24: 1.9039003 | DD24: 1.9941736 | DE24: 2.0183672 | DF24: 2.1594112 | DG24: 2.1323044 | DH24: 2.3162678 | DI24: 2.2553991 | DJ24: 2.3450916 | DK24: 2.8010871 | DL24: 3.0595713 | DM24: 3.1310415 | DN24: 3.4921519 | DO24: 3.8124139 | DP24: 3.9488312 | DQ24: 4.0732251 | DR24: 4.2498524 | DS24: 4.3000469 | DT24: 4.4039416 | DU24: 4.3365788 | DV24: 4.369701 | DW24: 4.4014519 | DX24: 4.6077451 | DY24: 4.4493219 | DZ24: 4.7599834 | EA24: 4.8800872 | EB24: 3.8836268 | EC24: 3.732457 | ED24: 3.678678 | EE24: 3.3482556 | EF24: 3.2597017 | EG24: 3.0152536 | EH24: 2.7806943 | EI24: 2.513235 | EJ24: 2.4159573 | EK24: 2.2468336 | EL24: 2.1778664 | EM24: 2.0899948 | EN24: 2.2839286 | EO24: 2.7017627 | EP24: 2.8535003 | EQ24: 3.2657072 | ER24: 3.8048556 | ES24: 3.7458079 | ET24: 3.4841569 | EU24: 3.3536683 | EV24: 3.0734875 | EW24: 2.8618694 | EX24: 2.8763815 | EY24: 2.7772189 | EZ24: 2.4507216 | FA24: 2.2577393 | FB24: 2.0430808 | FC24: 1.8947387 | FD24: 1.7856527 | FE24: 1.7730506 | FF24: 1.7411594 | FG24: 1.7519416 | FH24: 1.7215686 | FI24: 1.8013934 | FJ24: 1.8793176 | FK24: 1.8620733 | FL24: 1.9050527 | FM24: 1.8478345 | FN24: 1.8175302 | FO24: 1.7875752 | FP24: 1.8265014 | FQ24: 1.758933 | FR24: 1.7282641 | FS24: 1.6537355 | FT24: 1.5540922 | FU24: 1.5819298 | FV24: 1.5386949 | FW24: 1.4595532 | FX24: 1.4246473 | FY24: 1.4381793 | FZ24: 1.5097585 | GA24: 1.4500407 | GB24: 1.4670676 | GC24: 1.4630331 | GD24: 1.4616892 | GE24: 1.4048194 | GF24: 1.4062135 | GG24: 1.5404614 | GH24: 1.6445609 | GI24: 1.812684 | GJ24: 2.0058864 | GK24: 2.252072 | GL24: 2.64315 | GM24: 3.019896 | GN24: 3.3014331 | GO24: 3.9260655 | GP24: 4.2948745 | GQ24: 4.649445 | GR24: 5.3440122 | GS24: 5.5415115 | GT24: 6.3742945 | GU24: 6.847754
A25: Previsiones / Cartera irregular | B25: 72.230115 | C25: 74.972866 | D25: 88.330402 | E25: 102.35479 | F25: 113.87359 | G25: 122.6674 | H25: 117.96218 | I25: 115.10084 | J25: 114.43575 | K25: 116.17471 | L25: 117.67466 | M25: 119.60598 | N25: 120.63464 | O25: 122.05361 | P25: 123.23993 | Q25: 124.92147 | R25: 129.85066 | S25: 131.53866 | T25: 135.02414 | U25: 142.96387 | V25: 146.76928 | W25: 149.40641 | X25: 152.82092 | Y25: 155.80456 | Z25: 156.04402 | AA25: 154.10903 | AB25: 159.77559 | AC25: 163.80278 | AD25: 168.01728 | AE25: 170.21185 | AF25: 169.68661 | AG25: 167.05574 | AH25: 158.82935 | AI25: 153.25314 | AJ25: 152.72452 | AK25: 144.36212 | AL25: 139.15755 | AM25: 144.74942 | AN25: 141.37184 | AO25: 140.16455 | AP25: 143.11261 | AQ25: 137.38633 | AR25: 138.57415 | AS25: 138.6836 | AT25: 135.24533 | AU25: 130.84988 | AV25: 133.91079 | AW25: 132.36721 | AX25: 129.3631 | AY25: 128.96075 | AZ25: 130.96489 | BA25: 131.41204 | BB25: 133.28913 | BC25: 134.35044 | BD25: 136.89073 | BE25: 144.77031 | BF25: 147.99922 | BG25: 144.61481 | BH25: 142.59763 | BI25: 138.75434 | BJ25: 134.60473 | BK25: 134.87389 | BL25: 136.68665 | BM25: 135.95874 | BN25: 138.10724 | BO25: 138.2409 | BP25: 137.68122 | BQ25: 140.74525 | BR25: 139.87141 | BS25: 140.56681 | BT25: 140.88037 | BU25: 137.94703 | BV25: 138.43311 | BW25: 142.62038 | BX25: 144.7019 | BY25: 145.79555 | BZ25: 148.73745 | CA25: 152.26658 | CB25: 152.10475 | CC25: 155.56957 | CD25: 152.90487 | CE25: 152.29696 | CF25: 150.92123 | CG25: 146.11544 | CH25: 144.73005 | CI25: 142.61038 | CJ25: 143.54765 | CK25: 144.18404 | CL25: 145.38995 | CM25: 143.73745 | CN25: 144.969 | CO25: 143.64312 | CP25: 139.65885 | CQ25: 137.22759 | CR25: 133.10841 | CS25: 132.38566 | CT25: 130.7002 | CU25: 129.33247 | CV25: 131.80262 | CW25: 133.75258 | CX25: 136.94019 | CY25: 135.22347 | CZ25: 131.8983 | DA25: 131.00923 | DB25: 127.30374 | DC25: 126.3628 | DD25: 124.02521 | DE25: 122.31721 | DF25: 117.62148 | DG25: 118.13432 | DH25: 115.42579 | DI25: 117.68918 | DJ25: 118.52235 | DK25: 110.56188 | DL25: 104.28414 | DM25: 104.81292 | DN25: 102.06892 | DO25: 99.554493 | DP25: 101.98934 | DQ25: 102.37891 | DR25: 104.12095 | DS25: 106.95213 | DT25: 106.76292 | DU25: 105.17303 | DV25: 110.16662 | DW25: 112.56067 | DX25: 111.25244 | DY25: 116.75223 | DZ25: 105.05329 | EA25: 103.80348 | EB25: 127.82769 | EC25: 136.21911 | ED25: 147.30119 | EE25: 157.6219 | EF25: 164.65197 | EG25: 173.15953 | EH25: 190.2544 | EI25: 204.63607 | EJ25: 210.33381 | EK25: 237.48824 | EL25: 242.8483 | EM25: 250.98892 | EN25: 222.95622 | EO25: 191.14127 | EP25: 179.82338 | EQ25: 156.30933 | ER25: 136.40964 | ES25: 135.44894 | ET25: 141.32122 | EU25: 143.99243 | EV25: 146.31951 | EW25: 151.03192 | EX25: 145.67303 | EY25: 148.16539 | EZ25: 156.32161 | FA25: 161.51825 | FB25: 168.75414 | FC25: 168.89089 | FD25: 172.02323 | FE25: 173.21524 | FF25: 179.25536 | FG25: 170.00133 | FH25: 179.47589 | FI25: 178.20518 | FJ25: 168.61029 | FK25: 169.74329 | FL25: 165.56897 | FM25: 165.95383 | FN25: 166.79055 | FO25: 167.94883 | FP25: 161.2148 | FQ25: 165.93994 | FR25: 160.83524 | FS25: 172.5602 | FT25: 177.06151 | FU25: 183.34903 | FV25: 180.23548 | FW25: 187.72475 | FX25: 184.80645 | FY25: 186.0682 | FZ25: 169.14488 | GA25: 170.35046 | GB25: 169.0643 | GC25: 175.31229 | GD25: 175.62366 | GE25: 185.0084 | GF25: 193.67376 | GG25: 175.92898 | GH25: 172.81053 | GI25: 160.85386 | GJ25: 155.16636 | GK25: 147.50888 | GL25: 135.35769 | GM25: 121.4159 | GN25: 117.50913 | GO25: 109.45358 | GP25: 104.08168 | GQ25: 103.56848 | GR25: 97.451671 | GS25: 94.921553 | GT25: 90.827044 | GU25: 90.654532
A26: (Cartera irregular - Previsiones) / Financiaciones | B26: 10.378217 | C26: 7.6065361 | D26: 1.7860413 | E26: -0.1478771 | F26: -0.49769831 | G26: -0.56068552 | H26: -0.50517776 | I26: -0.49106859 | J26: -0.48201179 | K26: -0.52742811 | L26: -0.54788705 | M26: -0.57860635 | N26: -0.58669339 | O26: -0.60545035 | P26: -0.62869886 | Q26: -0.6521002 | R26: -0.71039847 | S26: -0.7251949 | T26: -0.76213003 | U26: -0.85545597 | V26: -0.88243161 | W26: -0.90188286 | X26: -0.91643849 | Y26: -0.94089294 | Z26: -0.9226837 | AA26: -0.85574821 | AB26: -0.90379084 | AC26: -0.94086553 | AD26: -0.93933524 | AE26: -0.97291047 | AF26: -0.95509459 | AG26: -0.93653334 | AH26: -0.87471817 | AI26: -0.82820988 | AJ26: -0.83433354 | AK26: -0.75383247 | AL26: -0.7039026 | AM26: -0.76240594 | AN26: -0.73104085 | AO26: -0.72590279 | AP26: -0.75203396 | AQ26: -0.68491614 | AR26: -0.69270717 | AS26: -0.68814625 | AT26: -0.65636673 | AU26: -0.60132226 | AV26: -0.63830341 | AW26: -0.6253037 | AX26: -0.58068079 | AY26: -0.57033438 | AZ26: -0.61018278 | BA26: -0.61632795 | BB26: -0.63030333 | BC26: -0.64264704 | BD26: -0.66787819 | BE26: -0.76363946 | BF26: -0.83915867 | BG26: -0.8152542 | BH26: -0.79292082 | BI26: -0.75479435 | BJ26: -0.71641591 | BK26: -0.70801822 | BL26: -0.73832493 | BM26: -0.74621785 | BN26: -0.76334163 | BO26: -0.77321701 | BP26: -0.76476787 | BQ26: -0.7776097 | BR26: -0.77255205 | BS26: -0.77550603 | BT26: -0.7769049 | BU26: -0.7505825 | BV26: -0.74642628 | BW26: -0.77378069 | BX26: -0.79540449 | BY26: -0.78609472 | BZ26: -0.8175997 | CA26: -0.84040947 | CB26: -0.82305112 | CC26: -0.8462763 | CD26: -0.83198867 | CE26: -0.83187546 | CF26: -0.8101651 | CG26: -0.75413348 | CH26: -0.73766487 | CI26: -0.70659672 | CJ26: -0.72301953 | CK26: -0.74378855 | CL26: -0.7404714 | CM26: -0.72143305 | CN26: -0.72500545 | CO26: -0.68220803 | CP26: -0.65631878 | CQ26: -0.6379728 | CR26: -0.58178255 | CS26: -0.59571025 | CT26: -0.57091781 | CU26: -0.55183965 | CV26: -0.57635549 | CW26: -0.60041145 | CX26: -0.64043411 | CY26: -0.62248878 | CZ26: -0.58259397 | DA26: -0.55276041 | DB26: -0.50989041 | DC26: -0.50192147 | DD26: -0.47910442 | DE26: -0.45044331 | DF26: -0.38052015 | DG26: -0.3866788 | DH26: -0.35730259 | DI26: -0.39896155 | DJ26: -0.43436617 | DK26: -0.29584759 | DL26: -0.13107637 | DM26: -0.15069457 | DN26: -0.072249702 | DO26: 0.01698458 | DP26: -0.078555599 | DQ26: -0.096898189 | DR26: -0.17513418 | DS26: -0.29894467 | DT26: -0.29783501 | DU26: -0.22433245 | DV26: -0.44425109 | DW26: -0.55285197 | DX26: -0.51848394 | DY26: -0.74536086 | DZ26: -0.24053583 | EA26: -0.18561301 | EB26: -1.0807237 | EC26: -1.3518627 | ED26: -1.7400585 | EE26: -1.9293287 | EF26: -2.1074614 | EG26: -2.2059452 | EH26: -2.509699 | EI26: -2.6297504 | EJ26: -2.6656177 | EK26: -3.0891321 | EL26: -3.1110452 | EM26: -3.1556606 | EN26: -2.8082322 | EO26: -2.4624209 | EP26: -2.2777605 | EQ26: -1.8388978 | ER26: -1.3853341 | ES26: -1.3278491 | ET26: -1.4396961 | EU26: -1.4753602 | EV26: -1.4236244 | EW26: -1.4604668 | EX26: -1.3137307 | EY26: -1.3376582 | EZ26: -1.3802858 | FA26: -1.3889218 | FB26: -1.4047027 | FC26: -1.3053024 | FD26: -1.2860848 | FE26: -1.2981432 | FF26: -1.3799622 | FG26: -1.2263823 | FH26: -1.368232 | FI26: -1.408783 | FJ26: -1.2894052 | FK26: -1.2986712 | FL26: -1.2491234 | FM26: -1.2187176 | FN26: -1.2139385 | FO26: -1.2146364 | FP26: -1.1180891 | FQ26: -1.1598395 | FR26: -1.0513937 | FS26: -1.1999538 | FT26: -1.1976069 | FU26: -1.3185232 | FV26: -1.2345793 | FW26: -1.2803894 | FX26: -1.2081928 | FY26: -1.2378151 | FZ26: -1.0439207 | GA26: -1.0201102 | GB26: -1.0132199 | GC26: -1.1018438 | GD26: -1.1053829 | GE26: -1.1942145 | GF26: -1.317253 | GG26: -1.1696566 | GH26: -1.1974135 | GI26: -1.1030882 | GJ26: -1.1065746 | GK26: -1.0699343 | GL26: -0.93455685 | GM26: -0.64673777 | GN26: -0.5780522 | GO26: -0.37115394 | GP26: -0.1753032 | GQ26: -0.16591435 | GR26: 0.13618303 | GS26: 0.28142271 | GT26: 0.58471124 | GU26: 0.63995464
A27: (Cartera irregular - Previsiones) / PN | B27: 19.093636 | C27: 12.93394 | D27: 3.6494881 | E27: -0.36313539 | F27: -1.4043958 | G27: -1.9910969 | H27: -1.7913425 | I27: -1.6193442 | J27: -1.5391449 | K27: -1.6703951 | L27: -1.7487889 | M27: -1.9948602 | N27: -2.1500113 | O27: -2.2411323 | P27: -2.3075261 | Q27: -2.4036803 | R27: -2.6703197 | S27: -2.75324 | T27: -2.9197357 | U27: -3.3560801 | V27: -3.467045 | W27: -3.6180151 | X27: -3.9161677 | Y27: -4.173904 | Z27: -4.1782724 | AA27: -3.9392479 | AB27: -4.1899191 | AC27: -4.4116416 | AD27: -4.5340487 | AE27: -4.6640999 | AF27: -4.5023131 | AG27: -4.360599 | AH27: -4.0242672 | AI27: -3.7711227 | AJ27: -3.7607404 | AK27: -3.340728 | AL27: -3.0934306 | AM27: -3.3493351 | AN27: -3.1755566 | AO27: -3.1830322 | AP27: -3.2744783 | AQ27: -3.0045948 | AR27: -3.0615758 | AS27: -3.1295563 | AT27: -2.9304458 | AU27: -2.645986 | AV27: -2.816129 | AW27: -2.7637513 | AX27: -2.5667518 | AY27: -2.5649787 | AZ27: -2.7216395 | BA27: -2.7640939 | BB27: -2.8236852 | BC27: -2.8642297 | BD27: -2.9729703 | BE27: -3.406207 | BF27: -3.5352892 | BG27: -3.3373128 | BH27: -3.2172568 | BI27: -3.0399249 | BJ27: -2.8393964 | BK27: -2.852169 | BL27: -2.9304033 | BM27: -2.9331526 | BN27: -3.0041557 | BO27: -3.0386028 | BP27: -3.0242164 | BQ27: -3.1020987 | BR27: -3.0278846 | BS27: -3.0461613 | BT27: -3.0451751 | BU27: -2.9961137 | BV27: -2.9966103 | BW27: -3.1838758 | BX27: -3.223597 | BY27: -3.2228803 | BZ27: -3.3338659 | CA27: -3.4260377 | CB27: -3.4094583 | CC27: -3.5294059 | CD27: -3.4159129 | CE27: -3.3608812 | CF27: -3.2059571 | CG27: -3.0476503 | CH27: -2.9534003 | CI27: -2.8083413 | CJ27: -2.8705292 | CK27: -3.0339462 | CL27: -3.04207 | CM27: -2.9793503 | CN27: -3.0367211 | CO27: -2.9311894 | CP27: -2.8026027 | CQ27: -2.6860733 | CR27: -2.4363706 | CS27: -2.5420517 | CT27: -2.4741062 | CU27: -2.3429335 | CV27: -2.4253485 | CW27: -2.5438798 | CX27: -2.7412471 | CY27: -2.6850717 | CZ27: -2.509767 | DA27: -2.3569776 | DB27: -2.0208368 | DC27: -2.0031691 | DD27: -1.8927256 | DE27: -1.8603435 | DF27: -1.6364034 | DG27: -1.6829564 | DH27: -1.5106087 | DI27: -1.8176094 | DJ27: -1.9194021 | DK27: -1.2046465 | DL27: -0.53479416 | DM27: -0.58598411 | DN27: -0.2669267 | DO27: 0.060772732 | DP27: -0.28193459 | DQ27: -0.34952575 | DR27: -0.61585192 | DS27: -0.99804095 | DT27: -0.97693577 | DU27: -0.79751483 | DV27: -1.4251144 | DW27: -1.7273666 | DX27: -1.5369121 | DY27: -2.0707602 | DZ27: -0.53689415 | EA27: -0.4066979 | EB27: -2.3917973 | EC27: -3.0477703 | ED27: -3.8655957 | EE27: -4.2480244 | EF27: -4.5217804 | EG27: -4.6549097 | EH27: -5.1838856 | EI27: -5.4151965 | EJ27: -5.4811477 | EK27: -6.2385734 | EL27: -6.0979845 | EM27: -6.0613359 | EN27: -5.2438138 | EO27: -4.5247115 | EP27: -4.154911 | EQ27: -3.3385819 | ER27: -2.4437166 | ES27: -2.3350298 | ET27: -2.5137735 | EU27: -2.590781 | EV27: -2.548062 | EW27: -2.6101976 | EX27: -2.2812521 | EY27: -2.280757 | EZ27: -2.2936703 | FA27: -2.278546 | FB27: -2.3115571 | FC27: -2.1902759 | FD27: -2.1002462 | FE27: -2.0331119 | FF27: -2.0579437 | FG27: -1.8254998 | FH27: -2.0403371 | FI27: -2.0477377 | FJ27: -1.8309006 | FK27: -1.8093875 | FL27: -1.767685 | FM27: -1.8243745 | FN27: -1.8032846 | FO27: -1.7779089 | FP27: -1.5994442 | FQ27: -1.6455485 | FR27: -1.4326025 | FS27: -1.5984845 | FT27: -1.462517 | FU27: -1.4243696 | FV27: -1.2405936 | FW27: -1.2424869 | FX27: -1.1543525 | FY27: -1.1727835 | FZ27: -1.1608664 | GA27: -1.2484975 | GB27: -1.3003744 | GC27: -1.4644063 | GD27: -1.5661251 | GE27: -1.7743989 | GF27: -2.0910285 | GG27: -1.9938058 | GH27: -2.0929482 | GI27: -1.9853164 | GJ27: -2.0891439 | GK27: -2.0901825 | GL27: -1.9171745 | GM27: -1.4591177 | GN27: -1.3700252 | GO27: -0.90110169 | GP27: -0.44099023 | GQ27: -0.40662609 | GR27: 0.33564048 | GS27: 0.70317074 | GT27: 1.407948 | GU27: 1.4877078
A28: Fuente: BCRA
A33: Bancos privados nacionales
A34: En porcentaje | B34: 37591 | C34: 37956 | D34: 38322 | E34: 38687 | F34: 39052 | G34: 39417 | H34: 39783 | I34: 40148 | J34: 40179 | K34: 40210 | L34: 40238 | M34: 40269 | N34: 40299 | O34: 40330 | P34: 40360 | Q34: 40391 | R34: 40422 | S34: 40452 | T34: 40483 | U34: 40513 | V34: 40544 | W34: 40575 | X34: 40603 | Y34: 40634 | Z34: 40664 | AA34: 40695 | AB34: 40725 | AC34: 40756 | AD34: 40787 | AE34: 40817 | AF34: 40848 | AG34: 40878 | AH34: 40909 | AI34: 40940 | AJ34: 40969 | AK34: 41000 | AL34: 41030 | AM34: 41061 | AN34: 41091 | AO34: 41122 | AP34: 41153 | AQ34: 41183 | AR34: 41214 | AS34: 41244 | AT34: 41275 | AU34: 41306 | AV34: 41334 | AW34: 41365 | AX34: 41395 | AY34: 41426 | AZ34: 41456 | BA34: 41487 | BB34: 41518 | BC34: 41548 | BD34: 41579 | BE34: 41609 | BF34: 41640 | BG34: 41671 | BH34: 41699 | BI34: 41730 | BJ34: 41760 | BK34: 41791 | BL34: 41821 | BM34: 41852 | BN34: 41883 | BO34: 41913 | BP34: 41944 | BQ34: 41974 | BR34: 42005 | BS34: 42036 | BT34: 42064 | BU34: 42095 | BV34: 42125 | BW34: 42156 | BX34: 42186 | BY34: 42217 | BZ34: 42248 | CA34: 42278 | CB34: 42309 | CC34: 42339 | CD34: 42370 | CE34: 42401 | CF34: 42430 | CG34: 42461 | CH34: 42491 | CI34: 42522 | CJ34: 42552 | CK34: 42583 | CL34: 42614 | CM34: 42644 | CN34: 42675 | CO34: 42705 | CP34: 42736 | CQ34: 42767 | CR34: 42795 | CS34: 42826 | CT34: 42856 | CU34: 42887 | CV34: 42917 | CW34: 42948 | CX34: 42979 | CY34: 43009 | CZ34: 43040 | DA34: 43070 | DB34: 43101 | DC34: 43132 | DD34: 43160 | DE34: 43191 | DF34: 43221 | DG34: 43252 | DH34: 43282 | DI34: 43313 | DJ34: 43344 | DK34: 43374 | DL34: 43405 | DM34: 43435 | DN34: 43466 | DO34: 43497 | DP34: 43525 | DQ34: 43556 | DR34: 43586 | DS34: 43617 | DT34: 43647 | DU34: 43678 | DV34: 43709 | DW34: 43739 | DX34: 43770 | DY34: 43800 | DZ34: 43831 | EA34: 43862 | EB34: 43891 | EC34: 43922 | ED34: 43952 | EE34: 43983 | EF34: 44013 | EG34: 44044 | EH34: 44075 | EI34: 44105 | EJ34: 44136 | EK34: 44166 | EL34: 44197 | EM34: 44228 | EN34: 44256 | EO34: 44287 | EP34: 44317 | EQ34: 44348 | ER34: 44378 | ES34: 44409 | ET34: 44440 | EU34: 44470 | EV34: 44501 | EW34: 44531 | EX34: 44562 | EY34: 44593 | EZ34: 44621 | FA34: 44652 | FB34: 44682 | FC34: 44713 | FD34: 44743 | FE34: 44774 | FF34: 44805 | FG34: 44835 | FH34: 44866 | FI34: 44896 | FJ34: 44927 | FK34: 44958 | FL34: 44986 | FM34: 45017 | FN34: 45047 | FO34: 45078 | FP34: 45108 | FQ34: 45139 | FR34: 45170 | FS34: 45200 | FT34: 45231 | FU34: 45261 | FV34: 45292 | FW34: 45323 | FX34: 45352 | FY34: 45383 | FZ34: 45413 | GA34: 45444 | GB34: 45474 | GC34: 45505 | GD34: 45536 | GE34: 45566 | GF34: 45597 | GG34: 45627 | GH34: 45658 | GI34: 45689 | GJ34: 45717 | GK34: 45748 | GL34: 45778 | GM34: 45809 | GN34: 45839 | GO34: 45870 | GP34: 45901 | GQ34: 45931 | GR34: 45962 | GS34: 45992 | GT34: 46023 | GU34: 46054
A35: Cartera irregular total | B35: 14.181279 | C35: 11.872855 | D35: 9.0252673 | E35: 4.6809368 | F35: 2.8509186 | G35: 2.4794275 | H35: 3.0061245 | I35: 3.6955426 | J35: 3.7947146 | K35: 3.7158798 | L35: 3.5066029 | M35: 3.3837145 | N35: 3.2824713 | O35: 3.1769295 | P35: 3.1792656 | Q35: 3.1130559 | R35: 2.8495764 | S35: 2.8044785 | T35: 2.6678749 | U35: 2.3918834 | V35: 2.2776993 | W35: 2.222028 | X35: 2.1335356 | Y35: 2.1854479 | Z35: 2.1794406 | AA35: 2.079315 | AB35: 2.0343021 | AC35: 2.0006633 | AD35: 1.836255 | AE35: 1.8690336 | AF35: 1.7995011 | AG35: 1.7787373 | AH35: 1.900925 | AI35: 1.9683217 | AJ35: 1.990123 | AK35: 2.1744457 | AL35: 2.2831484 | AM35: 2.0340373 | AN35: 2.1361362 | AO35: 2.2093856 | AP35: 2.0492785 | AQ35: 2.205396 | AR35: 2.1269332 | AS35: 2.0869963 | AT35: 2.1982661 | AU35: 2.3205551 | AV35: 2.1346573 | AW35: 2.208248 | AX35: 2.2430676 | AY35: 2.2299701 | AZ35: 2.2861789 | BA35: 2.2758661 | BB35: 2.2338323 | BC35: 2.2217259 | BD35: 2.1089987 | BE35: 1.9122315 | BF35: 1.995945 | BG35: 2.0429022 | BH35: 2.0708585 | BI35: 2.2371769 | BJ35: 2.3187413 | BK35: 2.2587387 | BL35: 2.2610025 | BM35: 2.3315037 | BN35: 2.19984 | BO35: 2.2327686 | BP35: 2.2390921 | BQ35: 2.0902421 | BR35: 2.1264605 | BS35: 2.0935376 | BT35: 2.0979799 | BU35: 2.1897859 | BV35: 2.1458519 | BW35: 1.9755175 | BX35: 1.9645937 | BY35: 1.9060538 | BZ35: 1.8977588 | CA35: 1.8187138 | CB35: 1.8229663 | CC35: 1.7648356 | CD35: 1.822786 | CE35: 1.8789859 | CF35: 1.8591504 | CG35: 1.8872465 | CH35: 1.8960616 | CI35: 1.8986519 | CJ35: 1.891252 | CK35: 1.8977008 | CL35: 1.8398037 | CM35: 1.872267 | CN35: 1.7823387 | CO35: 1.6725314 | CP35: 1.780873 | CQ35: 1.839558 | CR35: 1.8347375 | CS35: 1.931602 | CT35: 1.9121896 | CU35: 1.9080777 | CV35: 1.8028777 | CW35: 1.8028226 | CX35: 1.6813489 | CY35: 1.7209503 | CZ35: 1.7567842 | DA35: 1.7450712 | DB35: 1.8725235 | DC35: 1.9249031 | DD35: 2.0037589 | DE35: 2.0588159 | DF35: 2.243939 | DG35: 2.1739223 | DH35: 2.3583736 | DI35: 2.3217808 | DJ35: 2.4051988 | DK35: 2.7536725 | DL35: 2.8635692 | DM35: 2.9322534 | DN35: 3.2724157 | DO35: 3.7049075 | DP35: 3.9641266 | DQ35: 4.1911774 | DR35: 4.39573 | DS35: 4.3539386 | DT35: 4.5652245 | DU35: 4.5942491 | DV35: 4.4547283 | DW35: 4.5391084 | DX35: 4.608411 | DY35: 4.6291477 | DZ35: 4.9631077 | EA35: 5.1051449 | EB35: 4.0032126 | EC35: 3.7939144 | ED35: 3.8468554 | EE35: 3.6754155 | EF35: 3.606277 | EG35: 3.4930418 | EH35: 3.1686062 | EI35: 2.810692 | EJ35: 2.5389274 | EK35: 2.2902976 | EL35: 2.1986991 | EM35: 2.1241106 | EN35: 2.3452061 | EO35: 2.8316247 | EP35: 2.975405 | EQ35: 3.4612618 | ER35: 4.1334072 | ES35: 3.9636946 | ET35: 3.7511305 | EU35: 3.6206565 | EV35: 3.2867598 | EW35: 2.9831627 | EX35: 3.077006 | EY35: 3.0052228 | EZ35: 2.6966447 | FA35: 2.4763875 | FB35: 2.2235051 | FC35: 2.0694628 | FD35: 2.0175721 | FE35: 2.0272936 | FF35: 2.0106538 | FG35: 2.0382741 | FH35: 2.0225435 | FI35: 2.0830627 | FJ35: 2.2220302 | FK35: 2.2073772 | FL35: 2.2493856 | FM35: 2.2035101 | FN35: 2.1218673 | FO35: 2.0576955 | FP35: 2.1246112 | FQ35: 1.9999268 | FR35: 1.9504777 | FS35: 1.882933 | FT35: 1.8016341 | FU35: 1.8434707 | FV35: 1.8188691 | FW35: 1.7100369 | FX35: 1.6097526 | FY35: 1.5452099 | FZ35: 1.5943214 | GA35: 1.4850665 | GB35: 1.4863386 | GC35: 1.4428608 | GD35: 1.4247245 | GE35: 1.3469933 | GF35: 1.3315673 | GG35: 1.5338786 | GH35: 1.6829197 | GI35: 1.8682665 | GJ35: 2.0755844 | GK35: 2.3830455 | GL35: 2.7612544 | GM35: 3.1201522 | GN35: 3.4032941 | GO35: 4.1144667 | GP35: 4.4635085 | GQ35: 4.8836642 | GR35: 5.5220405 | GS35: 5.4926229 | GT35: 6.1452413 | GU35: 6.4139918
A36: Previsiones / Cartera irregular | B36: 93.220226 | C36: 87.867599 | D36: 95.237915 | E36: 107.88156 | F36: 117.41303 | G36: 117.27607 | H36: 113.99076 | I36: 108.24925 | J36: 107.83556 | K36: 108.56618 | L36: 110.9495 | M36: 112.96538 | N36: 113.94107 | O36: 115.82262 | P36: 116.2648 | Q36: 117.47875 | R36: 120.5116 | S36: 120.95749 | T36: 123.95881 | U36: 132.70092 | V36: 135.70265 | W36: 137.92342 | X36: 140.68799 | Y36: 150.3147 | Z36: 149.3664 | AA36: 140.04253 | AB36: 143.60011 | AC36: 146.32989 | AD36: 150.12638 | AE36: 151.45193 | AF36: 151.48848 | AG36: 152.42402 | AH36: 146.18456 | AI36: 142.14003 | AJ36: 142.36316 | AK36: 135.15852 | AL36: 130.14253 | AM36: 140.46885 | AN36: 136.83974 | AO36: 132.30962 | AP36: 136.92798 | AQ36: 129.08524 | AR36: 129.79635 | AS36: 130.452 | AT36: 126.82233 | AU36: 122.0906 | AV36: 127.58151 | AW36: 125.52796 | AX36: 122.61421 | AY36: 121.96142 | AZ36: 122.37797 | BA36: 122.78186 | BB36: 121.84356 | BC36: 122.69026 | BD36: 124.37173 | BE36: 131.5137 | BF36: 135.96016 | BG36: 131.96487 | BH36: 129.52608 | BI36: 123.87778 | BJ36: 124.0302 | BK36: 124.18849 | BL36: 126.13922 | BM36: 125.65225 | BN36: 127.36516 | BO36: 127.90251 | BP36: 126.94922 | BQ36: 128.96746 | BR36: 128.21754 | BS36: 129.53401 | BT36: 130.34173 | BU36: 126.88439 | BV36: 127.25311 | BW36: 132.40442 | BX36: 133.66231 | BY36: 132.70918 | BZ36: 133.1058 | CA36: 136.22417 | CB36: 134.18741 | CC36: 137.60657 | CD36: 135.06997 | CE36: 133.7831 | CF36: 132.53547 | CG36: 129.69352 | CH36: 128.75255 | CI36: 128.02098 | CJ36: 129.93835 | CK36: 134.11495 | CL36: 133.79386 | CM36: 131.91281 | CN36: 135.24113 | CO36: 134.58331 | CP36: 129.44234 | CQ36: 127.2191 | CR36: 125.8751 | CS36: 123.01086 | CT36: 123.9021 | CU36: 124.00438 | CV36: 127.59766 | CW36: 128.3068 | CX36: 135.59155 | CY36: 132.23621 | CZ36: 132.21133 | DA36: 128.25663 | DB36: 123.14215 | DC36: 121.68391 | DD36: 119.60207 | DE36: 116.7322 | DF36: 111.03917 | DG36: 111.5488 | DH36: 109.3464 | DI36: 111.2945 | DJ36: 112.09116 | DK36: 109.64024 | DL36: 109.24495 | DM36: 111.97808 | DN36: 110.99865 | DO36: 104.17088 | DP36: 106.3382 | DQ36: 106.68025 | DR36: 108.76013 | DS36: 115.55202 | DT36: 114.88114 | DU36: 110.18839 | DV36: 118.78705 | DW36: 122.22747 | DX36: 122.29665 | DY36: 125.97113 | DZ36: 91.683729 | EA36: 91.468573 | EB36: 113.1096 | EC36: 123.09796 | ED36: 134.16927 | EE36: 131.73028 | EF36: 141.58396 | EG36: 148.26658 | EH36: 160.40735 | EI36: 170.72176 | EJ36: 193.46677 | EK36: 229.13154 | EL36: 236.62596 | EM36: 240.55089 | EN36: 214.42228 | EO36: 180.12652 | EP36: 172.87768 | EQ36: 148.89516 | ER36: 125.4049 | ES36: 125.04232 | ET36: 128.40978 | EU36: 131.14625 | EV36: 134.592 | EW36: 139.24972 | EX36: 135.16839 | EY36: 134.8986 | EZ36: 138.76897 | FA36: 143.72213 | FB36: 149.68025 | FC36: 149.89873 | FD36: 147.97804 | FE36: 146.31131 | FF36: 149.96623 | FG36: 141.43267 | FH36: 150.01057 | FI36: 148.59709 | FJ36: 140.36856 | FK36: 140.37123 | FL36: 135.78644 | FM36: 134.46487 | FN36: 135.38361 | FO36: 138.97104 | FP36: 135.53178 | FQ36: 142.98526 | FR36: 135.97058 | FS36: 139.59061 | FT36: 136.79514 | FU36: 146.51713 | FV36: 158.72294 | FW36: 163.74187 | FX36: 169.86406 | FY36: 171.97906 | FZ36: 162.45889 | GA36: 168.29361 | GB36: 166.73526 | GC36: 173.19413 | GD36: 173.57708 | GE36: 180.91494 | GF36: 185.56701 | GG36: 161.97824 | GH36: 157.30645 | GI36: 149.47259 | GJ36: 147.14025 | GK36: 139.06689 | GL36: 127.49106 | GM36: 117.92227 | GN36: 114.88539 | GO36: 106.46161 | GP36: 101.76885 | GQ36: 101.71766 | GR36: 98.142511 | GS36: 98.381681 | GT36: 94.285414 | GU36: 93.630051
A37: (Cartera irregular - Previsiones) / Financiaciones | B37: 0.96145861 | C37: 1.4404624 | D37: 0.42979086 | E37: -0.36893106 | F37: -0.49643134 | G37: -0.42834751 | H37: -0.4205797 | I37: -0.3048546 | J37: -0.29733701 | K37: -0.31830888 | L37: -0.3839556 | M37: -0.4387115 | N37: -0.45761176 | O37: -0.50267356 | P37: -0.5171011 | Q37: -0.54412329 | R37: -0.58449374 | S37: -0.58774837 | T37: -0.63919119 | U37: -0.78216779 | V37: -0.81319893 | W37: -0.8426689 | X37: -0.86809274 | Y37: -1.0996015 | Z37: -1.0759113 | AA37: -0.83261032 | AB37: -0.8869579 | AC37: -0.92690507 | AD37: -0.9204482 | AE37: -0.9616539 | AF37: -0.92653582 | AG37: -0.93248567 | AH37: -0.87793385 | AI37: -0.82945142 | AJ37: -0.84307904 | AK37: -0.76450281 | AL37: -0.68819881 | AM37: -0.82315143 | AN37: -0.78694705 | AO37: -0.713844 | AP37: -0.75675724 | AQ37: -0.64144474 | AR37: -0.63374852 | AS37: -0.63553204 | AT37: -0.5896261 | AU37: -0.51262449 | AV37: -0.58877063 | AW37: -0.56372074 | AX37: -0.50725194 | AY37: -0.48973303 | AZ37: -0.5116005 | BA37: -0.51848454 | BB37: -0.48794854 | BC37: -0.50411543 | BD37: -0.51399941 | BE37: -0.60261481 | BF37: -0.71774502 | BG37: -0.65301103 | BH37: -0.61144329 | BI37: -0.53418829 | BJ37: -0.5571981 | BK37: -0.54635482 | BL37: -0.59100833 | BM37: -0.59808305 | BN37: -0.60198969 | BO37: -0.62299836 | BP37: -0.60341783 | BQ37: -0.60549004 | BR37: -0.60003482 | BS37: -0.61830569 | BT37: -0.63656331 | BU37: -0.58871056 | BV37: -0.58481135 | BW37: -0.64015489 | BX37: -0.66132771 | BY37: -0.6234546 | BZ37: -0.62826818 | CA37: -0.65881393 | CB37: -0.62322503 | CC37: -0.66369422 | CD37: -0.63925045 | CE37: -0.63477965 | CF37: -0.6048834 | CG37: -0.56038987 | CH37: -0.54516613 | CI37: -0.53202084 | CJ37: -0.56620969 | CK37: -0.64739975 | CL37: -0.62174061 | CM37: -0.59749304 | CN37: -0.62811634 | CO37: -0.57841671 | CP37: -0.5243307 | CQ37: -0.50071117 | CR37: -0.47474025 | CS37: -0.4444783 | CT37: -0.45705351 | CU37: -0.45802216 | CV37: -0.49755202 | CW37: -0.5103213 | CX37: -0.5984181 | CY37: -0.5547691 | CZ37: -0.56588362 | DA37: -0.49309833 | DB37: -0.43334229 | DC37: -0.41739425 | DD37: -0.39277813 | DE37: -0.34448514 | DF37: -0.24771233 | DG37: -0.25106198 | DH37: -0.22042292 | DI37: -0.26223363 | DJ37: -0.29081653 | DK37: -0.26546072 | DL37: -0.26473558 | DM37: -0.35122756 | DN37: -0.35992158 | DO37: -0.15452722 | DP37: -0.25125435 | DQ37: -0.27998117 | DR37: -0.3850715 | DS37: -0.67712535 | DT37: -0.67935747 | DU37: -0.46807987 | DV37: -0.83691205 | DW37: -1.0089289 | DX37: -1.0275213 | DY37: -1.2022418 | DZ37: 0.41274549 | EA37: 0.43554168 | EB37: -0.52480533 | EC37: -0.87631673 | ED37: -1.3144426 | EE37: -1.1662195 | EF37: -1.4996329 | EG37: -1.6859718 | EH37: -1.9140711 | EI37: -1.9877708 | EJ37: -2.3730536 | EK37: -2.9574966 | EL37: -3.0039939 | EM37: -2.9854562 | EN37: -2.6834382 | EO37: -2.2688824 | EP37: -2.168406 | EQ37: -1.6923896 | ER37: -1.0500878 | ES37: -0.99260091 | ET37: -1.0656878 | EU37: -1.1276987 | EV37: -1.1369559 | EW37: -1.1708831 | EX37: -1.0821334 | EY37: -1.0487807 | EZ37: -1.0454615 | FA37: -1.0827293 | FB37: -1.1046428 | FC37: -1.0326357 | FD37: -0.96799157 | FE37: -0.93886616 | FF37: -1.0046479 | FG37: -0.84451144 | FH37: -1.0114856 | FI37: -1.0123079 | FJ37: -0.89700159 | FK37: -0.89114542 | FL37: -0.80497493 | FM37: -0.75943695 | FN37: -0.75079331 | FO37: -0.8019053 | FP37: -0.7549121 | FQ37: -0.85967379 | FR37: -0.70159816 | FS37: -0.74546466 | FT37: -0.66291371 | FU37: -0.85752969 | FV37: -1.0680935 | FW37: -1.0900095 | FX37: -1.1246385 | FY37: -1.1122276 | FZ37: -0.9957955 | GA37: -1.0142055 | GB37: -0.99191186 | GC37: -1.0560894 | GD37: -1.0482707 | GE37: -1.0899189 | GF37: -1.1393823 | GG37: -0.95067093 | GH37: -0.96442148 | GI37: -0.92427992 | GJ37: -0.97843576 | GK37: -0.93098169 | GL37: -0.75909814 | GM37: -0.55920202 | GN37: -0.50659345 | GO37: -0.26586071 | GP37: -0.078952682 | GQ37: -0.083884635 | GR37: 0.10257127 | GS37: 0.088888148 | GT37: 0.35117507 | GU37: 0.40856804
A38: (Cartera irregular - Previsiones) / PN | B38: 2.5722934 | C38: 4.4091803 | D38: 1.2630869 | E38: -1.0738228 | F38: -1.3662774 | G38: -1.4217905 | H38: -1.3983193 | I38: -0.98078438 | J38: -0.94329113 | K38: -0.99589585 | L38: -1.2126917 | M38: -1.4586587 | N38: -1.6460642 | O38: -1.8113094 | P38: -1.8589379 | Q38: -1.9637401 | R38: -2.1563013 | S38: -2.2206426 | T38: -2.4825408 | U38: -3.1337267 | V38: -3.2656929 | W38: -3.3839212 | X38: -3.6044126 | Y38: -4.9016369 | Z38: -4.8688012 | AA38: -3.8634771 | AB38: -4.1101944 | AC38: -4.3493392 | AD38: -4.4626818 | AE38: -4.6467547 | AF38: -4.4544842 | AG38: -4.4789198 | AH38: -4.127947 | AI38: -3.8890337 | AJ38: -3.896374 | AK38: -3.489155 | AL38: -3.1358914 | AM38: -3.7727108 | AN38: -3.5593189 | AO38: -3.2894284 | AP38: -3.4751086 | AQ38: -2.9471933 | AR38: -2.957203 | AS38: -3.0284689 | AT38: -2.7421718 | AU38: -2.363344 | AV38: -2.7287745 | AW38: -2.6282287 | AX38: -2.3823938 | AY38: -2.3212606 | AZ38: -2.384915 | BA38: -2.4302108 | BB38: -2.2945584 | BC38: -2.347574 | BD38: -2.3995068 | BE38: -2.8342542 | BF38: -3.2356293 | BG38: -2.859422 | BH38: -2.6353605 | BI38: -2.2521363 | BJ38: -2.3239778 | BK38: -2.3267115 | BL38: -2.4543788 | BM38: -2.4565572 | BN38: -2.5013658 | BO38: -2.5887904 | BP38: -2.5446484 | BQ38: -2.546915 | BR38: -2.5010061 | BS38: -2.571137 | BT38: -2.645047 | BU38: -2.4881429 | BV38: -2.4867202 | BW38: -2.7766074 | BX38: -2.8136203 | BY38: -2.6862744 | BZ38: -2.6782128 | CA38: -2.8100916 | CB38: -2.7004177 | CC38: -2.873191 | CD38: -2.742805 | CE38: -2.6461369 | CF38: -2.5203276 | CG38: -2.3765192 | CH38: -2.2740752 | CI38: -2.1595239 | CJ38: -2.2804804 | CK38: -2.6874515 | CL38: -2.607428 | CM38: -2.5333985 | CN38: -2.7570806 | CO38: -2.5892734 | CP38: -2.3067479 | CQ38: -2.1804207 | CR38: -2.0898224 | CS38: -1.9722323 | CT38: -2.0470358 | CU38: -1.9029454 | CV38: -2.0662353 | CW38: -2.1141672 | CX38: -2.528516 | CY38: -2.3553424 | CZ38: -2.3900007 | DA38: -1.9784761 | DB38: -1.6794314 | DC38: -1.6211201 | DD38: -1.5267114 | DE38: -1.3921666 | DF38: -1.046417 | DG38: -1.0541795 | DH38: -0.90006145 | DI38: -1.158278 | DJ38: -1.2724941 | DK38: -1.0891064 | DL38: -1.072792 | DM38: -1.3636863 | DN38: -1.3167931 | DO38: -0.55204697 | DP38: -0.88246685 | DQ38: -1.0060277 | DR38: -1.3265677 | DS38: -2.1983395 | DT38: -2.1500033 | DU38: -1.5787484 | DV38: -2.5568554 | DW38: -3.020568 | DX38: -3.0064246 | DY38: -3.403598 | DZ38: 0.90598478 | EA38: 0.92837179 | EB38: -1.1276538 | EC38: -1.9484958 | ED38: -2.8437503 | EE38: -2.4733423 | EF38: -3.1074215 | EG38: -3.455324 | EH38: -3.8764426 | EI38: -4.0376922 | EJ38: -4.7870349 | EK38: -5.8552818 | EL38: -5.751084 | EM38: -5.6129555 | EN38: -4.8199469 | EO38: -3.9876695 | EP38: -3.7249834 | EQ38: -2.8531729 | ER38: -1.6974705 | ES38: -1.6245004 | ET38: -1.753015 | EU38: -1.8748004 | EV38: -1.9504571 | EW38: -2.0286017 | EX38: -1.7919697 | EY38: -1.7130268 | EZ38: -1.6475791 | FA38: -1.6594743 | FB38: -1.7298724 | FC38: -1.6412968 | FD38: -1.4817941 | FE38: -1.3879974 | FF38: -1.4144732 | FG38: -1.183893 | FH38: -1.415849 | FI38: -1.3849493 | FJ38: -1.1778962 | FK38: -1.1377458 | FL38: -1.0525124 | FM38: -1.0439926 | FN38: -1.0315138 | FO38: -1.0897328 | FP38: -0.98650007 | FQ38: -1.124225 | FR38: -0.90859205 | FS38: -0.94334468 | FT38: -0.75303563 | FU38: -0.8427482 | FV38: -0.95606584 | FW38: -0.94060925 | FX38: -0.93475481 | FY38: -0.92111214 | FZ38: -1.0122882 | GA38: -1.1357731 | GB38: -1.1475575 | GC38: -1.2756055 | GD38: -1.3740006 | GE38: -1.550008 | GF38: -1.7609577 | GG38: -1.5606465 | GH38: -1.6200101 | GI38: -1.5946629 | GJ38: -1.7661646 | GK38: -1.7250555 | GL38: -1.497588 | GM38: -1.2639499 | GN38: -1.1849748 | GO38: -0.63527223 | GP38: -0.19734524 | GQ38: -0.20663628 | GR38: 0.25458349 | GS38: 0.22309423 | GT38: 0.85849347 | GU38: 0.96561358
A39: Al sector privado no financiero | B39: 31.333773 | C39: 25.936118 | D39: 14.636229 | E39: 6.7941144 | F39: 3.5176567 | G39: 2.7473716 | H39: 3.2871492 | I39: 3.8264418 | J39: 3.9339444 | K39: 3.8536271 | L39: 3.6307972 | M39: 3.4957062 | N39: 3.3834187 | O39: 3.2817507 | P39: 3.2832323 | Q39: 3.2121666 | R39: 2.9364498 | S39: 2.8842585 | T39: 2.745463 | U39: 2.4638576 | V39: 2.3529116 | W39: 2.29127 | X39: 2.1998936 | Y39: 2.2517646 | Z39: 2.2471966 | AA39: 2.1434413 | AB39: 2.0951363 | AC39: 2.0586945 | AD39: 1.8952132 | AE39: 1.9295075 | AF39: 1.8578733 | AG39: 1.8347151 | AH39: 1.9556592 | AI39: 2.0289524 | AJ39: 2.0526553 | AK39: 2.2427931 | AL39: 2.3487481 | AM39: 2.1034995 | AN39: 2.2000534 | AO39: 2.2770094 | AP39: 2.1190656 | AQ39: 2.2758623 | AR39: 2.1936628 | AS39: 2.1522945 | AT39: 2.2680267 | AU39: 2.3926119 | AV39: 2.2039761 | AW39: 2.2846675 | AX39: 2.3241564 | AY39: 2.3141527 | AZ39: 2.3641952 | BA39: 2.3532438 | BB39: 2.3120167 | BC39: 2.2901214 | BD39: 2.187399 | BE39: 1.9850205 | BF39: 2.0645287 | BG39: 2.1156873 | BH39: 2.1448857 | BI39: 2.3191116 | BJ39: 2.4039485 | BK39: 2.3491082 | BL39: 2.3396163 | BM39: 2.4087733 | BN39: 2.269388 | BO39: 2.2947376 | BP39: 2.3121276 | BQ39: 2.1539365 | BR39: 2.1925291 | BS39: 2.1524591 | BT39: 2.1587038 | BU39: 2.2519889 | BV39: 2.2167367 | BW39: 2.0293256 | BX39: 2.013166 | BY39: 1.9612186 | BZ39: 1.9483088 | CA39: 1.8638457 | CB39: 1.8644976 | CC39: 1.805362 | CD39: 1.8754879 | CE39: 1.9361522 | CF39: 1.9175745 | CG39: 1.9527405 | CH39: 1.9656763 | CI39: 1.9623321 | CJ39: 1.9585454 | CK39: 1.9655576 | CL39: 1.910832 | CM39: 1.9365887 | CN39: 1.8516625 | CO39: 1.7389061 | CP39: 1.847496 | CQ39: 1.8946662 | CR39: 1.8920991 | CS39: 1.9938657 | CT39: 1.9759188 | CU39: 1.9755525 | CV39: 1.8737195 | CW39: 1.8731963 | CX39: 1.7488082 | CY39: 1.7871497 | CZ39: 1.8240192 | DA39: 1.8068015 | DB39: 1.9276723 | DC39: 1.9804539 | DD39: 2.0652072 | DE39: 2.1317491 | DF39: 2.3249966 | DG39: 2.2531827 | DH39: 2.4443114 | DI39: 2.4071888 | DJ39: 2.489226 | DK39: 2.8474829 | DL39: 2.9638834 | DM39: 3.029101 | DN39: 3.3791869 | DO39: 3.8198027 | DP39: 4.0854083 | DQ39: 4.3105001 | DR39: 4.3578772 | DS39: 4.4648487 | DT39: 4.6726236 | DU39: 4.7198049 | DV39: 4.58869 | DW39: 4.6737261 | DX39: 4.7363975 | DY39: 4.793944 | DZ39: 5.1164544 | EA39: 5.2518507 | EB39: 4.1124534 | EC39: 3.9220442 | ED39: 3.974356 | EE39: 3.8004582 | EF39: 3.7182899 | EG39: 3.5952096 | EH39: 3.2690845 | EI39: 2.8922194 | EJ39: 2.621305 | EK39: 2.3697382 | EL39: 2.2580601 | EM39: 2.1854183 | EN39: 2.4182006 | EO39: 2.9305157 | EP39: 3.0580124 | EQ39: 3.5539497 | ER39: 4.2497072 | ES39: 4.0797734 | ET39: 3.8652079 | EU39: 3.7293928 | EV39: 3.4004394 | EW39: 3.118989 | EX39: 3.1724391 | EY39: 3.1218262 | EZ39: 2.7750897 | FA39: 2.5572274 | FB39: 2.2940153 | FC39: 2.1278234 | FD39: 2.060595 | FE39: 2.0761065 | FF39: 2.0638187 | FG39: 2.083008 | FH39: 2.06608 | FI39: 2.1235312 | FJ39: 2.2549727 | FK39: 2.2386284 | FL39: 2.2827502 | FM39: 2.24127 | FN39: 2.1607592 | FO39: 2.1200385 | FP39: 2.1726439 | FQ39: 2.052118 | FR39: 2.0068266 | FS39: 1.9489032 | FT39: 1.8399143 | FU39: 1.9019462 | FV39: 1.8750733 | FW39: 1.7631087 | FX39: 1.6569721 | FY39: 1.5922311 | FZ39: 1.6603791 | GA39: 1.5411066 | GB39: 1.5423851 | GC39: 1.5036417 | GD39: 1.4859602 | GE39: 1.4120699 | GF39: 1.3940132 | GG39: 1.6000278 | GH39: 1.7490185 | GI39: 1.9484739 | GJ39: 2.1671968 | GK39: 2.4900071 | GL39: 2.8977778 | GM39: 3.2925529 | GN39: 3.5707034 | GO39: 4.3215413 | GP39: 4.6901876 | GQ39: 5.1018769 | GR39: 5.8193573 | GS39: 5.8318338 | GT39: 6.5757608 | GU39: 6.8503769
A40: Previsiones / Cartera irregular | B40: 94.118049 | C40: 87.564217 | D40: 92.612008 | E40: 107.31707 | F40: 117.04784 | G40: 116.67204 | H40: 113.42244 | I40: 107.22144 | J40: 107.57788 | K40: 108.38777 | L40: 110.74127 | M40: 112.77406 | N40: 113.76965 | O40: 115.60179 | P40: 116.01436 | Q40: 117.22398 | R40: 120.23792 | S40: 120.66163 | T40: 123.68103 | U40: 132.27377 | V40: 135.15803 | W40: 137.39885 | X40: 140.08264 | Y40: 149.66533 | Z40: 148.67656 | AA40: 139.56353 | AB40: 143.06537 | AC40: 145.83329 | AD40: 149.55248 | AE40: 150.83906 | AF40: 150.88279 | AG40: 151.87635 | AH40: 145.66544 | AI40: 141.67313 | AJ40: 141.9259 | AK40: 134.77903 | AL40: 129.8513 | AM40: 139.9891 | AN40: 136.40063 | AO40: 131.85449 | AP40: 136.44611 | AQ40: 128.70824 | AR40: 129.38307 | AS40: 129.99185 | AT40: 126.33135 | AU40: 121.67916 | AV40: 127.06687 | AW40: 125.02938 | AX40: 122.1061 | AY40: 121.47724 | AZ40: 122.02798 | BA40: 122.41238 | BB40: 121.46613 | BC40: 122.33305 | BD40: 123.92613 | BE40: 131.09674 | BF40: 135.54235 | BG40: 131.493 | BH40: 129.1414 | BI40: 123.46444 | BJ40: 123.59543 | BK40: 123.80132 | BL40: 125.71907 | BM40: 125.29457 | BN40: 127.01487 | BO40: 127.6416 | BP40: 126.6379 | BQ40: 128.63157 | BR40: 127.85521 | BS40: 129.23819 | BT40: 130.07883 | BU40: 126.6516 | BV40: 126.97514 | BW40: 132.09906 | BX40: 133.47168 | BY40: 132.7137 | BZ40: 132.80103 | CA40: 135.92893 | CB40: 133.85747 | CC40: 137.27222 | CD40: 134.69593 | CE40: 133.39563 | CF40: 132.05566 | CG40: 129.1125 | CH40: 128.21741 | CI40: 127.3409 | CJ40: 129.16893 | CK40: 133.31163 | CL40: 133.00413 | CM40: 131.21539 | CN40: 134.3199 | CO40: 133.49842 | CP40: 128.40304 | CQ40: 126.2526 | CR40: 124.89546 | CS40: 122.1117 | CT40: 123.01646 | CU40: 123.04959 | CV40: 126.60031 | CW40: 127.32064 | CX40: 134.49361 | CY40: 131.12183 | CZ40: 131.12919 | DA40: 127.25437 | DB40: 122.33318 | DC40: 120.90744 | DD40: 118.84122 | DE40: 115.84602 | DF40: 110.10016 | DG40: 110.6196 | DH40: 108.50154 | DI40: 110.35654 | DJ40: 111.22212 | DK40: 108.89335 | DL40: 108.52357 | DM40: 111.25335 | DN40: 110.32645 | DO40: 103.65028 | DP40: 105.6472 | DQ40: 106.23796 | DR40: 97.470109 | DS40: 115.18096 | DT40: 114.51798 | DU40: 109.76781 | DV40: 118.23647 | DW40: 121.80205 | DX40: 121.90718 | DY40: 125.55541 | DZ40: 91.18588 | EA40: 90.681916 | EB40: 112.97303 | EC40: 122.88406 | ED40: 133.96794 | EE40: 131.52994 | EF40: 141.37925 | EG40: 148.06012 | EH40: 160.11588 | EI40: 170.30695 | EJ40: 193.12976 | EK40: 228.70351 | EL40: 236.2508 | EM40: 240.24981 | EN40: 214.10149 | EO40: 179.77456 | EP40: 172.4898 | EQ40: 148.66698 | ER40: 125.16372 | ES40: 124.67053 | ET40: 128.01464 | EU40: 130.76307 | EV40: 134.20231 | EW40: 138.83699 | EX40: 134.74314 | EY40: 134.49299 | EZ40: 138.33188 | FA40: 143.37074 | FB40: 149.15831 | FC40: 149.62935 | FD40: 147.79325 | FE40: 146.0832 | FF40: 149.77023 | FG40: 141.22502 | FH40: 149.87595 | FI40: 148.48258 | FJ40: 140.30636 | FK40: 140.31796 | FL40: 135.72202 | FM40: 134.41123 | FN40: 135.27092 | FO40: 138.80949 | FP40: 135.43919 | FQ40: 142.88959 | FR40: 135.89549 | FS40: 140.83905 | FT40: 136.69797 | FU40: 146.25691 | FV40: 158.49497 | FW40: 163.57638 | FX40: 169.581 | FY40: 171.65036 | FZ40: 161.97845 | GA40: 167.48897 | GB40: 165.89976 | GC40: 172.21535 | GD40: 172.53311 | GE40: 179.83724 | GF40: 184.24036 | GG40: 161.26928 | GH40: 156.7553 | GI40: 148.7542 | GJ40: 146.50659 | GK40: 138.48013 | GL40: 126.92574 | GM40: 117.40983 | GN40: 114.46217 | GO40: 106.10277 | GP40: 101.47525 | GQ40: 101.47872 | GR40: 97.901557 | GS40: 98.221187 | GT40: 94.120349 | GU40: 93.488359
A41: (Cartera irregular - Previsiones) / Financiaciones | B41: 1.8430371 | C41: 3.2253594 | D41: 1.0813234 | E41: -0.49713032 | F41: -0.59968456 | G41: -0.45804287 | H41: -0.44121548 | I41: -0.27632425 | J41: -0.29810973 | K41: -0.32323335 | L41: -0.38999383 | M41: -0.44654368 | N41: -0.46588507 | O41: -0.51201183 | P41: -0.52578868 | Q41: -0.55326305 | R41: -0.59427643 | S41: -0.59593468 | T41: -0.65015389 | U41: -0.79517969 | V41: -0.82723741 | W41: -0.85690873 | X41: -0.88177536 | Y41: -1.1183463 | Z41: -1.0938579 | AA41: -0.84802109 | AB41: -0.90227825 | AC41: -0.94356741 | AD41: -0.93912513 | AE41: -0.98094355 | AF41: -0.94533782 | AG41: -0.95178317 | AH41: -0.89306046 | AI41: -0.845528 | AJ41: -0.86059418 | AK41: -0.78002163 | AL41: -0.70113194 | AM41: -0.84117046 | AN41: -0.80083326 | AO41: -0.72532967 | AP41: -0.77231687 | AQ41: -0.65336003 | AR41: -0.64456541 | AS41: -0.64551292 | AT41: -0.59720216 | AU41: -0.51869825 | AV41: -0.59654743 | AW41: -0.57183805 | AX41: -0.51378039 | AY41: -0.4970162 | AZ41: -0.52078447 | BA41: -0.52741783 | BB41: -0.49630055 | BC41: -0.5114539 | BD41: -0.52335992 | BE41: -0.61727668 | BF41: -0.73378209 | BG41: -0.66629345 | BH41: -0.62504982 | BI41: -0.54416653 | BJ41: -0.56722202 | BK41: -0.55911869 | BL41: -0.60172766 | BM41: -0.6092889 | BN41: -0.61307225 | BO41: -0.63430227 | BP41: -0.61590228 | BQ41: -0.61670586 | BR41: -0.61073347 | BS41: -0.62934017 | BT41: -0.64931287 | BU41: -0.60019107 | BV41: -0.59796786 | BW41: -0.65139448 | BX41: -0.67384044 | BY41: -0.64158711 | BZ41: -0.63906537 | CA41: -0.66965982 | CB41: -0.63127176 | CC41: -0.6728985 | CD41: -0.65071805 | CE41: -0.64659026 | CF41: -0.61469116 | CG41: -0.56849166 | CH41: -0.55466295 | CI41: -0.53651931 | CJ41: -0.57128674 | CK41: -0.65475917 | CL41: -0.6306535 | CM41: -0.60451372 | CN41: -0.63548866 | CO41: -0.58250615 | CP41: -0.52474505 | CQ41: -0.4973991 | CR41: -0.47104674 | CS41: -0.44087752 | CT41: -0.45478647 | CU41: -0.45535679 | CV41: -0.49841512 | CW41: -0.51176924 | CX41: -0.60322709 | CY41: -0.55619365 | CZ41: -0.56780244 | DA41: -0.49243243 | DB41: -0.43051055 | DC41: -0.41406222 | DD41: -0.38911019 | DE41: -0.33779731 | DF41: -0.23482837 | DG41: -0.23927903 | DH41: -0.20780415 | DI41: -0.24930139 | DJ41: -0.2793439 | DK41: -0.25323666 | DL41: -0.25262864 | DM41: -0.34087538 | DN41: -0.34894992 | DO41: -0.1394334 | DP41: -0.2307113 | DQ41: -0.26888713 | DR41: 0.11024953 | DS41: -0.6778067 | DT41: -0.67837067 | DU41: -0.46102159 | DV41: -0.83681526 | DW41: -1.018968 | DX41: -1.0376113 | DY41: -1.2251119 | DZ41: 0.45097041 | EA41: 0.48937186 | EB41: -0.53350997 | EC41: -0.89752285 | ED41: -1.350007 | EE41: -1.1982821 | EF41: -1.5386006 | EG41: -1.727862 | EH41: -1.9652388 | EI41: -2.0334313 | EJ41: -2.4412152 | EK41: -3.0499362 | EL41: -3.0766249 | EM41: -3.0650449 | EN41: -2.7592029 | EO41: -2.3378059 | EP41: -2.2167472 | EQ41: -1.7296 | ER41: -1.0693845 | ES41: -1.0065016 | ET41: -1.0828241 | EU41: -1.1472758 | EV41: -1.1630289 | EW41: -1.2113215 | EX41: -1.1022048 | EY41: -1.0768111 | EZ41: -1.063744 | FA41: -1.1090885 | FB41: -1.1276991 | FC41: -1.056025 | FD41: -0.98482538 | FE41: -0.95673622 | FF41: -1.0271674 | FG41: -0.85872041 | FH41: -1.030477 | FI41: -1.0295427 | FJ41: -0.90889743 | FK41: -0.90256921 | FL41: -0.8154445 | FM41: -0.77124868 | FN41: -0.76211964 | FO41: -0.82277613 | FP41: -0.76996738 | FQ41: -0.88014505 | FR41: -0.72036017 | FS41: -0.7959136 | FT41: -0.67521119 | FU41: -0.87978156 | FV41: -1.0968235 | FW41: -1.1209207 | FX41: -1.1529377 | FY41: -1.1408393 | FZ41: -1.0290772 | GA41: -1.040077 | GB41: -1.016428 | GC41: -1.0858601 | GD41: -1.0778131 | GE41: -1.1273576 | GF41: -1.1743218 | GG41: -0.98032552 | GH41: -0.99266063 | GI41: -0.94996287 | GJ41: -1.0078893 | GK41: -0.95815799 | GL41: -0.78024803 | GM41: -0.57322801 | GN41: -0.51640126 | GO41: -0.26373361 | GP41: -0.069191779 | GQ41: -0.075442695 | GR41: 0.12211588 | GS41: 0.10373745 | GT41: 0.38663178 | GU41: 0.44607193
A42: (Cartera irregular - Previsiones) / PN | B42: 2.2035306 | C42: 4.4700224 | D42: 1.9215094 | E42: -0.9933684 | F42: -1.3319199 | G42: -1.3672277 | H42: -1.3397839 | I42: -0.85785188 | J42: -0.91149603 | K42: -0.97365687 | L42: -1.1885585 | M42: -1.435833 | N42: -1.6243466 | O42: -1.7843709 | P42: -1.828678 | Q42: -1.9336226 | R42: -2.1258959 | S42: -2.1876624 | T42: -2.4519139 | U42: -3.0927866 | V42: -3.2158687 | W42: -3.3371071 | X42: -3.5507745 | Y42: -4.8383702 | Z42: -4.8007053 | AA42: -3.8172161 | AB42: -4.0597802 | AC42: -4.302703 | AD42: -4.4115374 | AE42: -4.5913214 | AF42: -4.4020161 | AG42: -4.4320298 | AH42: -4.0815253 | AI42: -3.8459004 | AJ42: -3.8560764 | AK42: -3.4514171 | AL42: -3.1055435 | AM42: -3.7279561 | AN42: -3.5168607 | AO42: -3.2430678 | AP42: -3.4297315 | AQ42: -2.9089382 | AR42: -2.9161624 | AS42: -2.9826841 | AT42: -2.691956 | AU42: -2.3191621 | AV42: -2.6776407 | AW42: -2.5767088 | AX42: -2.3287102 | AY42: -2.2699372 | AZ42: -2.3474645 | BA42: -2.3906562 | BB42: -2.2547741 | BC42: -2.31058 | BD42: -2.3555934 | BE42: -2.7966574 | BF42: -3.1978966 | BG42: -2.8171723 | BH42: -2.600981 | BI42: -2.2131128 | BJ42: -2.2818822 | BK42: -2.2894 | BL42: -2.4148613 | BM42: -2.4222297 | BN42: -2.4692793 | BO42: -2.5644858 | BP42: -2.5151649 | BQ42: -2.5173098 | BR42: -2.4688234 | BS42: -2.5453251 | BT42: -2.6220889 | BU42: -2.4665442 | BV42: -2.4613141 | BW42: -2.7503975 | BX42: -2.7970578 | BY42: -2.6865538 | BZ42: -2.6535501 | CA42: -2.7871769 | CB42: -2.6742942 | CC42: -2.8475617 | CD42: -2.713498 | CE42: -2.6156574 | CF42: -2.4831306 | CG42: -2.3300064 | CH42: -2.2317444 | CI42: -2.1071005 | CJ42: -2.2218497 | CK42: -2.624146 | CL42: -2.5464742 | CM42: -2.4780199 | CN42: -2.6849952 | CO42: -2.5080329 | CP42: -2.2253107 | CQ42: -2.1029868 | CR42: -2.0106948 | CS42: -1.8951599 | CT42: -1.9711768 | CU42: -1.8272471 | CV42: -1.9915517 | CW42: -2.0405023 | CX42: -2.4504988 | CY42: -2.2739007 | CZ42: -2.3096879 | DA42: -1.9082863 | DB42: -1.6207186 | DC42: -1.5630367 | DD42: -1.4652506 | DE42: -1.3184084 | DF42: -0.95738929 | DG42: -0.96934619 | DH42: -0.8186917 | DI42: -1.0620846 | DJ42: -1.1810315 | DK42: -1.0047245 | DL42: -0.989081 | DM42: -1.2811747 | DN42: -1.2363115 | DO42: -0.48314114 | DP42: -0.78776989 | DQ42: -0.93941853 | DR42: 0.42586602 | DS42: -2.1458859 | DT42: -2.0975572 | DU42: -1.5141397 | DV42: -2.4841977 | DW42: -2.9627337 | DX42: -2.9537885 | DY42: -3.3491048 | DZ42: 0.9602184 | EA42: 1.0139717 | EB42: -1.1149703 | EC42: -1.9304453 | ED42: -2.8269771 | EE42: -2.4577134 | EF42: -3.0921118 | EG42: -3.4405368 | EH42: -3.8577291 | EI42: -4.0139988 | EJ42: -4.7697593 | EK42: -5.8358524 | EL42: -5.7352696 | EM42: -5.6009079 | EN42: -4.8064138 | EO42: -3.9701383 | EP42: -3.7051447 | EQ42: -2.8398573 | ER42: -1.6813513 | ES42: -1.6003763 | ET42: -1.7286295 | EU42: -1.8517309 | EV42: -1.9284816 | EW42: -2.0072642 | EX42: -1.7702967 | EY42: -1.6931098 | EZ42: -1.6289969 | FA42: -1.6461299 | FB42: -1.7116854 | FC42: -1.6324242 | FD42: -1.4760764 | FE42: -1.3811516 | FF42: -1.4089162 | FG42: -1.1779478 | FH42: -1.4120274 | FI42: -1.381678 | FJ42: -1.1760743 | FK42: -1.1362353 | FL42: -1.0506106 | FM42: -1.0423598 | FN42: -1.0282268 | FO42: -1.0852135 | FP42: -0.98392832 | FQ42: -1.1217205 | FR42: -0.90669334 | FS42: -0.96361463 | FT42: -0.75104192 | FU42: -0.8380324 | FV42: -0.95235294 | FW42: -0.93816485 | FX42: -0.93096417 | FY42: -0.91689853 | FZ42: -1.0044948 | GA42: -1.1223868 | GB42: -1.1331857 | GC42: -1.2580997 | GD42: -1.3544989 | GE42: -1.5293575 | GF42: -1.7336491 | GG42: -1.5411372 | GH42: -1.6044146 | GI42: -1.5714672 | GJ42: -1.7424066 | GK42: -1.6991159 | GL42: -1.4667783 | GM42: -1.2278069 | GN42: -1.1512805 | GO42: -0.59999135 | GP42: -0.16458555 | GQ42: -0.17789212 | GR42: 0.28760789 | GS42: 0.24521859 | GT42: 0.88328903 | GU42: 0.98709154
A43: Fuente: BCRA
A48: Bancos privados extranjeros
A49: En porcentaje | B49: 37591 | C49: 37956 | D49: 38322 | E49: 38687 | F49: 39052 | G49: 39417 | H49: 39783 | I49: 40148 | J49: 40179 | K49: 40210 | L49: 40238 | M49: 40269 | N49: 40299 | O49: 40330 | P49: 40360 | Q49: 40391 | R49: 40422 | S49: 40452 | T49: 40483 | U49: 40513 | V49: 40544 | W49: 40575 | X49: 40603 | Y49: 40634 | Z49: 40664 | AA49: 40695 | AB49: 40725 | AC49: 40756 | AD49: 40787 | AE49: 40817 | AF49: 40848 | AG49: 40878 | AH49: 40909 | AI49: 40940 | AJ49: 40969 | AK49: 41000 | AL49: 41030 | AM49: 41061 | AN49: 41091 | AO49: 41122 | AP49: 41153 | AQ49: 41183 | AR49: 41214 | AS49: 41244 | AT49: 41275 | AU49: 41306 | AV49: 41334 | AW49: 41365 | AX49: 41395 | AY49: 41426 | AZ49: 41456 | BA49: 41487 | BB49: 41518 | BC49: 41548 | BD49: 41579 | BE49: 41609 | BF49: 41640 | BG49: 41671 | BH49: 41699 | BI49: 41730 | BJ49: 41760 | BK49: 41791 | BL49: 41821 | BM49: 41852 | BN49: 41883 | BO49: 41913 | BP49: 41944 | BQ49: 41974 | BR49: 42005 | BS49: 42036 | BT49: 42064 | BU49: 42095 | BV49: 42125 | BW49: 42156 | BX49: 42186 | BY49: 42217 | BZ49: 42248 | CA49: 42278 | CB49: 42309 | CC49: 42339 | CD49: 42370 | CE49: 42401 | CF49: 42430 | CG49: 42461 | CH49: 42491 | CI49: 42522 | CJ49: 42552 | CK49: 42583 | CL49: 42614 | CM49: 42644 | CN49: 42675 | CO49: 42705 | CP49: 42736 | CQ49: 42767 | CR49: 42795 | CS49: 42826 | CT49: 42856 | CU49: 42887 | CV49: 42917 | CW49: 42948 | CX49: 42979 | CY49: 43009 | CZ49: 43040 | DA49: 43070 | DB49: 43101 | DC49: 43132 | DD49: 43160 | DE49: 43191 | DF49: 43221 | DG49: 43252 | DH49: 43282 | DI49: 43313 | DJ49: 43344 | DK49: 43374 | DL49: 43405 | DM49: 43435 | DN49: 43466 | DO49: 43497 | DP49: 43525 | DQ49: 43556 | DR49: 43586 | DS49: 43617 | DT49: 43647 | DU49: 43678 | DV49: 43709 | DW49: 43739 | DX49: 43770 | DY49: 43800 | DZ49: 43831 | EA49: 43862 | EB49: 43891 | EC49: 43922 | ED49: 43952 | EE49: 43983 | EF49: 44013 | EG49: 44044 | EH49: 44075 | EI49: 44105 | EJ49: 44136 | EK49: 44166 | EL49: 44197 | EM49: 44228 | EN49: 44256 | EO49: 44287 | EP49: 44317 | EQ49: 44348 | ER49: 44378 | ES49: 44409 | ET49: 44440 | EU49: 44470 | EV49: 44501 | EW49: 44531 | EX49: 44562 | EY49: 44593 | EZ49: 44621 | FA49: 44652 | FB49: 44682 | FC49: 44713 | FD49: 44743 | FE49: 44774 | FF49: 44805 | FG49: 44835 | FH49: 44866 | FI49: 44896 | FJ49: 44927 | FK49: 44958 | FL49: 44986 | FM49: 45017 | FN49: 45047 | FO49: 45078 | FP49: 45108 | FQ49: 45139 | FR49: 45170 | FS49: 45200 | FT49: 45231 | FU49: 45261 | FV49: 45292 | FW49: 45323 | FX49: 45352 | FY49: 45383 | FZ49: 45413 | GA49: 45444 | GB49: 45474 | GC49: 45505 | GD49: 45536 | GE49: 45566 | GF49: 45597 | GG49: 45627 | GH49: 45658 | GI49: 45689 | GJ49: 45717 | GK49: 45748 | GL49: 45778 | GM49: 45809 | GN49: 45839 | GO49: 45870 | GP49: 45901 | GQ49: 45931 | GR49: 45962 | GS49: 45992 | GT49: 46023 | GU49: 46054
A50: Cartera irregular total | B50: 23.146237 | C50: 18.935737 | D50: 8.7412488 | E50: 4.188887 | F50: 2.9813001 | G50: 1.919322 | H50: 2.0357328 | I50: 2.4293672 | J50: 2.4951079 | K50: 2.4260033 | L50: 2.3516151 | M50: 2.2066937 | N50: 2.1108945 | O50: 2.0366804 | P50: 1.9547724 | Q50: 1.8559262 | R50: 1.668169 | S50: 1.547666 | T50: 1.4279695 | U50: 1.3548021 | V50: 1.2748802 | W50: 1.2264564 | X50: 1.1427256 | Y50: 1.0954841 | Z50: 1.0331635 | AA50: 1.0006433 | AB50: 0.91892858 | AC50: 0.88396166 | AD50: 0.84667289 | AE50: 0.83141011 | AF50: 0.85466207 | AG50: 0.91822997 | AH50: 0.9825943 | AI50: 1.0378992 | AJ50: 1.0692271 | AK50: 1.1174837 | AL50: 1.1949659 | AM50: 1.245607 | AN50: 1.2774166 | AO50: 1.2756201 | AP50: 1.3065162 | AQ50: 1.328955 | AR50: 1.3311097 | AS50: 1.3424261 | AT50: 1.3950357 | AU50: 1.4449427 | AV50: 1.4948052 | AW50: 1.5153188 | AX50: 1.5589461 | AY50: 1.5565894 | AZ50: 1.5221987 | BA50: 1.516603 | BB50: 1.4248411 | BC50: 1.4011041 | BD50: 1.3844821 | BE50: 1.3706405 | BF50: 1.3815604 | BG50: 1.4817097 | BH50: 1.5271519 | BI50: 1.5375485 | BJ50: 1.6859007 | BK50: 1.6663213 | BL50: 1.6502862 | BM50: 1.7040252 | BN50: 1.6854211 | BO50: 1.7002619 | BP50: 1.700588 | BQ50: 1.6230733 | BR50: 1.6396446 | BS50: 1.6297755 | BT50: 1.5963595 | BU50: 1.660192 | BV50: 1.6290673 | BW50: 1.5651433 | BX50: 1.507728 | BY50: 1.440255 | BZ50: 1.3773466 | CA50: 1.321711 | CB50: 1.2677408 | CC50: 1.2141015 | CD50: 1.2451164 | CE50: 1.2320637 | CF50: 1.2393406 | CG50: 1.2911187 | CH50: 1.3093963 | CI50: 1.3321832 | CJ50: 1.3388679 | CK50: 1.3721913 | CL50: 1.3203226 | CM50: 1.3291979 | CN50: 1.336481 | CO50: 1.3413125 | CP50: 1.4139402 | CQ50: 1.4802417 | CR50: 1.5650464 | CS50: 1.6282214 | CT50: 1.6865936 | CU50: 1.7187114 | CV50: 1.6878995 | CW50: 1.6255879 | CX50: 1.6566081 | CY50: 1.6856171 | CZ50: 1.7586109 | DA50: 1.6874556 | DB50: 1.7384448 | DC50: 1.7573214 | DD50: 1.8533534 | DE50: 1.8339896 | DF50: 1.9134889 | DG50: 1.9392466 | DH50: 2.1053123 | DI50: 2.0248872 | DJ50: 2.1188816 | DK50: 2.651741 | DL50: 3.0546095 | DM50: 3.1209128 | DN50: 3.4939156 | DO50: 3.6938583 | DP50: 3.7033293 | DQ50: 3.7178414 | DR50: 3.8919883 | DS50: 4.0267879 | DT50: 4.0299639 | DU50: 3.8618916 | DV50: 4.0440461 | DW50: 4.0251099 | DX50: 4.3614281 | DY50: 3.9801831 | DZ50: 4.2674294 | EA50: 4.3651939 | EB50: 3.5322287 | EC50: 3.4463243 | ED50: 3.2988269 | EE50: 2.8256983 | EF50: 2.7347694 | EG50: 2.3724135 | EH50: 2.2301242 | EI50: 2.0748808 | EJ50: 2.1509731 | EK50: 2.0640212 | EL50: 2.0502246 | EM50: 1.9491599 | EN50: 2.1061795 | EO50: 2.4173157 | EP50: 2.5913064 | EQ50: 2.9245362 | ER50: 3.3224046 | ES50: 3.3565646 | ET50: 3.0412556 | EU50: 2.9144623 | EV50: 2.6782828 | EW50: 2.5327358 | EX50: 2.5157991 | EY50: 2.3648862 | EZ50: 2.0729419 | FA50: 1.9115973 | FB50: 1.7474318 | FC50: 1.6185578 | FD50: 1.4774568 | FE50: 1.4361201 | FF50: 1.3859822 | FG50: 1.3905752 | FH50: 1.353892 | FI50: 1.4432279 | FJ50: 1.4881043 | FK50: 1.4778414 | FL50: 1.5129461 | FM50: 1.4496632 | FN50: 1.4681909 | FO50: 1.4482007 | FP50: 1.4850629 | FQ50: 1.4709243 | FR50: 1.4484721 | FS50: 1.3628365 | FT50: 1.261227 | FU50: 1.2660207 | FV50: 1.2199358 | FW50: 1.1708201 | FX50: 1.192854 | FY50: 1.2720911 | FZ50: 1.3497275 | GA50: 1.3399148 | GB50: 1.3740135 | GC50: 1.3965834 | GD50: 1.4086874 | GE50: 1.3697972 | GF50: 1.3941466 | GG50: 1.4353331 | GH50: 1.4816862 | GI50: 1.6096823 | GJ50: 1.7649509 | GK50: 1.916391 | GL50: 2.2645711 | GM50: 2.6148939 | GN50: 2.8982187 | GO50: 3.3626082 | GP50: 3.7005116 | GQ50: 3.9597627 | GR50: 4.6004666 | GS50: 5.026078 | GT50: 5.9584345 | GU50: 6.6523338
A51: Previsiones / Cartera irregular | B51: 63.420623 | C51: 65.215098 | D51: 84.041028 | E51: 97.069279 | F51: 111.14259 | G51: 131.45728 | H51: 125.51809 | I51: 128.73316 | J51: 126.24453 | K51: 129.70297 | L51: 129.29475 | M51: 131.38065 | N51: 132.6141 | O51: 133.25039 | P51: 136.35808 | Q51: 139.17263 | R51: 148.04019 | S51: 153.77155 | T51: 159.50526 | U51: 165.30953 | V51: 171.02866 | W51: 174.46626 | X51: 180.12929 | Y51: 167.86283 | Z51: 171.13933 | AA51: 183.40545 | AB51: 195.83437 | AC51: 203.14911 | AD51: 207.79224 | AE51: 212.47803 | AF51: 208.74756 | AG51: 196.89119 | AH51: 186.75508 | AI51: 178.02857 | AJ51: 175.57095 | AK51: 165.45674 | AL51: 159.19045 | AM51: 155.34288 | AN51: 152.27794 | AO51: 156.97303 | AP51: 156.03994 | AQ51: 153.88122 | AR51: 155.31172 | AS51: 154.34975 | AT51: 151.26508 | AU51: 147.46791 | AV51: 145.7087 | AW51: 144.98908 | AX51: 141.81531 | AY51: 141.42638 | AZ51: 145.84674 | BA51: 146.44943 | BB51: 153.27776 | BC51: 154.80145 | BD51: 158.12049 | BE51: 165.50312 | BF51: 167.68068 | BG51: 164.13861 | BH51: 161.99434 | BI51: 161.57671 | BJ51: 150.59608 | BK51: 150.69225 | BL51: 152.36625 | BM51: 151.21687 | BN51: 153.58798 | BO51: 153.31696 | BP51: 153.45618 | BQ51: 157.37415 | BR51: 156.63598 | BS51: 156.23245 | BT51: 156.23917 | BU51: 153.74456 | BV51: 154.49516 | BW51: 156.90146 | BX51: 160.1979 | BY51: 162.76714 | BZ51: 171.44905 | CA51: 175.69714 | CB51: 179.35855 | CC51: 182.86548 | CD51: 180.35384 | CE51: 181.15234 | CF51: 179.9018 | CG51: 171.85284 | CH51: 169.56558 | CI51: 164.83451 | CJ51: 164.52284 | CK51: 159.98582 | CL51: 163.79083 | CM51: 162.73729 | CN51: 160.71845 | CO51: 158.19796 | CP51: 155.28919 | CQ51: 152.5377 | CR51: 144.57189 | CS51: 146.20065 | CT51: 141.00981 | CU51: 138.10074 | CV51: 139.02794 | CW51: 142.46917 | CX51: 141.13308 | CY51: 141.05671 | CZ51: 134.34029 | DA51: 136.75167 | DB51: 134.54266 | DC51: 134.18728 | DD51: 131.34723 | DE51: 131.26497 | DF51: 128.21962 | DG51: 128.01495 | DH51: 124.81682 | DI51: 127.66655 | DJ51: 128.4822 | DK51: 113.4839 | DL51: 100.92652 | DM51: 99.306982 | DN51: 94.93024 | DO51: 95.903741 | DP51: 98.628572 | DQ51: 98.651165 | DR51: 99.900055 | DS51: 98.79407 | DT51: 98.756164 | DU51: 100.34583 | DV51: 101.73993 | DW51: 102.55309 | DX51: 99.958671 | DY51: 106.57386 | DZ51: 122.74614 | EA51: 120.44065 | EB51: 145.70566 | EC51: 151.7144 | ED51: 163.16388 | EE51: 191.60972 | EF51: 196.01578 | EG51: 211.31773 | EH51: 235.23188 | EI51: 254.58905 | EJ51: 233.54918 | EK51: 250.28357 | EL51: 252.57488 | EM51: 264.82737 | EN51: 234.03058 | EO51: 205.69008 | EP51: 189.259 | EQ51: 165.72739 | ER51: 150.19864 | ES51: 148.34065 | ET51: 157.87218 | EU51: 160.75397 | EV51: 162.15326 | EW51: 166.71991 | EX51: 160.07888 | EY51: 166.79504 | EZ51: 180.99207 | FA51: 187.05069 | FB51: 195.14395 | FC51: 194.81821 | FD51: 206.64737 | FE51: 212.09049 | FF51: 223.01474 | FG51: 213.11653 | FH51: 224.89318 | FI51: 222.86973 | FJ51: 210.41634 | FK51: 212.14169 | FL51: 209.7129 | FM51: 213.03024 | FN51: 211.42834 | FO51: 208.61443 | FP51: 196.85751 | FQ51: 196.53772 | FR51: 194.88252 | FS51: 214.51626 | FT51: 237.66057 | FU51: 237.90181 | FV51: 212.63126 | FW51: 222.85496 | FX51: 207.29054 | FY51: 207.0217 | FZ51: 181.10109 | GA51: 178.53003 | GB51: 175.41729 | GC51: 182.69606 | GD51: 182.97173 | GE51: 194.62939 | GF51: 207.13259 | GG51: 200.42345 | GH51: 200.78391 | GI51: 182.82006 | GJ51: 171.13537 | GK51: 164.10376 | GL51: 150.92584 | GM51: 130.33697 | GN51: 124.71759 | GO51: 117.08653 | GP51: 110.55355 | GQ51: 108.30702 | GR51: 98.537642 | GS51: 92.09097 | GT51: 87.120968 | GU51: 87.756623
A52: (Cartera irregular - Previsiones) / Financiaciones | B52: 8.4667492 | C52: 6.5867775 | D52: 1.3950134 | E52: 0.12276458 | F52: -0.3321939 | G52: -0.6037665 | H52: -0.51948003 | I52: -0.69803402 | J52: -0.65482927 | K52: -0.72059508 | L52: -0.68889978 | M52: -0.69247478 | N52: -0.68844918 | O52: -0.67720421 | P52: -0.71071777 | Q52: -0.72701503 | R52: -0.80139153 | S52: -0.83220396 | T52: -0.84971704 | U52: -0.88481492 | V52: -0.90553026 | W52: -0.91329621 | X52: -0.91565791 | Y52: -0.74342647 | Z52: -0.73498561 | AA52: -0.83459108 | AB52: -0.88064942 | AC52: -0.91179857 | AD52: -0.9126477 | AE52: -0.93515375 | AF52: -0.92942415 | AG52: -0.88968392 | AH52: -0.85245046 | AI52: -0.80985794 | AJ52: -0.80802506 | AK52: -0.73146832 | AL52: -0.70730571 | AM52: -0.68935474 | AN52: -0.66780709 | AO52: -0.72675947 | AP52: -0.73217094 | AQ52: -0.7160572 | AR52: -0.73625963 | AS52: -0.72960515 | AT52: -0.71516624 | AU52: -0.6858841 | AV52: -0.68325601 | AW52: -0.68172806 | AX52: -0.65187819 | AY52: -0.64483862 | AZ52: -0.6978785 | BA52: -0.7044534 | BB52: -0.75912334 | BC52: -0.76782532 | BD52: -0.80466784 | BE52: -0.89781225 | BF52: -0.93504949 | BG52: -0.95034798 | BH52: -0.94674772 | BI52: -0.94677179 | BJ52: -0.85299976 | BK52: -0.84469584 | BL52: -0.86419296 | BM52: -0.87274832 | BN52: -0.90318312 | BO52: -0.90652794 | BP52: -0.90906931 | BQ52: -0.93122455 | BR52: -0.92862872 | BS52: -0.91646272 | BT52: -0.89777927 | BU52: -0.89226283 | BV52: -0.88776288 | BW52: -0.8905894 | BX52: -0.90762056 | BY52: -0.90400688 | BZ52: -0.98410113 | CA52: -1.0004975 | CB52: -1.0060607 | CC52: -1.006071 | CD52: -1.0004988 | CE52: -0.99984848 | CF52: -0.99025539 | CG52: -0.92770543 | CH52: -0.9108892 | CI52: -0.86371443 | CJ52: -0.86387554 | CK52: -0.82312022 | CL52: -0.84224476 | CM52: -0.83390267 | CN52: -0.81149058 | CO52: -0.78061656 | CP52: -0.78175608 | CQ52: -0.77768499 | CR52: -0.69757073 | CS52: -0.7522488 | CT52: -0.69166883 | CU52: -0.65484184 | CV52: -0.65875244 | CW52: -0.69037373 | CX52: -0.68141396 | CY52: -0.69205887 | CZ52: -0.60391218 | DA52: -0.62016806 | DB52: -0.60050514 | DC52: -0.60078046 | DD52: -0.58097497 | DE52: -0.57339634 | DF52: -0.53997935 | DG52: -0.54327905 | DH52: -0.52247154 | DI52: -0.56021646 | DJ52: -0.60350405 | DK52: -0.35755816 | DL52: -0.028301672 | DM52: 0.021628483 | DN52: 0.17713312 | DO52: 0.15131001 | DP52: 0.050788478 | DQ52: 0.050147539 | DR52: 0.0038898461 | DS52: 0.048560237 | DT52: 0.05012615 | DU52: -0.013355749 | DV52: -0.070363425 | DW52: -0.10276482 | DX52: 0.0018025286 | DY52: -0.26165175 | DZ52: -0.97067569 | EA52: -0.89227418 | EB52: -1.6144285 | EC52: -1.7822459 | ED52: -2.0836672 | EE52: -2.5886143 | EF52: -2.6258102 | EG52: -2.6409168 | EH52: -3.0158388 | EI52: -3.2075385 | EJ52: -2.872607 | EK52: -3.1018847 | EL52: -3.1281277 | EM52: -3.2127489 | EN52: -2.8229245 | EO52: -2.5548629 | EP52: -2.3129743 | EQ52: -1.9222214 | ER52: -1.6678018 | ES52: -1.6225853 | ET52: -1.7600408 | EU52: -1.7706517 | EV52: -1.66464 | EW52: -1.689839 | EX52: -1.511464 | EY52: -1.5796267 | EZ52: -1.6789186 | FA52: -1.6640585 | FB52: -1.6625757 | FC52: -1.5346876 | FD52: -1.5756688 | FE52: -1.6097541 | FF52: -1.7049623 | FG52: -1.5729704 | FH52: -1.6909187 | FI52: -1.7732901 | FJ52: -1.6431104 | FK52: -1.6572763 | FL52: -1.6598971 | FM52: -1.6385578 | FN52: -1.6359807 | FO52: -1.5729549 | FP52: -1.4383949 | FQ52: -1.4199969 | FR52: -1.3743468 | FS52: -1.5606695 | FT52: -1.7362123 | FU52: -1.7458654 | FV52: -1.3740291 | FW52: -1.4384105 | FX52: -1.2798195 | FY52: -1.3614135 | FZ52: -1.0946437 | GA52: -1.0522354 | GB52: -1.0362437 | GC52: -1.1549194 | GD52: -1.1688122 | GE52: -1.2962308 | GF52: -1.4935854 | GG52: -1.4414111 | GH52: -1.4933013 | GI52: -1.3331398 | GJ52: -1.2555043 | GK52: -1.2284788 | GL52: -1.1532519 | GM52: -0.79327951 | GN52: -0.71636977 | GO52: -0.57455296 | GP52: -0.39053546 | GQ52: -0.32893838 | GR52: 0.067275269 | GS52: 0.397514 | GT52: 0.76738868 | GU52: 0.81447027
A53: (Cartera irregular - Previsiones) / PN | B53: 37.01338 | C53: 24.78471 | D53: 6.0809545 | E53: 0.52960827 | F53: -1.5595329 | G53: -3.0504695 | H53: -2.5425067 | I53: -2.545352 | J53: -2.3546813 | K53: -2.5874646 | L53: -2.4743221 | M53: -2.7575946 | N53: -2.8408251 | O53: -2.8500803 | P53: -2.9423734 | Q53: -3.0198937 | R53: -3.3788682 | S53: -3.4812129 | T53: -3.5214715 | U53: -3.7186912 | V53: -3.8085842 | W53: -4.0064233 | X53: -4.4406125 | Y53: -3.5633545 | Z53: -3.6101202 | AA53: -4.1323743 | AB53: -4.4310558 | AC53: -4.631777 | AD53: -4.776942 | AE53: -4.8540367 | AF53: -4.715447 | AG53: -4.4039648 | AH53: -4.1816932 | AI53: -3.9133919 | AJ53: -3.8860931 | AK53: -3.4369737 | AL53: -3.2678551 | AM53: -3.1795888 | AN53: -3.034608 | AO53: -3.3015373 | AP53: -3.3001059 | AQ53: -3.266861 | AR53: -3.3573402 | AS53: -3.436325 | AT53: -3.3238967 | AU53: -3.1194785 | AV53: -3.1080003 | AW53: -3.0949408 | AX53: -2.9472953 | AY53: -2.9991872 | AZ53: -3.2199636 | BA53: -3.2638664 | BB53: -3.5027362 | BC53: -3.5281004 | BD53: -3.6980805 | BE53: -4.1258258 | BF53: -3.9800856 | BG53: -3.9416628 | BH53: -3.905556 | BI53: -3.927425 | BJ53: -3.4672265 | BK53: -3.4767786 | BL53: -3.5089208 | BM53: -3.5068498 | BN53: -3.5997794 | BO53: -3.5782392 | BP53: -3.5879684 | BQ53: -3.7383696 | BR53: -3.6336437 | BS53: -3.5956817 | BT53: -3.52447 | BU53: -3.5635588 | BV53: -3.5738183 | BW53: -3.6666293 | BX53: -3.6968162 | BY53: -3.7258064 | BZ53: -4.0490665 | CA53: -4.1041176 | CB53: -4.1816838 | CC53: -4.2529234 | CD53: -4.1539767 | CE53: -4.1352081 | CF53: -3.9501737 | CG53: -3.804496 | CH53: -3.720999 | CI53: -3.5675874 | CJ53: -3.5963027 | CK53: -3.5169574 | CL53: -3.6309794 | CM53: -3.5736783 | CN53: -3.463851 | CO53: -3.4587935 | CP53: -3.4796165 | CQ53: -3.3695781 | CR53: -2.9584491 | CS53: -3.2903955 | CT53: -3.0930125 | CU53: -3.0696718 | CV53: -3.0372071 | CW53: -3.233411 | CX53: -3.2002961 | CY53: -3.278526 | CZ53: -2.8826954 | DA53: -3.0728642 | DB53: -2.6159429 | DC53: -2.6477545 | DD53: -2.507459 | DE53: -2.612088 | DF53: -2.5566854 | DG53: -2.6503132 | DH53: -2.4788477 | DI53: -2.8494101 | DJ53: -2.8990092 | DK53: -1.5542909 | DL53: -0.12493497 | DM53: 0.09053951 | DN53: 0.70582908 | DO53: 0.57685937 | DP53: 0.19419798 | DQ53: 0.19299558 | DR53: 0.01469867 | DS53: 0.17600287 | DT53: 0.17966384 | DU53: -0.053173683 | DV53: -0.25224874 | DW53: -0.35594338 | DX53: 0.0057268767 | DY53: -0.76022508 | DZ53: -2.3447859 | EA53: -2.1399225 | EB53: -3.9287781 | EC53: -4.3395572 | ED53: -5.0564193 | EE53: -6.3143186 | EF53: -6.1985543 | EG53: -6.0864754 | EH53: -6.7418806 | EI53: -7.0782262 | EJ53: -6.3996553 | EK53: -6.8247953 | EL53: -6.6169663 | EM53: -6.656166 | EN53: -5.7962047 | EO53: -5.2322596 | EP53: -4.7420849 | EQ53: -3.9676343 | ER53: -3.3867296 | ES53: -3.2403412 | ET53: -3.4623432 | EU53: -3.486177 | EV53: -3.319187 | EW53: -3.3703412 | EX53: -2.9288192 | EY53: -3.024402 | EZ53: -3.129305 | FA53: -3.1286857 | FB53: -3.0645023 | FC53: -2.8926854 | FD53: -2.8949027 | FE53: -2.8257934 | FF53: -2.8595559 | FG53: -2.6226922 | FH53: -2.8256281 | FI53: -2.8845138 | FJ53: -2.6257786 | FK53: -2.6179255 | FL53: -2.6466018 | FM53: -2.783239 | FN53: -2.7347649 | FO53: -2.6181666 | FP53: -2.3485498 | FQ53: -2.2806373 | FR53: -2.0612196 | FS53: -2.340221 | FT53: -2.3748131 | FU53: -2.1879515 | FV53: -1.6313962 | FW53: -1.6518569 | FX53: -1.4930107 | FY53: -1.5744563 | FZ53: -1.4184899 | GA53: -1.5010106 | GB53: -1.5730071 | GC53: -1.8164749 | GD53: -1.9297804 | GE53: -2.1735126 | GF53: -2.6143889 | GG53: -2.80736 | GH53: -2.9698766 | GI53: -2.7510927 | GJ53: -2.7385095 | GK53: -2.8045906 | GL53: -2.7416606 | GM53: -1.9656321 | GN53: -1.8875718 | GO53: -1.5584095 | GP53: -1.0885475 | GQ53: -0.87542983 | GR53: 0.18202178 | GS53: 1.1016281 | GT53: 2.0337324 | GU53: 2.0745337
A54: Al sector privado no financiero | B54: 40.219633 | C54: 33.551971 | D54: 15.926686 | E54: 5.8065816 | F54: 3.655123 | G54: 2.1863427 | H54: 2.3027874 | I54: 2.5990095 | J54: 2.6684046 | K54: 2.5895534 | L54: 2.5049847 | M54: 2.342017 | N54: 2.2406892 | O54: 2.1570168 | P54: 2.0701608 | Q54: 1.9656972 | R54: 1.7655779 | S54: 1.6386498 | T54: 1.5156688 | U54: 1.4359282 | V54: 1.3472466 | W54: 1.2945004 | X54: 1.2059513 | Y54: 1.1549299 | Z54: 1.0869432 | AA54: 1.0528815 | AB54: 0.96868954 | AC54: 0.93211705 | AD54: 0.89376782 | AE54: 0.87958594 | AF54: 0.90877431 | AG54: 0.97597781 | AH54: 1.0407735 | AI54: 1.1000379 | AJ54: 1.1340452 | AK54: 1.1827827 | AL54: 1.2654667 | AM54: 1.3185186 | AN54: 1.3500508 | AO54: 1.3463642 | AP54: 1.3780328 | AQ54: 1.4016283 | AR54: 1.4025355 | AS54: 1.4116165 | AT54: 1.465595 | AU54: 1.516405 | AV54: 1.5668894 | AW54: 1.585564 | AX54: 1.6336487 | AY54: 1.633651 | AZ54: 1.5904243 | BA54: 1.5827745 | BB54: 1.4872937 | BC54: 1.4632686 | BD54: 1.4446256 | BE54: 1.4333767 | BF54: 1.4410551 | BG54: 1.547597 | BH54: 1.5897568 | BI54: 1.5981095 | BJ54: 1.7533565 | BK54: 1.7286305 | BL54: 1.7056028 | BM54: 1.7603573 | BN54: 1.7447045 | BO54: 1.754456 | BP54: 1.7503332 | BQ54: 1.6694048 | BR54: 1.6861229 | BS54: 1.6741395 | BT54: 1.6452645 | BU54: 1.708017 | BV54: 1.6730309 | BW54: 1.6052953 | BX54: 1.55037 | BY54: 1.4773984 | BZ54: 1.4140961 | CA54: 1.3567599 | CB54: 1.2997322 | CC54: 1.2479659 | CD54: 1.278003 | CE54: 1.2627835 | CF54: 1.2740792 | CG54: 1.3279383 | CH54: 1.3423843 | CI54: 1.3686714 | CJ54: 1.3760127 | CK54: 1.4128431 | CL54: 1.3622127 | CM54: 1.3692792 | CN54: 1.3737256 | CO54: 1.3861163 | CP54: 1.4636592 | CQ54: 1.5297713 | CR54: 1.616305 | CS54: 1.6814295 | CT54: 1.7406997 | CU54: 1.7849035 | CV54: 1.7505079 | CW54: 1.6851366 | CX54: 1.7183147 | CY54: 1.7468843 | CZ54: 1.8288998 | DA54: 1.7575184 | DB54: 1.8032536 | DC54: 1.8226399 | DD54: 1.9176106 | DE54: 1.899036 | DF54: 1.98539 | DG54: 2.0097271 | DH54: 2.1836491 | DI54: 2.0987983 | DJ54: 2.1951037 | DK54: 2.751754 | DL54: 3.1595473 | DM54: 3.2378789 | DN54: 3.605972 | DO54: 3.8048854 | DP54: 3.8123827 | DQ54: 3.8401864 | DR54: 4.1446406 | DS54: 4.1397555 | DT54: 4.1437859 | DU54: 3.9642789 | DV54: 4.1510541 | DW54: 4.1288667 | DX54: 4.4739427 | DY54: 4.092259 | DZ54: 4.3812799 | EA54: 4.4885689 | EB54: 3.646255 | EC54: 3.5385702 | ED54: 3.3869913 | EE54: 2.9045443 | EF54: 2.8086103 | EG54: 2.4366027 | EH54: 2.2857804 | EI54: 2.1252412 | EJ54: 2.2048666 | EK54: 2.1215067 | EL54: 2.0954326 | EM54: 1.9922669 | EN54: 2.1513613 | EO54: 2.4781542 | EP54: 2.6576431 | EQ54: 2.9964557 | ER54: 3.3969577 | ES54: 3.4305148 | ET54: 3.1167329 | EU54: 2.9873899 | EV54: 2.7471189 | EW54: 2.6021922 | EX54: 2.5770402 | EY54: 2.4292585 | EZ54: 2.1284224 | FA54: 1.9663185 | FB54: 1.7933955 | FC54: 1.664647 | FD54: 1.5163955 | FE54: 1.4754251 | FF54: 1.4258569 | FG54: 1.4277725 | FH54: 1.3871504 | FI54: 1.4820342 | FJ54: 1.5177955 | FK54: 1.5068195 | FL54: 1.5445785 | FM54: 1.4789521 | FN54: 1.4956083 | FO54: 1.4791096 | FP54: 1.5097452 | FQ54: 1.4961236 | FR54: 1.4743589 | FS54: 1.3935722 | FT54: 1.2800385 | FU54: 1.2874592 | FV54: 1.2401721 | FW54: 1.1877737 | FX54: 1.2109793 | FY54: 1.2955307 | FZ54: 1.3708595 | GA54: 1.3641622 | GB54: 1.3971848 | GC54: 1.4249957 | GD54: 1.4380736 | GE54: 1.3975179 | GF54: 1.4187147 | GG54: 1.4651528 | GH54: 1.5130636 | GI54: 1.6444222 | GJ54: 1.8032035 | GK54: 1.9622781 | GL54: 2.3269581 | GM54: 2.6822682 | GN54: 2.9776685 | GO54: 3.4579296 | GP54: 3.8119488 | GQ54: 4.0909545 | GR54: 4.7639938 | GS54: 5.1934354 | GT54: 6.1319839 | GU54: 6.8445924
A55: Previsiones / Cartera irregular | B55: 64.361053 | C55: 68.074648 | D55: 84.673641 | E55: 97.011449 | F55: 110.90553 | G55: 130.56853 | H55: 124.91988 | I55: 128.28466 | J55: 125.83221 | K55: 129.29651 | L55: 128.93371 | M55: 131.01351 | N55: 132.19782 | O55: 132.82023 | P55: 135.83191 | Q55: 138.66961 | R55: 147.4943 | S55: 153.16697 | T55: 158.85058 | U55: 164.50472 | V55: 170.24076 | W55: 173.63013 | X55: 179.26388 | Y55: 167.04224 | Z55: 170.2256 | AA55: 181.96723 | AB55: 193.44583 | AC55: 200.6693 | AD55: 205.12063 | AE55: 209.76015 | AF55: 206.11437 | AG55: 194.45799 | AH55: 182.36792 | AI55: 173.77646 | AJ55: 171.36326 | AK55: 161.62974 | AL55: 155.83535 | AM55: 152.06697 | AN55: 149.17175 | AO55: 153.95756 | AP55: 153.13414 | AQ55: 151.04867 | AR55: 152.78212 | AS55: 151.71972 | AT55: 148.73174 | AU55: 144.9724 | AV55: 143.35 | AW55: 142.74795 | AX55: 139.60908 | AY55: 139.28078 | AZ55: 143.79439 | BA55: 144.38667 | BB55: 151.12067 | BC55: 152.63461 | BD55: 155.93912 | BE55: 163.22956 | BF55: 165.33585 | BG55: 162.01531 | BH55: 159.99674 | BI55: 159.63169 | BJ55: 148.94185 | BK55: 149.10503 | BL55: 150.80272 | BM55: 149.73211 | BN55: 152.11213 | BO55: 151.83655 | BP55: 152.09791 | BQ55: 155.96689 | BR55: 155.28608 | BS55: 154.93577 | BT55: 154.88274 | BU55: 152.61933 | BV55: 153.31174 | BW55: 155.69785 | BX55: 158.98316 | BY55: 162.76718 | BZ55: 170.10342 | CA55: 174.29401 | CB55: 177.82035 | CC55: 181.33632 | CD55: 178.89749 | CE55: 179.80234 | CF55: 178.47865 | CG55: 170.3271 | CH55: 168.16393 | CI55: 163.46213 | CJ55: 163.0551 | CK55: 158.6866 | CL55: 162.12164 | CM55: 161.01937 | CN55: 159.26788 | CO55: 156.46251 | CP55: 153.76812 | CQ55: 151.04442 | CR55: 143.15079 | CS55: 144.84929 | CT55: 139.62419 | CU55: 136.44864 | CV55: 137.40295 | CW55: 140.856 | CX55: 139.47767 | CY55: 139.52041 | CZ55: 132.69654 | DA55: 134.99923 | DB55: 132.97235 | DC55: 132.65498 | DD55: 130.04281 | DE55: 129.96258 | DF55: 126.87806 | DG55: 126.67776 | DH55: 123.45353 | DI55: 126.36581 | DJ55: 127.13695 | DK55: 112.39777 | DL55: 100.12903 | DM55: 98.498346 | DN55: 94.272141 | DO55: 95.364958 | DP55: 98.073202 | DQ55: 98.124568 | DR55: 154.73283 | DS55: 98.319992 | DT55: 98.29565 | DU55: 99.858526 | DV55: 101.25993 | DW55: 102.08783 | DX55: 99.521136 | DY55: 106.06733 | DZ55: 122.25766 | EA55: 119.97219 | EB55: 145.20728 | EC55: 151.33447 | ED55: 162.73546 | EE55: 191.12093 | EF55: 194.95881 | EG55: 210.11039 | EH55: 233.93377 | EI55: 252.46484 | EJ55: 231.35924 | EK55: 247.49425 | EL55: 250.15644 | EM55: 263.05369 | EN55: 232.78286 | EO55: 204.28058 | EP55: 187.90465 | EQ55: 164.77634 | ER55: 149.30994 | ES55: 147.55057 | ET55: 157.23319 | EU55: 160.09246 | EV55: 161.29167 | EW55: 165.79415 | EX55: 159.27742 | EY55: 165.90667 | EZ55: 179.62746 | FA55: 184.48363 | FB55: 193.69529 | FC55: 193.19566 | FD55: 204.26798 | FE55: 210.70928 | FF55: 220.95975 | FG55: 211.10905 | FH55: 222.27166 | FI55: 220.42583 | FJ55: 209.0791 | FK55: 210.98648 | FL55: 207.6686 | FM55: 210.77177 | FN55: 209.50121 | FO55: 206.7001 | FP55: 195.15888 | FQ55: 194.28071 | FR55: 191.77721 | FS55: 211.66111 | FT55: 232.69083 | FU55: 233.77057 | FV55: 209.40677 | FW55: 219.81787 | FX55: 203.96632 | FY55: 202.47635 | FZ55: 177.14934 | GA55: 173.39896 | GB55: 172.30563 | GC55: 178.37325 | GD55: 178.73091 | GE55: 190.27021 | GF55: 203.17159 | GG55: 196.16908 | GH55: 196.17367 | GI55: 178.61916 | GJ55: 168.24357 | GK55: 161.46287 | GL55: 148.39686 | GM55: 127.50523 | GN55: 121.90237 | GO55: 114.41066 | GP55: 107.99937 | GQ55: 106.78556 | GR55: 96.781107 | GS55: 90.47923 | GT55: 86.57941 | GU55: 87.235817
A56: (Cartera irregular - Previsiones) / Financiaciones | B56: 14.333854 | C56: 10.711585 | D56: 2.4409809 | E56: 0.17353266 | F56: -0.39861037 | G56: -0.66833274 | H56: -0.57385183 | I56: -0.73512096 | J56: -0.68930778 | K56: -0.75864882 | L56: -0.724785 | M56: -0.72634167 | N56: -0.72145316 | O56: -0.70793793 | P56: -0.74177805 | Q56: -0.76012753 | R56: -0.83854876 | S56: -0.87122052 | T56: -0.89197984 | U56: -0.92624147 | V56: -0.94631627 | W56: -0.95314242 | X56: -0.95588377 | Y56: -0.77429093 | Z56: -0.76331236 | AA56: -0.86301781 | AB56: -0.90519999 | AC56: -0.93835573 | AD56: -0.93953434 | AE56: -0.96543481 | AF56: -0.96434013 | AG56: -0.92188905 | AH56: -0.85726349 | AI56: -0.81156904 | AJ56: -0.80929163 | AK56: -0.72894595 | AL56: -0.70657783 | AM56: -0.68651264 | AN56: -0.66384353 | AO56: -0.72646527 | AP56: -0.73220586 | AQ56: -0.71551262 | AR56: -0.74028792 | AS56: -0.73008405 | AT56: -0.71420995 | AU56: -0.68196371 | AV56: -0.67924661 | AW56: -0.67779606 | AX56: -0.64707324 | AY56: -0.64171088 | AZ56: -0.69651666 | BA56: -0.70254085 | BB56: -0.76031457 | BC56: -0.77018566 | BD56: -0.80811087 | BE56: -0.90631782 | BF56: -0.94152563 | BG56: -0.95974716 | BH56: -0.95380216 | BI56: -0.95297962 | BJ56: -0.85812513 | BK56: -0.84884455 | BL56: -0.86649269 | BM56: -0.87546282 | BN56: -0.90920259 | BO56: -0.9094495 | BP56: -0.911887 | BQ56: -0.93431387 | BR56: -0.93219116 | BS56: -0.91970149 | BT56: -0.9029662 | BU56: -0.89874714 | BV56: -0.89192192 | BW56: -0.89411493 | BX56: -0.91445723 | BY56: -0.9273214 | BZ56: -0.99132971 | CA56: -1.0079914 | CB56: -1.0114562 | CC56: -1.0150495 | CD56: -1.0083123 | CE56: -1.0077307 | CF56: -0.99988016 | CG56: -0.93390052 | CH56: -0.91502188 | CI56: -0.86858794 | CJ56: -0.8676462 | CK56: -0.82914965 | CL56: -0.84622883 | CM56: -0.83552552 | CN56: -0.81417802 | CO56: -0.78263608 | CP56: -0.7869821 | CQ56: -0.78086281 | CR56: -0.69744843 | CS56: -0.75410916 | CT56: -0.68973815 | CU56: -0.65057305 | CV56: -0.65474163 | CW56: -0.68847935 | CX56: -0.67835069 | CY56: -0.6903759 | CZ56: -0.59798697 | DA56: -0.61511783 | DB56: -0.59457514 | DC56: -0.59518268 | DD56: -0.57610413 | DE56: -0.56900008 | DF56: -0.53363422 | DG56: -0.5361502 | DH56: -0.51214269 | DI56: -0.55336519 | DJ56: -0.59568416 | DK56: -0.34115626 | DL56: -0.0040769086 | DM56: 0.04862175 | DN56: 0.20654498 | DO56: 0.17635805 | DP56: 0.073456913 | DQ56: 0.072020069 | DR56: -2.268479 | DS56: 0.069548225 | DT56: 0.07062461 | DU56: 0.0056084209 | DV56: -0.052300226 | DW56: -0.086203666 | DX56: 0.021424091 | DY56: -0.24829076 | DZ56: -0.97517032 | EA56: -0.89646534 | EB56: -1.6483726 | EC56: -1.8165063 | ED56: -2.1248447 | EE56: -2.6466478 | EF56: -2.6670228 | EG56: -2.6829527 | EH56: -3.0614319 | EI56: -3.2402456 | EJ56: -2.896296 | EK56: -3.1291005 | EL56: -3.1464271 | EM56: -3.2484647 | EN56: -2.856639 | EO56: -2.5842335 | EP56: -2.3361918 | EQ56: -1.9409944 | ER56: -1.6750377 | ES56: -1.6312295 | ET56: -1.7838058 | EU56: -1.7951962 | EV56: -1.6837551 | EW56: -1.7120904 | EX56: -1.5276028 | EY56: -1.6010435 | EZ56: -1.6948087 | FA56: -1.6612173 | FB56: -1.6803272 | FC56: -1.5513788 | FD56: -1.581115 | FE56: -1.6334325 | FF56: -1.7247129 | FG56: -1.5863844 | FH56: -1.6960918 | FI56: -1.784752 | FJ56: -1.6555976 | FK56: -1.672366 | FL56: -1.6630262 | FM56: -1.6382614 | FN56: -1.6377092 | FO56: -1.5782115 | FP56: -1.4366566 | FQ56: -1.410556 | FR56: -1.3531254 | FS56: -1.5560781 | FT56: -1.6984937 | FU56: -1.7222415 | FV56: -1.3568322 | FW56: -1.4231651 | FX56: -1.2590106 | FY56: -1.3276126 | FZ56: -1.057609 | GA56: -1.0012808 | GB56: -1.0102432 | GC56: -1.1168155 | GD56: -1.1322084 | GE56: -1.2615423 | GF56: -1.4637105 | GG56: -1.409024 | GH56: -1.4551687 | GI56: -1.292831 | GJ56: -1.2305704 | GK56: -1.2060726 | GL56: -1.1261746 | GM56: -0.73776408 | GN56: -0.65217991 | GO56: -0.49831045 | GP56: -0.30493191 | GQ56: -0.27759428 | GR56: 0.15334785 | GS56: 0.49445501 | GT56: 0.8229484 | GU56: 0.87365631
A57: (Cartera irregular - Previsiones) / PN | B57: 35.353373 | C57: 21.704033 | D57: 5.7949652 | E57: 0.53987823 | F57: -1.5257492 | G57: -2.9628327 | H57: -2.4818636 | I57: -2.5047341 | J57: -2.3168831 | K57: -2.5511567 | L57: -2.4429683 | M57: -2.72435 | N57: -2.8035523 | O57: -2.8121884 | P57: -2.8987173 | Q57: -2.9799852 | R57: -3.339112 | S57: -3.4405932 | T57: -3.4811369 | U57: -3.6711694 | V57: -3.7645472 | W57: -3.9595446 | X57: -4.3904372 | Y57: -3.5186396 | Z57: -3.5620736 | AA57: -4.0592107 | AB57: -4.3184676 | AC57: -4.5185015 | AD57: -4.6565372 | AE57: -4.7350708 | AF57: -4.5996653 | AG57: -4.2920176 | AH57: -3.9690686 | AI57: -3.6991199 | AJ57: -3.6687618 | AK57: -3.2352247 | AL57: -3.0819133 | AM57: -2.9907278 | AN57: -2.8538648 | AO57: -3.1263222 | AP57: -3.1284546 | AQ57: -3.094694 | AR57: -3.1988413 | AS57: -3.2695837 | AT57: -3.1592546 | AU57: -2.9551333 | AV57: -2.9474038 | AW57: -2.9405586 | AX57: -2.7916085 | AY57: -2.8436699 | AZ57: -3.0756269 | BA57: -3.1187301 | BB57: -3.3607049 | BC57: -3.3883685 | BD57: -3.5591848 | BE57: -3.9825141 | BF57: -3.842192 | BG57: -3.8111721 | BH57: -3.7797043 | BI57: -3.8033655 | BJ57: -3.3538637 | BK57: -3.3679152 | BL57: -3.4039045 | BM57: -3.404949 | BN57: -3.5004333 | BO57: -3.4784721 | BP57: -3.49659 | BQ57: -3.6466752 | BR57: -3.5470339 | BS57: -3.512762 | BT57: -3.4394625 | BU57: -3.4889494 | BV57: -3.4962082 | BW57: -3.5890679 | BX57: -3.6222178 | BY57: -3.725808 | BZ57: -3.9728073 | CA57: -4.0280433 | CB57: -4.1006294 | CC57: -4.1744396 | CD57: -4.0786868 | CE57: -4.0664129 | CF57: -3.8798134 | CG57: -3.7237107 | CH57: -3.6460205 | CI57: -3.4920651 | CJ57: -3.5144878 | CK57: -3.4407794 | CL57: -3.535968 | CM57: -3.4758213 | CN57: -3.3810979 | CO57: -3.3556493 | CP57: -3.3838873 | CQ57: -3.2738019 | CR57: -2.8641243 | CS57: -3.1941523 | CT57: -2.9885052 | CU57: -2.936532 | CV57: -2.9107454 | CW57: -3.110588 | CX57: -3.0714979 | CY57: -3.1558463 | CZ57: -2.744709 | DA57: -2.9263364 | DB57: -2.4970207 | DC57: -2.5290701 | DD57: -2.4031138 | DE57: -2.5032664 | DF57: -2.4351333 | DG57: -2.523804 | DH57: -2.3426683 | DI57: -2.7154389 | DJ57: -2.7620784 | DK57: -1.42909 | DL57: -0.017399363 | DM57: 0.19618387 | DN57: 0.79745109 | DO57: 0.65273324 | DP57: 0.27283969 | DQ57: 0.2683424 | DR57: -5.1721965 | DS57: 0.24519325 | DT57: 0.24618161 | DU57: 0.021752255 | DV57: -0.18265959 | DW57: -0.29107714 | DX57: 0.066355244 | DY57: -0.70163055 | DZ57: -2.2943925 | EA57: -2.0908433 | EB57: -3.8858432 | EC57: -4.307572 | ED57: -5.0220252 | EE57: -6.2804757 | EF57: -6.1301819 | EG57: -6.0203197 | EH57: -6.6770215 | EI57: -6.9808035 | EJ57: -6.2945755 | EK57: -6.6979734 | EL57: -6.5119301 | EM57: -6.5843827 | EN57: -5.7421359 | EO57: -5.1623908 | EP57: -4.6700597 | EQ57: -3.9101676 | ER57: -3.3267313 | ES57: -3.1873489 | ET57: -3.4240755 | EU57: -3.4481814 | EV57: -3.2731361 | EW57: -3.3235382 | EX57: -2.8897155 | EY57: -2.9841415 | EZ57: -3.0765367 | FA57: -3.0363836 | FB57: -3.0178056 | FC57: -2.8431492 | FD57: -2.8302846 | FE57: -2.790935 | FF57: -2.8117556 | FG57: -2.5761058 | FH57: -2.7662793 | FI57: -2.8271303 | FJ57: -2.5939651 | FK57: -2.5909489 | FL57: -2.5972812 | FM57: -2.7276229 | FN57: -2.687465 | FO57: -2.5720191 | FP57: -2.3073578 | FQ57: -2.2273152 | FR57: -1.9937585 | FS57: -2.2738851 | FT57: -2.2890686 | FU57: -2.1223759 | FV57: -1.5846711 | FW57: -1.6109945 | FX57: -1.4467229 | FY57: -1.507557 | FZ57: -1.3493495 | GA57: -1.4029081 | GB57: -1.5080842 | GC57: -1.7214997 | GD57: -1.8311205 | GE57: -2.0733588 | GF57: -2.5176943 | GG57: -2.6883927 | GH57: -2.8339857 | GI57: -2.6115152 | GJ57: -2.6271656 | GK57: -2.6890324 | GL57: -2.6054986 | GM57: -1.7821463 | GN57: -1.6725801 | GO57: -1.3143475 | GP57: -0.82509277 | GQ57: -0.71508944 | GR57: 0.40065905 | GS57: 1.326119 | GT57: 2.1192436 | GU57: 2.1627723
A58: Fuente: BCRA
A63: Bancos públicos
A64: En porcentaje | B64: 37591 | C64: 37956 | D64: 38322 | E64: 38687 | F64: 39052 | G64: 39417 | H64: 39783 | I64: 40148 | J64: 40179 | K64: 40210 | L64: 40238 | M64: 40269 | N64: 40299 | O64: 40330 | P64: 40360 | Q64: 40391 | R64: 40422 | S64: 40452 | T64: 40483 | U64: 40513 | V64: 40544 | W64: 40575 | X64: 40603 | Y64: 40634 | Z64: 40664 | AA64: 40695 | AB64: 40725 | AC64: 40756 | AD64: 40787 | AE64: 40817 | AF64: 40848 | AG64: 40878 | AH64: 40909 | AI64: 40940 | AJ64: 40969 | AK64: 41000 | AL64: 41030 | AM64: 41061 | AN64: 41091 | AO64: 41122 | AP64: 41153 | AQ64: 41183 | AR64: 41214 | AS64: 41244 | AT64: 41275 | AU64: 41306 | AV64: 41334 | AW64: 41365 | AX64: 41395 | AY64: 41426 | AZ64: 41456 | BA64: 41487 | BB64: 41518 | BC64: 41548 | BD64: 41579 | BE64: 41609 | BF64: 41640 | BG64: 41671 | BH64: 41699 | BI64: 41730 | BJ64: 41760 | BK64: 41791 | BL64: 41821 | BM64: 41852 | BN64: 41883 | BO64: 41913 | BP64: 41944 | BQ64: 41974 | BR64: 42005 | BS64: 42036 | BT64: 42064 | BU64: 42095 | BV64: 42125 | BW64: 42156 | BX64: 42186 | BY64: 42217 | BZ64: 42248 | CA64: 42278 | CB64: 42309 | CC64: 42339 | CD64: 42370 | CE64: 42401 | CF64: 42430 | CG64: 42461 | CH64: 42491 | CI64: 42522 | CJ64: 42552 | CK64: 42583 | CL64: 42614 | CM64: 42644 | CN64: 42675 | CO64: 42705 | CP64: 42736 | CQ64: 42767 | CR64: 42795 | CS64: 42826 | CT64: 42856 | CU64: 42887 | CV64: 42917 | CW64: 42948 | CX64: 42979 | CY64: 43009 | CZ64: 43040 | DA64: 43070 | DB64: 43101 | DC64: 43132 | DD64: 43160 | DE64: 43191 | DF64: 43221 | DG64: 43252 | DH64: 43282 | DI64: 43313 | DJ64: 43344 | DK64: 43374 | DL64: 43405 | DM64: 43435 | DN64: 43466 | DO64: 43497 | DP64: 43525 | DQ64: 43556 | DR64: 43586 | DS64: 43617 | DT64: 43647 | DU64: 43678 | DV64: 43709 | DW64: 43739 | DX64: 43770 | DY64: 43800 | DZ64: 43831 | EA64: 43862 | EB64: 43891 | EC64: 43922 | ED64: 43952 | EE64: 43983 | EF64: 44013 | EG64: 44044 | EH64: 44075 | EI64: 44105 | EJ64: 44136 | EK64: 44166 | EL64: 44197 | EM64: 44228 | EN64: 44256 | EO64: 44287 | EP64: 44317 | EQ64: 44348 | ER64: 44378 | ES64: 44409 | ET64: 44440 | EU64: 44470 | EV64: 44501 | EW64: 44531 | EX64: 44562 | EY64: 44593 | EZ64: 44621 | FA64: 44652 | FB64: 44682 | FC64: 44713 | FD64: 44743 | FE64: 44774 | FF64: 44805 | FG64: 44835 | FH64: 44866 | FI64: 44896 | FJ64: 44927 | FK64: 44958 | FL64: 44986 | FM64: 45017 | FN64: 45047 | FO64: 45078 | FP64: 45108 | FQ64: 45139 | FR64: 45170 | FS64: 45200 | FT64: 45231 | FU64: 45261 | FV64: 45292 | FW64: 45323 | FX64: 45352 | FY64: 45383 | FZ64: 45413 | GA64: 45444 | GB64: 45474 | GC64: 45505 | GD64: 45536 | GE64: 45566 | GF64: 45597 | GG64: 45627 | GH64: 45658 | GI64: 45689 | GJ64: 45717 | GK64: 45748 | GL64: 45778 | GM64: 45809 | GN64: 45839 | GO64: 45870 | GP64: 45901 | GQ64: 45931 | GR64: 45962 | GS64: 45992 | GT64: 46023 | GU64: 46054
A65: Cartera irregular total | B65: 15.173653 | C65: 22.353581 | D65: 14.892716 | E65: 6.8332509 | F65: 4.2832558 | G65: 3.4964219 | H65: 2.2289611 | I65: 2.0906459 | J65: 2.087736 | K65: 1.9614115 | L65: 1.9311912 | M65: 1.89957 | N65: 1.9748006 | O65: 1.8866619 | P65: 1.853211 | Q65: 1.8130428 | R65: 1.7280881 | S65: 1.6347969 | T65: 1.5689387 | U65: 1.5082632 | V65: 1.492832 | W65: 1.4076355 | X65: 1.3577089 | Y65: 1.3130362 | Z65: 1.2824559 | AA65: 1.2043824 | AB65: 1.1919236 | AC65: 1.1536479 | AD65: 1.0087398 | AE65: 0.99530347 | AF65: 0.93824822 | AG65: 0.9114572 | AH65: 0.95611466 | AI65: 0.93005748 | AJ65: 0.95420979 | AK65: 0.96866589 | AL65: 1.0098199 | AM65: 1.0284073 | AN65: 1.0387479 | AO65: 1.0273043 | AP65: 1.0911654 | AQ65: 1.0953984 | AR65: 1.0904926 | AS65: 1.0748883 | AT65: 1.0707312 | AU65: 1.0850755 | AV65: 1.1073578 | AW65: 1.1826553 | AX65: 1.1843793 | AY65: 1.1827655 | AZ65: 1.1359111 | BA65: 1.1010564 | BB65: 1.1188508 | BC65: 1.0989992 | BD65: 1.0917078 | BE65: 1.1930223 | BF65: 1.1989084 | BG65: 1.1685152 | BH65: 1.2234882 | BI65: 1.2223206 | BJ65: 1.2816027 | BK65: 1.2782281 | BL65: 1.3369958 | BM65: 1.3661706 | BN65: 1.3481539 | BO65: 1.3459267 | BP65: 1.3325247 | BQ65: 1.4617871 | BR65: 1.4648395 | BS65: 1.4938959 | BT65: 1.4410128 | BU65: 1.4745722 | BV65: 1.477588 | BW65: 1.4792267 | BX65: 1.4409389 | BY65: 1.4344106 | BZ65: 1.3453256 | CA65: 1.2850339 | CB65: 1.4700586 | CC65: 1.5328621 | CD65: 1.6290945 | CE65: 1.6425877 | CF65: 1.6255374 | CG65: 1.6157034 | CH65: 1.6593727 | CI65: 1.7193844 | CJ65: 1.7643671 | CK65: 1.8905442 | CL65: 1.8545847 | CM65: 1.8420196 | CN65: 1.762485 | CO65: 1.8759622 | CP65: 1.918138 | CQ65: 1.8239038 | CR65: 1.8228228 | CS65: 1.7254492 | CT65: 1.7925541 | CU65: 1.8015653 | CV65: 1.7647919 | CW65: 1.6874198 | CX65: 1.6131242 | CY65: 1.5591439 | CZ65: 1.5608201 | DA65: 1.5085416 | DB65: 1.5201348 | DC65: 1.5065961 | DD65: 1.4820066 | DE65: 1.5424332 | DF65: 1.6838273 | DG65: 1.6786896 | DH65: 1.7303649 | DI65: 1.7758269 | DJ65: 1.8330538 | DK65: 1.8250249 | DL65: 2.0262364 | DM65: 2.5331972 | DN65: 3.0790218 | DO65: 4.1148183 | DP65: 4.3726632 | DQ65: 4.5140721 | DR65: 5.0258784 | DS65: 5.1469119 | DT65: 5.2933211 | DU65: 5.462763 | DV65: 5.5629494 | DW65: 5.6102069 | DX65: 5.7325526 | DY65: 7.8006176 | DZ65: 7.9949627 | EA65: 8.1246794 | EB65: 7.6616822 | EC65: 7.979911 | ED65: 8.0050143 | EE65: 8.0138479 | EF65: 8.1776214 | EG65: 8.129868 | EH65: 8.3289752 | EI65: 8.012298 | EJ65: 7.867928 | EK65: 7.4497894 | EL65: 7.4458928 | EM65: 7.3453103 | EN65: 7.2914609 | EO65: 7.3106838 | EP65: 7.3352646 | EQ65: 8.1757012 | ER65: 8.5481853 | ES65: 7.9021372 | ET65: 7.5226632 | EU65: 7.3690019 | EV65: 6.9116493 | EW65: 6.5843187 | EX65: 6.585993 | EY65: 6.3053142 | EZ65: 6.022092 | FA65: 5.5143637 | FB65: 5.3668797 | FC65: 5.2469396 | FD65: 5.188781 | FE65: 5.1927169 | FF65: 5.1102435 | FG65: 5.0924587 | FH65: 5.0494942 | FI65: 5.1557382 | FJ65: 5.2399756 | FK65: 5.2281614 | FL65: 5.1256279 | FM65: 4.9429067 | FN65: 4.9150055 | FO65: 4.9640048 | FP65: 4.9418178 | FQ65: 5.2990317 | FR65: 4.9636706 | FS65: 4.4876996 | FT65: 4.2993036 | FU65: 6.8810789 | FV65: 6.7246921 | FW65: 3.0326001 | FX65: 2.8903918 | FY65: 2.719664 | FZ65: 2.5353247 | GA65: 2.4115671 | GB65: 2.0769175 | GC65: 1.8550473 | GD65: 1.7344468 | GE65: 1.590591 | GF65: 1.5938637 | GG65: 1.5621856 | GH65: 1.602151 | GI65: 1.6816108 | GJ65: 1.8618023 | GK65: 2.0487442 | GL65: 2.4191478 | GM65: 2.6403508 | GN65: 2.9218416 | GO65: 3.2987817 | GP65: 3.6674542 | GQ65: 4.1294262 | GR65: 4.8138868 | GS65: 5.2993862 | GT65: 6.0843204 | GU65: 6.2015797
A66: Previsiones / Cartera irregular | B66: 73.262171 | C66: 82.503965 | D66: 109.15394 | E66: 135.33954 | F66: 101.65809 | G66: 111.77965 | H66: 137.7572 | I66: 134.3003 | J66: 134.38782 | K66: 139.6673 | L66: 141.46311 | M66: 142.04926 | N66: 139.19033 | O66: 145.12142 | P66: 145.97986 | Q66: 152.2343 | R66: 155.26207 | S66: 160.80725 | T66: 163.80903 | U66: 165.61309 | V66: 166.05901 | W66: 175.57832 | X66: 179.26329 | Y66: 182.30145 | Z66: 183.68593 | AA66: 182.18614 | AB66: 184.10558 | AC66: 188.02221 | AD66: 201.86811 | AE66: 204.91926 | AF66: 205.62508 | AG66: 211.36077 | AH66: 203.86355 | AI66: 205.81817 | AJ66: 201.16689 | AK66: 197.45427 | AL66: 188.44188 | AM66: 184.05192 | AN66: 179.867 | AO66: 181.94744 | AP66: 172.33837 | AQ66: 170.48577 | AR66: 172.65662 | AS66: 173.78165 | AT66: 172.86912 | AU66: 172.81817 | AV66: 170.26422 | AW66: 151.52118 | AX66: 160.12991 | AY66: 160.11733 | AZ66: 163.28093 | BA66: 167.32405 | BB66: 165.77311 | BC66: 169.67524 | BD66: 167.69641 | BE66: 177.36873 | BF66: 180.87903 | BG66: 187.05381 | BH66: 180.7621 | BI66: 179.50635 | BJ66: 174.00874 | BK66: 174.16033 | BL66: 167.84761 | BM66: 165.63855 | BN66: 168.46648 | BO66: 169.58173 | BP66: 171.18847 | BQ66: 157.75595 | BR66: 156.8359 | BS66: 155.69164 | BT66: 155.54021 | BU66: 152.01144 | BV66: 152.69089 | BW66: 150.65297 | BX66: 153.5545 | BY66: 154.82317 | BZ66: 160.71493 | CA66: 164.26143 | CB66: 146.58694 | CC66: 150.72398 | CD66: 142.88659 | CE66: 143.92792 | CF66: 146.84599 | CG66: 158.14204 | CH66: 155.25246 | CI66: 147.30945 | CJ66: 145.13822 | CK66: 141.46668 | CL66: 147.16975 | CM66: 145.93252 | CN66: 152.14428 | CO66: 144.44918 | CP66: 142.11768 | CQ66: 146.08749 | CR66: 149.53825 | CS66: 155.3757 | CT66: 151.35345 | CU66: 151.66541 | CV66: 154.75065 | CW66: 159.75634 | CX66: 170.36989 | CY66: 174.72343 | CZ66: 173.97749 | DA66: 210.64873 | DB66: 172.31526 | DC66: 175.74667 | DD66: 177.72677 | DE66: 172.49648 | DF66: 158.92868 | DG66: 160.01235 | DH66: 157.70913 | DI66: 152.46403 | DJ66: 151.34086 | DK66: 156.97525 | DL66: 196.72776 | DM66: 166.558 | DN66: 139.59788 | DO66: 81.187658 | DP66: 82.042349 | DQ66: 83.296868 | DR66: 75.555701 | DS66: 76.937239 | DT66: 75.103641 | DU66: 75.561629 | DV66: 77.969466 | DW66: 76.380794 | DX66: 76.124175 | DY66: 76.093776 | DZ66: 65.382059 | EA66: 65.834901 | EB66: 71.728373 | EC66: 73.958588 | ED66: 76.807828 | EE66: 79.426604 | EF66: 77.483525 | EG66: 76.273676 | EH66: 74.553544 | EI66: 77.113576 | EJ66: 85.049636 | EK66: 88.040372 | EL66: 86.889261 | EM66: 89.281084 | EN66: 89.612473 | EO66: 88.934327 | EP66: 89.324235 | EQ66: 80.56383 | ER66: 77.928321 | ES66: 83.408846 | ET66: 84.313627 | EU66: 83.986791 | EV66: 84.736475 | EW66: 85.319837 | EX66: 85.87892 | EY66: 87.897576 | EZ66: 88.842078 | FA66: 89.031239 | FB66: 89.753286 | FC66: 89.840767 | FD66: 89.615408 | FE66: 88.031607 | FF66: 98.627576 | FG66: 99.862878 | FH66: 100.53392 | FI66: 103.07577 | FJ66: 101.96719 | FK66: 101.14841 | FL66: 100.87701 | FM66: 102.33003 | FN66: 103.56425 | FO66: 100.86452 | FP66: 100.99222 | FQ66: 99.410149 | FR66: 99.478859 | FS66: 101.01978 | FT66: 101.80205 | FU66: 125.61586 | FV66: 120.60299 | FW66: 154.22185 | FX66: 172.2453 | FY66: 131.10716 | FZ66: 134.50303 | GA66: 138.03986 | GB66: 141.98593 | GC66: 150.76693 | GD66: 156.12111 | GE66: 166.3385 | GF66: 134.70626 | GG66: 136.37429 | GH66: 134.95926 | GI66: 132.45875 | GJ66: 125.0082 | GK66: 120.36165 | GL66: 110.84923 | GM66: 107.5441 | GN66: 103.34635 | GO66: 100.37234 | GP66: 97.283139 | GQ66: 95.844199 | GR66: 96.843354 | GS66: 90.924458 | GT66: 86.416558 | GU66: 89.280905
A67: (Cartera irregular - Previsiones) / Financiaciones | B67: 4.0571053 | C67: 3.9109903 | D67: -1.3632697 | E67: -2.4148394 | F67: -0.071020249 | G67: -0.41186625 | H67: -0.84159339 | I67: -0.71709777 | J67: -0.71792692 | K67: -0.77803888 | L67: -0.80073193 | M67: -0.79875509 | N67: -0.77393092 | O67: -0.85128862 | P67: -0.85210374 | Q67: -0.94703017 | R67: -0.95497721 | S67: -0.99407497 | T67: -1.0011246 | U67: -0.98961812 | V67: -0.98615013 | W67: -1.0638672 | X67: -1.0761647 | Y67: -1.0806479 | Z67: -1.0732351 | AA67: -0.98983539 | AB67: -1.0024743 | AC67: -1.0154664 | AD67: -1.0275842 | AE67: -1.044265 | AF67: -0.99102541 | AG67: -1.0150058 | AH67: -0.99305467 | AI67: -0.98416985 | AJ67: -0.96534435 | AK67: -0.94400632 | AL67: -0.89310368 | AM67: -0.86439611 | AN67: -0.82961672 | AO67: -0.84184956 | AP67: -0.78933135 | AQ67: -0.77209999 | AR67: -0.79231507 | AS67: -0.79307032 | AT67: -0.78023242 | AU67: -0.79013217 | AV67: -0.77807639 | AW67: -0.60931796 | AX67: -0.71216615 | AY67: -0.7110471 | AZ67: -0.71881509 | BA67: -0.74127578 | BB67: -0.73590301 | BC67: -0.76573032 | BD67: -0.73904695 | BE67: -0.92302623 | BF67: -0.96966542 | BG67: -1.017237 | BH67: -0.98811478 | BI67: -0.9718225 | BJ67: -0.94849801 | BK67: -0.94793823 | BL67: -0.90711965 | BM67: -0.89673464 | BN67: -0.92303358 | BO67: -0.93651907 | BP67: -0.94860392 | BQ67: -0.84426895 | BR67: -0.83255469 | BS67: -0.83197514 | BT67: -0.80034151 | BU67: -0.76694622 | BV67: -0.77855433 | BW67: -0.74927225 | BX67: -0.77168762 | BY67: -0.78638939 | BZ67: -0.81681343 | CA67: -0.82578115 | CB67: -0.68485528 | CC67: -0.77752872 | CD67: -0.69866309 | CE67: -0.72155466 | CF67: -0.76149904 | CG67: -0.93940292 | CH67: -0.91684422 | CI67: -0.81343129 | CJ67: -0.79640383 | CK67: -0.78394593 | CL67: -0.87480302 | CM67: -0.84608595 | CN67: -0.91903513 | CO67: -0.83384985 | CP67: -0.80787513 | CQ67: -0.84059154 | CR67: -0.90299443 | CS67: -0.95547963 | CT67: -0.92053835 | CU67: -0.93078602 | CV67: -0.966235 | CW67: -1.0083403 | CX67: -1.1351537 | CY67: -1.1650458 | CZ67: -1.1546555 | DA67: -1.6691822 | DB67: -1.0992894 | DC67: -1.1411964 | DD67: -1.1519158 | DE67: -1.1182098 | DF67: -0.99225723 | DG67: -1.0074211 | DH67: -0.99857849 | DI67: -0.93167041 | DJ67: -0.9411056 | DK67: -1.0398125 | DL67: -1.959933 | DM67: -1.6860453 | DN67: -1.2192273 | DO67: 0.77409369 | DP67: 0.78522761 | DQ67: 0.7539914 | DR67: 1.2285407 | DS67: 1.18702 | DT67: 1.3178442 | DU67: 1.3350103 | DV67: 1.2255475 | DW67: 1.3250863 | DX67: 1.3686943 | DY67: 1.8648331 | DZ67: 2.7676915 | EA67: 2.7758048 | EB67: 2.1660822 | EC67: 2.0780815 | ED67: 1.8565367 | EE67: 1.6487207 | EF67: 1.8413121 | EG67: 1.9289188 | EH67: 2.119429 | EI67: 1.8337285 | EJ67: 1.1762839 | EK67: 0.89096708 | EL67: 0.97621158 | EM67: 0.78733761 | EN67: 0.75740244 | EO67: 0.80897638 | EP67: 0.78309559 | EQ67: 1.5890432 | ER67: 1.886728 | ES67: 1.3110558 | ET67: 1.180033 | EU67: 1.1800137 | EV67: 1.0549613 | EW67: 0.96658872 | EX67: 0.93001335 | EY67: 0.76309587 | EZ67: 0.67194031 | FA67: 0.6048574 | FB67: 0.54992883 | FC67: 0.53304883 | FD67: 0.53883374 | FE67: 0.62148475 | FF67: 0.070134212 | FG67: 0.0069828843 | FH67: -0.026960452 | FI67: -0.15857881 | FJ67: -0.10308051 | FK67: -0.060040639 | FL67: -0.04495234 | FM67: -0.11517099 | FN67: -0.17518285 | FO67: -0.042914862 | FP67: -0.049033784 | FQ67: 0.031256375 | FR67: 0.025867701 | FS67: -0.045764758 | FT67: -0.077475387 | FU67: -1.7626478 | FV67: -1.3854873 | FW67: -1.6443319 | FX67: -2.0881722 | FY67: -0.84601011 | FZ67: -0.87476379 | GA67: -0.91735685 | GB67: -0.87201307 | GC67: -0.94175057 | GD67: -0.97339083 | GE67: -1.0551742 | GF67: -0.55317049 | GG67: -0.568234 | GH67: -0.56010017 | GI67: -0.54582987 | GJ67: -0.46560319 | GK67: -0.4171581 | GL67: -0.26245886 | GM67: -0.19919066 | GN67: -0.097774977 | GO67: -0.012282539 | GP67: 0.09963963 | GQ67: 0.17161074 | GR67: 0.15195736 | GS67: 0.48094801 | GT67: 0.82646015 | GU67: 0.66475322
A68: (Cartera irregular - Previsiones) / PN | B68: 16.494559 | C68: 12.45189 | D68: -3.8891689 | E68: -7.062685 | F68: -0.20852827 | G68: -1.3568188 | H68: -3.3755661 | I68: -3.0730492 | J68: -3.0854551 | K68: -3.3558957 | L68: -3.4426642 | M68: -3.4224561 | N68: -3.3277183 | O68: -3.6830639 | P68: -3.634894 | Q68: -4.0444061 | R68: -4.0848444 | S68: -4.223333 | T68: -4.2339792 | U68: -4.2869872 | V68: -4.2543184 | W68: -4.5823997 | X68: -4.5347552 | Y68: -4.5776536 | Z68: -4.5626052 | AA68: -4.466797 | AB68: -4.6597048 | AC68: -4.7400068 | AD68: -4.9156381 | AE68: -4.9976594 | AF68: -4.9670891 | AG68: -5.0689031 | AH68: -4.8927667 | AI68: -4.9052299 | AJ68: -4.7615212 | AK68: -4.710877 | AL68: -4.5008037 | AM68: -4.3681369 | AN68: -4.2371625 | AO68: -4.2632304 | AP68: -3.9731609 | AQ68: -3.9315478 | AR68: -4.0567886 | AS68: -4.1988571 | AT68: -4.0897298 | AU68: -4.0572316 | AV68: -3.9468126 | AW68: -3.0692722 | AX68: -3.5918805 | AY68: -3.6197705 | AZ68: -3.6509247 | BA68: -3.7555978 | BB68: -3.7284825 | BC68: -3.8364498 | BD68: -3.737945 | BE68: -4.6927304 | BF68: -4.6119211 | BG68: -4.7864127 | BH68: -4.5290943 | BI68: -4.417165 | BJ68: -4.1982122 | BK68: -4.123575 | BL68: -3.8690955 | BM68: -3.7460922 | BN68: -3.8259251 | BO68: -3.8556919 | BP68: -3.8463153 | BQ68: -3.5048785 | BR68: -3.3468078 | BS68: -3.2360527 | BT68: -3.1906899 | BU68: -3.0284673 | BV68: -3.0816595 | BW68: -2.9826611 | BX68: -3.047487 | BY68: -3.0499192 | BZ68: -3.1270758 | CA68: -3.2182114 | CB68: -2.6698876 | CC68: -3.0837135 | CD68: -2.6827962 | CE68: -2.669387 | CF68: -2.7944053 | CG68: -3.4370208 | CH68: -3.3075109 | CI68: -2.9063007 | CJ68: -2.7603225 | CK68: -2.5719108 | CL68: -2.8592634 | CM68: -2.8015085 | CN68: -3.0901757 | CO68: -2.7792061 | CP68: -2.6892153 | CQ68: -2.8064093 | CR68: -2.9658591 | CS68: -3.155008 | CT68: -3.0288729 | CU68: -3.1395182 | CV68: -3.3131837 | CW68: -3.5536478 | CX68: -4.1469343 | CY68: -4.4048327 | CZ68: -4.5429078 | DA68: -7.1693063 | DB68: -4.030171 | DC68: -4.1127412 | DD68: -4.6103223 | DE68: -4.3777111 | DF68: -4.0375498 | DG68: -4.1146658 | DH68: -4.1563182 | DI68: -3.8526373 | DJ68: -3.8249452 | DK68: -4.1825907 | DL68: -8.1802371 | DM68: -6.3942752 | DN68: -4.5735504 | DO68: 2.917929 | DP68: 3.0948149 | DQ68: 3.1151868 | DR68: 5.1489488 | DS68: 4.8988309 | DT68: 5.2654293 | DU68: 5.8907944 | DV68: 5.1661054 | DW68: 5.7459948 | DX68: 5.9176764 | DY68: 8.0844475 | DZ68: 8.7417977 | EA68: 8.7958016 | EB68: 6.8097453 | EC68: 6.3715234 | ED68: 5.5186294 | EE68: 4.8862987 | EF68: 5.4457361 | EG68: 5.3619811 | EH68: 5.9125584 | EI68: 5.1274691 | EJ68: 3.2162882 | EK68: 2.4162293 | EL68: 2.5898907 | EM68: 2.0422741 | EN68: 1.9233075 | EO68: 2.0245774 | EP68: 1.9145052 | EQ68: 3.8845221 | ER68: 4.6515528 | ES68: 3.1416996 | ET68: 2.8341942 | EU68: 2.8670459 | EV68: 2.5962155 | EW68: 2.3763247 | EX68: 2.203987 | EY68: 1.7782855 | EZ68: 1.5441269 | FA68: 1.351444 | FB68: 1.2173035 | FC68: 1.1824133 | FD68: 1.138421 | FE68: 1.2639187 | FF68: 0.13564862 | FG68: 0.013029048 | FH68: -0.049113225 | FI68: -0.28005018 | FJ68: -0.17501683 | FK68: -0.099021682 | FL68: -0.073399873 | FM68: -0.19009155 | FN68: -0.28014603 | FO68: -0.067544769 | FP68: -0.076236587 | FQ68: 0.045902222 | FR68: 0.035791223 | FS68: -0.063070245 | FT68: -0.097902276 | FU68: -1.7741611 | FV68: -1.2521535 | FW68: -1.3317099 | FX68: -1.6108351 | FY68: -0.6271996 | FZ68: -0.68181144 | GA68: -0.74983392 | GB68: -0.7859866 | GC68: -0.91061355 | GD68: -1.0054143 | GE68: -1.2043554 | GF68: -0.63812879 | GG68: -0.70654433 | GH68: -0.69923336 | GI68: -0.71817433 | GJ68: -0.63912284 | GK68: -0.58258831 | GL68: -0.37405049 | GM68: -0.29402457 | GN68: -0.14877444 | GO68: -0.019538163 | GP68: 0.16191259 | GQ68: 0.26423848 | GR68: 0.23479413 | GS68: 0.74633256 | GT68: 1.2931942 | GU68: 1.0466625
A69: Al sector privado no financiero | B69: 41.551083 | C69: 41.439454 | D69: 26.840861 | E69: 11.159894 | F69: 6.8542262 | G69: 4.9198773 | H69: 2.8784194 | I69: 2.9745492 | J69: 2.9930689 | K69: 2.8812601 | L69: 2.822001 | M69: 2.7632621 | N69: 2.8594179 | O69: 2.7774236 | P69: 2.7171312 | Q69: 2.6610036 | R69: 2.5332188 | S69: 2.3738285 | T69: 2.2400837 | U69: 2.1422245 | V69: 2.1342105 | W69: 2.0049646 | X69: 1.9197093 | Y69: 1.8410133 | Z69: 1.7803367 | AA69: 1.7175853 | AB69: 1.663575 | AC69: 1.5836333 | AD69: 1.3709299 | AE69: 1.3364969 | AF69: 1.2667418 | AG69: 1.2267694 | AH69: 1.2756812 | AI69: 1.2527074 | AJ69: 1.2808813 | AK69: 1.2980707 | AL69: 1.3493019 | AM69: 1.3612592 | AN69: 1.3948136 | AO69: 1.3668635 | AP69: 1.444393 | AQ69: 1.4457743 | AR69: 1.4283067 | AS69: 1.4179549 | AT69: 1.4034076 | AU69: 1.416499 | AV69: 1.4436854 | AW69: 1.5393517 | AX69: 1.5466647 | AY69: 1.5354755 | AZ69: 1.4926776 | BA69: 1.4441109 | BB69: 1.4591448 | BC69: 1.4311245 | BD69: 1.4312963 | BE69: 1.5775642 | BF69: 1.5685734 | BG69: 1.5326504 | BH69: 1.6019215 | BI69: 1.5977927 | BJ69: 1.6758667 | BK69: 1.6739428 | BL69: 1.7529127 | BM69: 1.7870997 | BN69: 1.7544747 | BO69: 1.740348 | BP69: 1.7041669 | BQ69: 1.873807 | BR69: 1.8776196 | BS69: 1.8962667 | BT69: 1.8859981 | BU69: 1.92006 | BV69: 1.9163312 | BW69: 1.9179121 | BX69: 1.8175125 | BY69: 1.7869089 | BZ69: 1.6680555 | CA69: 1.5786324 | CB69: 1.7948798 | CC69: 1.9560436 | CD69: 1.9933436 | CE69: 2.0578675 | CF69: 2.1270445 | CG69: 2.1148075 | CH69: 2.164241 | CI69: 2.2370376 | CJ69: 2.2842755 | CK69: 2.1355406 | CL69: 2.0921704 | CM69: 2.0717859 | CN69: 1.9820561 | CO69: 2.2356896 | CP69: 2.2795403 | CQ69: 2.1471564 | CR69: 2.1326766 | CS69: 2.0036496 | CT69: 2.0696738 | CU69: 2.0660774 | CV69: 2.0071647 | CW69: 1.9078411 | CX69: 1.8114423 | CY69: 1.7380766 | CZ69: 1.7281331 | DA69: 1.6490533 | DB69: 1.6544819 | DC69: 1.6364083 | DD69: 1.6056262 | DE69: 1.6730106 | DF69: 1.8431033 | DG69: 1.8327508 | DH69: 1.888458 | DI69: 1.9254644 | DJ69: 1.9815556 | DK69: 1.971314 | DL69: 2.1910984 | DM69: 2.736788 | DN69: 3.3319197 | DO69: 3.5621442 | DP69: 3.8303461 | DQ69: 3.975908 | DR69: 4.4278427 | DS69: 4.6136316 | DT69: 4.8448506 | DU69: 5.0595071 | DV69: 5.2303745 | DW69: 5.4233191 | DX69: 5.4986077 | DY69: 7.8030457 | DZ69: 8.0148301 | EA69: 8.1809348 | EB69: 7.6895897 | EC69: 7.7902392 | ED69: 7.7909491 | EE69: 7.8174877 | EF69: 7.9830399 | EG69: 7.8367978 | EH69: 7.5193363 | EI69: 7.201542 | EJ69: 7.0668095 | EK69: 6.565185 | EL69: 6.7601994 | EM69: 6.6810709 | EN69: 6.6208336 | EO69: 6.6763531 | EP69: 6.7262482 | EQ69: 7.6898172 | ER69: 8.1467637 | ES69: 7.9366055 | ET69: 7.5185743 | EU69: 7.3598225 | EV69: 6.9392711 | EW69: 6.5493344 | EX69: 6.5425436 | EY69: 6.3251655 | EZ69: 6.0616448 | FA69: 5.5075341 | FB69: 5.3661612 | FC69: 5.2744456 | FD69: 5.2046123 | FE69: 5.2170649 | FF69: 5.1414221 | FG69: 5.1452342 | FH69: 5.10652 | FI69: 5.2756356 | FJ69: 5.3617634 | FK69: 5.369614 | FL69: 5.2692698 | FM69: 5.0764134 | FN69: 5.0479136 | FO69: 5.1605719 | FP69: 5.1254288 | FQ69: 5.5343886 | FR69: 5.1752007 | FS69: 4.761953 | FT69: 4.4702967 | FU69: 7.2383205 | FV69: 7.0830942 | FW69: 2.6950907 | FX69: 2.5898882 | FY69: 2.4319152 | FZ69: 2.2848399 | GA69: 2.2012444 | GB69: 1.8651862 | GC69: 1.6562181 | GD69: 1.5520637 | GE69: 1.416447 | GF69: 1.4288996 | GG69: 1.4072543 | GH69: 1.4523472 | GI69: 1.5441194 | GJ69: 1.7437044 | GK69: 1.9307771 | GL69: 2.3180688 | GM69: 2.5751449 | GN69: 2.8517711 | GO69: 3.2672725 | GP69: 3.8219231 | GQ69: 4.2863046 | GR69: 5.0119166 | GS69: 5.5448631 | GT69: 6.3481893 | GU69: 6.4949448
A70: Previsiones / Cartera irregular | B70: 76.117292 | C70: 85.39081 | D70: 108.21495 | E70: 134.79457 | F70: 100.6043 | G70: 110.79762 | H70: 136.64899 | I70: 122.40846 | J70: 122.69231 | K70: 127.64908 | L70: 129.58243 | M70: 130.23023 | N70: 125.1301 | O70: 130.79591 | P70: 131.70061 | Q70: 136.89922 | R70: 139.67302 | S70: 144.82552 | T70: 147.56287 | U70: 149.33301 | V70: 149.93032 | W70: 158.73951 | X70: 162.00425 | Y70: 164.91016 | Z70: 166.27274 | AA70: 165.03646 | AB70: 167.6084 | AC70: 171.36908 | AD70: 183.57837 | AE70: 186.95086 | AF70: 190.30212 | AG70: 195.8815 | AH70: 189.25359 | AI70: 191.19999 | AJ70: 187.15111 | AK70: 183.94191 | AL70: 175.79783 | AM70: 172.02075 | AN70: 168.42845 | AO70: 170.48407 | AP70: 161.70915 | AQ70: 160.21279 | AR70: 162.63174 | AS70: 164.0847 | AT70: 163.61633 | AU70: 163.37244 | AV70: 161.49788 | AW70: 151.66944 | AX70: 151.92178 | AY70: 152.06239 | AZ70: 155.00709 | BA70: 159.01481 | BB70: 157.75466 | BC70: 161.84139 | BD70: 160.06869 | BE70: 170.74279 | BF70: 174.39171 | BG70: 180.46548 | BH70: 174.58449 | BI70: 173.36104 | BJ70: 168.03657 | BK70: 168.23857 | BL70: 162.28576 | BM70: 160.26588 | BN70: 163.13439 | BO70: 164.31283 | BP70: 165.89739 | BQ70: 153.09815 | BR70: 152.21175 | BS70: 151.15053 | BT70: 151.09932 | BU70: 147.70827 | BV70: 148.4594 | BW70: 146.33683 | BX70: 149.20324 | BY70: 150.72197 | BZ70: 156.16146 | CA70: 159.61746 | CB70: 142.60849 | CC70: 147.13935 | CD70: 143.01087 | CE70: 144.33488 | CF70: 143.53483 | CG70: 143.64462 | CH70: 140.70239 | CI70: 136.90163 | CJ70: 136.48202 | CK70: 134.67627 | CL70: 136.88028 | CM70: 137.25613 | CN70: 143.8096 | CO70: 138.45723 | CP70: 137.15542 | CQ70: 142.14043 | CR70: 142.47127 | CS70: 150.26975 | CT70: 147.30276 | CU70: 148.28032 | CV70: 151.56183 | CW70: 156.80942 | CX70: 163.11886 | CY70: 166.83037 | CZ70: 166.44139 | DA70: 172.90835 | DB70: 171.64672 | DC70: 175.07667 | DD70: 177.02953 | DE70: 171.65639 | DF70: 158.11229 | DG70: 159.18622 | DH70: 156.91415 | DI70: 151.7502 | DJ70: 150.69674 | DK70: 156.32163 | DL70: 196.16213 | DM70: 166.10328 | DN70: 139.21572 | DO70: 101.82933 | DP70: 101.18586 | DQ70: 101.88056 | DR70: 75.673893 | DS70: 91.711752 | DT70: 88.847356 | DU70: 87.621867 | DV70: 89.72446 | DW70: 87.804623 | DX70: 87.275941 | DY70: 83.94732 | DZ70: 71.903127 | EA70: 72.272602 | EB70: 79.153997 | EC70: 81.515473 | ED70: 84.543261 | EE70: 87.233978 | EF70: 84.729208 | EG70: 84.400437 | EH70: 88.025844 | EI70: 91.193141 | EJ70: 100.60505 | EK70: 104.40536 | EL70: 103.01456 | EM70: 105.81151 | EN70: 106.00615 | EO70: 104.7481 | EP70: 104.81128 | EQ70: 92.504437 | ER70: 88.542931 | ES70: 88.944035 | ET70: 90.019653 | EU70: 89.624092 | EV70: 90.52883 | EW70: 91.246268 | EX70: 91.807175 | EY70: 92.889856 | EZ70: 93.933258 | FA70: 94.422433 | FB70: 95.06512 | FC70: 94.989658 | FD70: 94.615037 | FE70: 92.737924 | FF70: 103.76853 | FG70: 104.89864 | FH70: 105.4397 | FI70: 106.99246 | FJ70: 105.65684 | FK70: 104.66762 | FL70: 104.16669 | FM70: 105.49496 | FN70: 106.58461 | FO70: 103.57107 | FP70: 103.53878 | FQ70: 101.52436 | FR70: 101.55419 | FS70: 103.36799 | FT70: 103.8503 | FU70: 127.01356 | FV70: 121.89252 | FW70: 186.05579 | FX70: 205.97239 | FY70: 156.3908 | FZ70: 159.22489 | GA70: 162.14165 | GB70: 167.51717 | GC70: 178.26173 | GD70: 183.99508 | GE70: 196.34269 | GF70: 157.64153 | GG70: 158.33406 | GH70: 156.54197 | GI70: 151.14251 | GJ70: 139.99321 | GK70: 133.67728 | GL70: 120.81269 | GM70: 115.7619 | GN70: 110.96437 | GO70: 106.26159 | GP70: 97.691454 | GQ70: 96.189571 | GR70: 97.132973 | GS70: 91.162862 | GT70: 86.609422 | GU70: 89.46934
A71: (Cartera irregular - Previsiones) / Financiaciones | B71: 9.923524 | C71: 6.0539687 | D71: -2.2049634 | E71: -3.8830367 | F71: -0.041420071 | G71: -0.53122942 | H71: -1.0549115 | I71: -0.66655079 | J71: -0.67919653 | K71: -0.79664192 | L71: -0.83481655 | M71: -0.8353405 | N71: -0.71857444 | O71: -0.85533291 | P71: -0.86134709 | Q71: -0.98188949 | R71: -1.0050044 | S71: -1.0640809 | T71: -1.0654481 | U71: -1.0568238 | V71: -1.0656182 | W71: -1.1777065 | X71: -1.1903013 | Y71: -1.1950047 | Z71: -1.1798779 | AA71: -1.1170567 | AB71: -1.1247165 | AC71: -1.1302245 | AD71: -1.1458009 | AE71: -1.1620956 | AF71: -1.1438948 | AG71: -1.1762449 | AH71: -1.1385913 | AI71: -1.142469 | AJ71: -1.1163023 | AK71: -1.0896254 | AL71: -1.0227416 | AM71: -0.9803891 | AN71: -0.95444934 | AO71: -0.96342103 | AP71: -0.89132267 | AQ71: -0.87054102 | AR71: -0.89457333 | AS71: -0.90869211 | AT71: -0.89279647 | AU71: -0.89766997 | AV71: -0.88783592 | AW71: -0.79537431 | AX71: -0.80305576 | AY71: -0.79940528 | AZ71: -0.82107846 | BA71: -0.85223934 | BB71: -0.84272415 | BC71: -0.8850272 | BD71: -0.85976098 | BE71: -1.116013 | BF71: -1.1668886 | BG71: -1.2332546 | BH71: -1.194785 | BI71: -1.1721574 | BJ71: -1.1402022 | BK71: -1.1422747 | BL71: -1.091815 | BM71: -1.0770113 | BN71: -1.1076768 | BO71: -1.119267 | BP71: -1.1230015 | BQ71: -0.99495692 | BR71: -0.98033808 | BS71: -0.96995041 | BT71: -0.96373214 | BU71: -0.91602746 | BV71: -0.92864258 | BW71: -0.8886996 | BX71: -0.89427508 | BY71: -0.90635541 | BZ71: -0.93680429 | CA71: -0.94114059 | CB71: -0.76477124 | CC71: -0.92206618 | CD71: -0.85735436 | CE71: -0.91235305 | CF71: -0.92600524 | CG71: -0.92299967 | CH71: -0.88089779 | CI71: -0.82550329 | CJ71: -0.83334988 | CK71: -0.74052586 | CL71: -0.77159837 | CM71: -0.77186724 | CN71: -0.8683309 | CO71: -0.85978431 | CP71: -0.84697284 | CQ71: -0.90482087 | CR71: -0.90577489 | CS71: -1.0072295 | CT71: -0.97901278 | CU71: -0.99750886 | CV71: -1.0349308 | CW71: -1.0838333 | CX71: -1.1433618 | CY71: -1.1615629 | CZ71: -1.1481957 | DA71: -1.2022976 | DB71: -1.1853819 | DC71: -1.2285609 | DD71: -1.2368063 | DE71: -1.198819 | DF71: -1.0710695 | DG71: -1.0847359 | DH71: -1.0747999 | DI71: -0.99643174 | DJ71: -1.0045842 | DK71: -1.1102761 | DL71: -2.1070069 | DM71: -1.8091067 | DN71: -1.3066364 | DO71: -0.065163511 | DP71: -0.045422718 | DQ71: -0.074769475 | DR71: 1.0771217 | DS71: 0.38238921 | DT71: 0.54032893 | DU71: 0.6262725 | DV71: 0.53744921 | DW71: 0.66139423 | DX71: 0.69964606 | DY71: 1.2525979 | DZ71: 2.2519167 | EA71: 2.2683603 | EB71: 1.6029721 | EC71: 1.4399889 | ED71: 1.2042267 | EE71: 0.99798217 | EF71: 1.2190734 | EG71: 1.2225062 | EH71: 0.90037708 | EI71: 0.63422962 | EJ71: -0.042758035 | EK71: -0.28922032 | EL71: -0.20379011 | EM71: -0.38827119 | EN71: -0.39765723 | EO71: -0.317 | EP71: -0.32361831 | EQ71: 0.57639507 | ER71: 0.93338037 | ES71: 0.87746836 | ET71: 0.75037981 | EU71: 0.76364838 | EV71: 0.65723015 | EW71: 0.57331116 | EX71: 0.53601917 | EY71: 0.44972839 | EZ71: 0.36774437 | FA71: 0.30718639 | FB71: 0.26481361 | FC71: 0.26426775 | FD71: 0.28026644 | FE71: 0.37886721 | FF71: -0.19375599 | FG71: -0.25204629 | FH71: -0.27777927 | FI71: -0.36889655 | FJ71: -0.30330625 | FK71: -0.25063322 | FL71: -0.21955421 | FM71: -0.27894706 | FN71: -0.33238525 | FO71: -0.18428775 | FP71: -0.1813774 | FQ71: -0.084363997 | FR71: -0.080432201 | FS71: -0.16038194 | FT71: -0.17211962 | FU71: -1.9553279 | FV71: -1.5506681 | FW71: -2.3192816 | FX71: -2.7445663 | FY71: -1.3713764 | FZ71: -1.353194 | GA71: -1.3678896 | GB71: -1.2593209 | GC71: -1.296185 | GD71: -1.3036571 | GE71: -1.3646431 | GF71: -0.82363952 | GG71: -0.82090858 | GH71: -0.82118571 | GI71: -0.78970137 | GJ71: -0.69736334 | GK71: -0.6502333 | GL71: -0.4824524 | GM71: -0.40589166 | GN71: -0.31267873 | GO71: -0.20458335 | GP71: 0.088230843 | GQ71: 0.16332657 | GR71: 0.14369298 | GS71: 0.4900072 | GT71: 0.85005923 | GU71: 0.68396056
A72: (Cartera irregular - Previsiones) / PN | B72: 13.966073 | C72: 9.9458839 | D72: -3.4832889 | E72: -6.8919904 | F72: -0.075671551 | G72: -1.2382724 | H72: -3.2604124 | I72: -1.9956793 | J72: -2.0212009 | K72: -2.3198076 | L72: -2.4315579 | M72: -2.4344291 | N72: -2.1103357 | O72: -2.4849209 | P72: -2.4751511 | Q72: -2.8448791 | R72: -2.9197541 | S72: -3.0993808 | T72: -3.1414062 | U72: -3.2084857 | V72: -3.2009807 | W72: -3.5444911 | X72: -3.5300091 | Y72: -3.5925612 | Z72: -3.5953537 | AA72: -3.5175133 | AB72: -3.7282097 | AC72: -3.8251091 | AD72: -4.0121501 | AE72: -4.1206873 | AF72: -4.2248938 | AG72: -4.3417963 | AH72: -4.1840487 | AI72: -4.2071635 | AJ72: -4.0827409 | AK72: -4.0390235 | AL72: -3.8402625 | AM72: -3.7267583 | AN72: -3.6151634 | AO72: -3.6515302 | AP72: -3.376769 | AQ72: -3.3469982 | AR72: -3.4849695 | AS72: -3.6348597 | AT72: -3.5520019 | AU72: -3.5194616 | AV72: -3.4374065 | AW72: -3.069255 | AX72: -3.092876 | AY72: -3.1265444 | AZ72: -3.1650905 | BA72: -3.2831956 | BB72: -3.2654581 | BC72: -3.3962953 | BD72: -3.3084083 | BE72: -4.2814264 | BF72: -4.2328826 | BG72: -4.4144638 | BH72: -4.1720109 | BI72: -4.0654547 | BJ72: -3.8533165 | BK72: -3.7882622 | BL72: -3.5465174 | BM72: -3.434438 | BN72: -3.5228487 | BO72: -3.5585651 | BP72: -3.5552462 | BQ72: -3.2180587 | BR72: -3.0705316 | BS72: -2.9683492 | BT72: -2.93187 | BU72: -2.7749184 | BV72: -2.831176 | BW72: -2.7256628 | BX72: -2.7969411 | BY72: -2.8188503 | BZ72: -2.8894653 | CA72: -2.9824595 | CB72: -2.4396778 | CC72: -2.8640079 | CD72: -2.623342 | CE72: -2.6234652 | CF72: -2.5955872 | CG72: -2.5787321 | CH72: -2.4353383 | CI72: -2.2658883 | CJ72: -2.2299904 | CK72: -2.1498305 | CL72: -2.232722 | CM72: -2.271373 | CN72: -2.5951492 | CO72: -2.4036153 | CP72: -2.3714849 | CQ72: -2.5650602 | CR72: -2.5417373 | CS72: -2.8629624 | CT72: -2.7889222 | CU72: -2.9327818 | CV72: -3.1191393 | CW72: -3.3772338 | CX72: -3.7183602 | CY72: -3.9382388 | CZ72: -4.0788297 | DA72: -4.7172087 | DB72: -3.9829123 | DC72: -4.0662689 | DD72: -4.5578958 | DE72: -4.3258354 | DF72: -3.9807071 | DG72: -4.0571412 | DH72: -4.0982035 | DI72: -3.7994988 | DJ72: -3.7762969 | DK72: -4.1338564 | DL72: -8.1310984 | DM72: -6.3497771 | DN72: -4.5289302 | DO72: -0.22542462 | DP72: -0.1651911 | DQ72: -0.28590662 | DR72: 5.1013696 | DS72: 1.4730532 | DT72: 1.9885717 | DU72: 2.5666977 | DV72: 2.089279 | DW72: 2.5748009 | DX72: 2.7449498 | DY72: 4.9140946 | DZ72: 6.4349252 | EA72: 6.4863265 | EB72: 4.5387953 | EC72: 4.0941508 | ED72: 3.3345811 | EE72: 2.7554967 | EF72: 3.3715173 | EG72: 3.180363 | EH72: 2.3524907 | EI72: 1.6658932 | EJ72: -0.10995451 | EK72: -0.74996548 | EL72: -0.50192247 | EM72: -0.93366313 | EN72: -0.93940198 | EO72: -0.73707498 | EP72: -0.73488382 | EQ72: 1.3039175 | ER72: 2.1238334 | ES72: 1.9622005 | ET72: 1.6881005 | EU72: 1.7400835 | EV72: 1.5071919 | EW72: 1.3243991 | EX72: 1.195644 | EY72: 0.98817548 | EZ72: 0.79374102 | FA72: 0.64767643 | FB72: 0.55328472 | FC72: 0.55128699 | FD72: 0.55889539 | FE72: 0.72767857 | FF72: -0.35389175 | FG72: -0.44295955 | FH72: -0.47694541 | FI72: -0.61306441 | FJ72: -0.48557888 | FK72: -0.38883903 | FL72: -0.33761898 | FM72: -0.4347291 | FN72: -0.50274077 | FO72: -0.27164515 | FP72: -0.26514662 | FQ72: -0.1161244 | FR72: -0.10453045 | FS72: -0.20351972 | FT72: -0.20500458 | FU72: -1.850124 | FV72: -1.3161284 | FW72: -1.7512285 | FX72: -1.975199 | FY72: -0.95288422 | FZ72: -0.98818044 | GA72: -1.0423888 | GB72: -1.0707212 | GC72: -1.1866371 | GD72: -1.2756356 | GE72: -1.480444 | GF72: -0.9042274 | GG72: -0.97395902 | GH72: -0.97492952 | GI72: -0.99035836 | GJ72: -0.91262904 | GK72: -0.86754533 | GL72: -0.6583528 | GM72: -0.57030881 | GN72: -0.45379239 | GO72: -0.31034585 | GP72: 0.1369958 | GQ72: 0.24139596 | GR72: 0.21260585 | GS72: 0.72478983 | GT72: 1.2719343 | GU72: 1.0260454
A73: Fuente: BCRA
A78: Entidades financieras no bancarias (EFNB)
A79: En porcentaje | B79: 37591 | C79: 37956 | D79: 38322 | E79: 38687 | F79: 39052 | G79: 39417 | H79: 39783 | I79: 40148 | J79: 40179 | K79: 40210 | L79: 40238 | M79: 40269 | N79: 40299 | O79: 40330 | P79: 40360 | Q79: 40391 | R79: 40422 | S79: 40452 | T79: 40483 | U79: 40513 | V79: 40544 | W79: 40575 | X79: 40603 | Y79: 40634 | Z79: 40664 | AA79: 40695 | AB79: 40725 | AC79: 40756 | AD79: 40787 | AE79: 40817 | AF79: 40848 | AG79: 40878 | AH79: 40909 | AI79: 40940 | AJ79: 40969 | AK79: 41000 | AL79: 41030 | AM79: 41061 | AN79: 41091 | AO79: 41122 | AP79: 41153 | AQ79: 41183 | AR79: 41214 | AS79: 41244 | AT79: 41275 | AU79: 41306 | AV79: 41334 | AW79: 41365 | AX79: 41395 | AY79: 41426 | AZ79: 41456 | BA79: 41487 | BB79: 41518 | BC79: 41548 | BD79: 41579 | BE79: 41609 | BF79: 41640 | BG79: 41671 | BH79: 41699 | BI79: 41730 | BJ79: 41760 | BK79: 41791 | BL79: 41821 | BM79: 41852 | BN79: 41883 | BO79: 41913 | BP79: 41944 | BQ79: 41974 | BR79: 42005 | BS79: 42036 | BT79: 42064 | BU79: 42095 | BV79: 42125 | BW79: 42156 | BX79: 42186 | BY79: 42217 | BZ79: 42248 | CA79: 42278 | CB79: 42309 | CC79: 42339 | CD79: 42370 | CE79: 42401 | CF79: 42430 | CG79: 42461 | CH79: 42491 | CI79: 42522 | CJ79: 42552 | CK79: 42583 | CL79: 42614 | CM79: 42644 | CN79: 42675 | CO79: 42705 | CP79: 42736 | CQ79: 42767 | CR79: 42795 | CS79: 42826 | CT79: 42856 | CU79: 42887 | CV79: 42917 | CW79: 42948 | CX79: 42979 | CY79: 43009 | CZ79: 43040 | DA79: 43070 | DB79: 43101 | DC79: 43132 | DD79: 43160 | DE79: 43191 | DF79: 43221 | DG79: 43252 | DH79: 43282 | DI79: 43313 | DJ79: 43344 | DK79: 43374 | DL79: 43405 | DM79: 43435 | DN79: 43466 | DO79: 43497 | DP79: 43525 | DQ79: 43556 | DR79: 43586 | DS79: 43617 | DT79: 43647 | DU79: 43678 | DV79: 43709 | DW79: 43739 | DX79: 43770 | DY79: 43800 | DZ79: 43831 | EA79: 43862 | EB79: 43891 | EC79: 43922 | ED79: 43952 | EE79: 43983 | EF79: 44013 | EG79: 44044 | EH79: 44075 | EI79: 44105 | EJ79: 44136 | EK79: 44166 | EL79: 44197 | EM79: 44228 | EN79: 44256 | EO79: 44287 | EP79: 44317 | EQ79: 44348 | ER79: 44378 | ES79: 44409 | ET79: 44440 | EU79: 44470 | EV79: 44501 | EW79: 44531 | EX79: 44562 | EY79: 44593 | EZ79: 44621 | FA79: 44652 | FB79: 44682 | FC79: 44713 | FD79: 44743 | FE79: 44774 | FF79: 44805 | FG79: 44835 | FH79: 44866 | FI79: 44896 | FJ79: 44927 | FK79: 44958 | FL79: 44986 | FM79: 45017 | FN79: 45047 | FO79: 45078 | FP79: 45108 | FQ79: 45139 | FR79: 45170 | FS79: 45200 | FT79: 45231 | FU79: 45261 | FV79: 45292 | FW79: 45323 | FX79: 45352 | FY79: 45383 | FZ79: 45413 | GA79: 45444 | GB79: 45474 | GC79: 45505 | GD79: 45536 | GE79: 45566 | GF79: 45597 | GG79: 45627 | GH79: 45658 | GI79: 45689 | GJ79: 45717 | GK79: 45748 | GL79: 45778 | GM79: 45809 | GN79: 45839 | GO79: 45870 | GP79: 45901 | GQ79: 45931 | GR79: 45962 | GS79: 45992 | GT79: 46023 | GU79: 46054
A80: Cartera irregular total | B80: 34.402695 | C80: 14.915362 | D80: 7.1610572 | E80: 5.8738354 | F80: 5.3105938 | G80: 6.5753391 | H80: 9.2928433 | I80: 11.056719 | J80: 10.449358 | K80: 10.181014 | L80: 9.9987313 | M80: 9.0098003 | N80: 8.8825447 | O80: 6.5172467 | P80: 6.224814 | Q80: 5.9102124 | R80: 5.4392037 | S80: 4.9318278 | T80: 4.6619087 | U80: 4.4799318 | V80: 4.2954921 | W80: 4.1677113 | X80: 3.9337461 | Y80: 3.6240975 | Z80: 3.5347286 | AA80: 3.2139249 | AB80: 3.1347715 | AC80: 2.9189348 | AD80: 2.7612923 | AE80: 2.7434891 | AF80: 2.7251663 | AG80: 2.698237 | AH80: 2.7650173 | AI80: 2.966654 | AJ80: 3.1145367 | AK80: 3.2591822 | AL80: 3.3724595 | AM80: 3.3935358 | AN80: 3.4796852 | AO80: 3.4818105 | AP80: 3.5228902 | AQ80: 3.4982267 | AR80: 3.5491901 | AS80: 3.6444811 | AT80: 3.6897539 | AU80: 3.8307439 | AV80: 3.9358071 | AW80: 3.941927 | AX80: 3.9389385 | AY80: 4.0162839 | AZ80: 3.9906536 | BA80: 3.9809006 | BB80: 3.6047453 | BC80: 3.5189902 | BD80: 3.5440919 | BE80: 3.5171514 | BF80: 3.5892545 | BG80: 3.7190601 | BH80: 3.9226132 | BI80: 4.2405844 | BJ80: 4.736454 | BK80: 4.9467272 | BL80: 5.1465222 | BM80: 5.1968682 | BN80: 5.1672986 | BO80: 5.2221572 | BP80: 5.3593149 | BQ80: 5.0775649 | BR80: 5.1633558 | BS80: 5.0778076 | BT80: 5.2582773 | BU80: 5.480854 | BV80: 5.5300268 | BW80: 5.6136609 | BX80: 5.4638945 | BY80: 5.3694274 | BZ80: 5.0669612 | CA80: 5.0534854 | CB80: 4.754845 | CC80: 4.7065423 | CD80: 4.7038993 | CE80: 4.6898557 | CF80: 4.4747467 | CG80: 4.5041297 | CH80: 4.4867884 | CI80: 4.4877892 | CJ80: 4.947908 | CK80: 4.7476336 | CL80: 4.5616225 | CM80: 4.5170608 | CN80: 4.1852305 | CO80: 3.9130677 | CP80: 3.9029271 | CQ80: 3.8793972 | CR80: 3.9729978 | CS80: 4.1774808 | CT80: 4.3515541 | CU80: 4.2249819 | CV80: 4.1927974 | CW80: 4.1866608 | CX80: 4.0943323 | CY80: 4.090916 | CZ80: 4.1715069 | DA80: 4.1300835 | DB80: 4.3680679 | DC80: 4.4956811 | DD80: 4.5624854 | DE80: 4.6941254 | DF80: 4.7348741 | DG80: 4.8242877 | DH80: 4.8327186 | DI80: 4.6282539 | DJ80: 4.7107487 | DK80: 4.9766267 | DL80: 5.4466512 | DM80: 5.9737427 | DN80: 5.9348445 | DO80: 6.761394 | DP80: 6.7510873 | DQ80: 7.5063379 | DR80: 7.7612673 | DS80: 7.7415571 | DT80: 7.6498648 | DU80: 7.6775558 | DV80: 7.7753736 | DW80: 7.4484259 | DX80: 7.9061993 | DY80: 7.7999034 | DZ80: 7.6168249 | EA80: 7.7319603 | EB80: 6.522046 | EC80: 6.6822968 | ED80: 6.4824158 | EE80: 6.6838066 | EF80: 7.0116139 | EG80: 6.3764542 | EH80: 5.4512112 | EI80: 5.0848951 | EJ80: 4.512158 | EK80: 4.0956733 | EL80: 3.8401173 | EM80: 3.6126314 | EN80: 3.6148641 | EO80: 3.6873753 | EP80: 3.7148057 | EQ80: 3.9548933 | ER80: 4.9847508 | ES80: 5.4085583 | ET80: 5.8214948 | EU80: 5.8783499 | EV80: 6.2269147 | EW80: 6.3214907 | EX80: 6.3913771 | EY80: 6.0932509 | EZ80: 5.7736203 | FA80: 5.4726119 | FB80: 5.3050525 | FC80: 5.028037 | FD80: 4.9025136 | FE80: 4.9225713 | FF80: 4.6954235 | FG80: 4.6644995 | FH80: 4.302133 | FI80: 3.7106788 | FJ80: 3.8485158 | FK80: 3.8700358 | FL80: 3.8179908 | FM80: 3.702811 | FN80: 3.7893802 | FO80: 3.5263285 | FP80: 3.613998 | FQ80: 3.5101383 | FR80: 3.4205582 | FS80: 3.2458973 | FT80: 3.459898 | FU80: 3.4593976 | FV80: 3.3451645 | FW80: 3.2192355 | FX80: 3.4401411 | FY80: 4.305905 | FZ80: 4.1902914 | GA80: 4.2014467 | GB80: 4.4270429 | GC80: 4.081033 | GD80: 4.3872647 | GE80: 4.6624026 | GF80: 4.7573606 | GG80: 3.4523379 | GH80: 3.5227148 | GI80: 3.7124593 | GJ80: 3.7940903 | GK80: 3.8525806 | GL80: 4.2285607 | GM80: 4.3027517 | GN80: 4.5135501 | GO80: 4.3817508 | GP80: 4.8203095 | GQ80: 5.214659 | GR80: 5.0220118 | GS80: 5.4638939 | GT80: 5.7260389 | GU80: 6.106099
A81: Previsiones / Cartera irregular | B81: 84.626425 | C81: 87.29843 | D81: 96.800721 | E81: 85.333651 | F81: 84.484252 | G81: 76.382409 | H81: 65.879808 | I81: 71.348454 | J81: 73.031 | K81: 74.677459 | L81: 75.447924 | M81: 79.4828 | N81: 79.530742 | O81: 75.865841 | P81: 76.659981 | Q81: 100.98674 | R81: 104.73491 | S81: 110.62362 | T81: 112.23036 | U81: 114.8507 | V81: 115.55191 | W81: 116.70299 | X81: 118.7937 | Y81: 120.08194 | Z81: 119.63767 | AA81: 120.99207 | AB81: 119.97611 | AC81: 123.68352 | AD81: 124.29702 | AE81: 122.5971 | AF81: 120.26349 | AG81: 118.43043 | AH81: 116.13053 | AI81: 111.12123 | AJ81: 106.07284 | AK81: 103.18859 | AL81: 100.27441 | AM81: 100.32416 | AN81: 98.387894 | AO81: 95.299888 | AP81: 91.346013 | AQ81: 88.818129 | AR81: 84.710023 | AS81: 83.550931 | AT81: 82.912394 | AU81: 81.567914 | AV81: 81.332652 | AW81: 80.637447 | AX81: 80.047128 | AY81: 80.341406 | AZ81: 82.191692 | BA81: 82.002966 | BB81: 82.055839 | BC81: 84.170589 | BD81: 83.29028 | BE81: 84.825816 | BF81: 83.058799 | BG81: 81.044302 | BH81: 78.633202 | BI81: 76.353543 | BJ81: 70.540507 | BK81: 69.738507 | BL81: 68.34639 | BM81: 68.417857 | BN81: 69.513987 | BO81: 69.893515 | BP81: 69.82978 | BQ81: 75.064668 | BR81: 74.031333 | BS81: 74.915797 | BT81: 75.551948 | BU81: 76.205218 | BV81: 77.601697 | BW81: 79.79826 | BX81: 81.842239 | BY81: 83.144546 | BZ81: 85.392603 | CA81: 85.957163 | CB81: 90.096996 | CC81: 93.03412 | CD81: 92.340456 | CE81: 91.262744 | CF81: 88.339675 | CG81: 86.036168 | CH81: 84.31684 | CI81: 83.141179 | CJ81: 74.72843 | CK81: 76.038506 | CL81: 76.335638 | CM81: 75.66966 | CN81: 75.867421 | CO81: 75.933104 | CP81: 77.029551 | CQ81: 78.043552 | CR81: 77.846777 | CS81: 76.86604 | CT81: 75.583806 | CU81: 77.526056 | CV81: 78.295128 | CW81: 78.76244 | CX81: 79.888695 | CY81: 80.521165 | CZ81: 80.524853 | DA81: 81.775233 | DB81: 81.214426 | DC81: 80.847522 | DD81: 79.552686 | DE81: 77.234647 | DF81: 75.591256 | DG81: 75.041328 | DH81: 76.172468 | DI81: 77.049735 | DJ81: 77.199908 | DK81: 74.818855 | DL81: 71.680618 | DM81: 67.770637 | DN81: 70.240415 | DO81: 65.588189 | DP81: 66.962466 | DQ81: 61.662782 | DR81: 61.220111 | DS81: 61.816972 | DT81: 62.666699 | DU81: 62.550625 | DV81: 64.49039 | DW81: 63.146773 | DX81: 61.643605 | DY81: 61.243051 | DZ81: 58.832494 | EA81: 57.078855 | EB81: 68.945047 | EC81: 69.473175 | ED81: 71.771844 | EE81: 69.87939 | EF81: 67.32226 | EG81: 73.065945 | EH81: 81.932596 | EI81: 85.311936 | EJ81: 89.879692 | EK81: 96.461254 | EL81: 103.16171 | EM81: 108.79758 | EN81: 107.07075 | EO81: 104.28475 | EP81: 101.60507 | EQ81: 96.365083 | ER81: 81.095989 | ES81: 76.919037 | ET81: 70.048935 | EU81: 67.900694 | EV81: 66.054985 | EW81: 67.244323 | EX81: 67.384763 | EY81: 68.383784 | EZ81: 69.310481 | FA81: 69.796304 | FB81: 69.889794 | FC81: 70.923729 | FD81: 74.596271 | FE81: 75.099905 | FF81: 100.18235 | FG81: 94.604712 | FH81: 86.541778 | FI81: 83.740381 | FJ81: 81.699855 | FK81: 80.655267 | FL81: 79.547087 | FM81: 79.321056 | FN81: 78.34825 | FO81: 80.264328 | FP81: 80.227919 | FQ81: 81.814607 | FR81: 78.943427 | FS81: 83.029609 | FT81: 78.721856 | FU81: 77.728524 | FV81: 83.389941 | FW81: 92.090663 | FX81: 88.797612 | FY81: 84.938386 | FZ81: 84.481179 | GA81: 81.874711 | GB81: 83.631218 | GC81: 86.333703 | GD81: 86.6396 | GE81: 86.957425 | GF81: 97.667253 | GG81: 96.539616 | GH81: 89.658012 | GI81: 91.50645 | GJ81: 99.850379 | GK81: 106.26513 | GL81: 103.40848 | GM81: 103.08012 | GN81: 97.191258 | GO81: 97.831649 | GP81: 98.46612 | GQ81: 95.663835 | GR81: 93.545465 | GS81: 82.344481 | GT81: 84.955491 | GU81: 82.768577
A82: (Cartera irregular - Previsiones) / Financiaciones | B82: 5.2889242 | C82: 1.894485 | D82: 0.22910223 | E82: 0.86147719 | F82: 0.82397832 | G82: 1.5529367 | H82: 3.170736 | I82: 3.167921 | J82: 2.8180873 | K82: 2.5780914 | L82: 2.4548961 | M82: 1.8485588 | N82: 1.818191 | O82: 1.5728827 | P82: 1.4528728 | Q82: -0.058318166 | R82: -0.25754166 | S82: -0.52393846 | T82: -0.57016834 | U82: -0.66530131 | V82: -0.66803098 | W82: -0.69613226 | X82: -0.73929659 | Y82: -0.72778917 | Z82: -0.69413834 | AA82: -0.67466923 | AB82: -0.62620547 | AC82: -0.69130636 | AD82: -0.67091168 | AE82: -0.61994903 | AF82: -0.55221389 | AG82: -0.49729678 | AH82: -0.446012 | AI82: -0.32992832 | AJ82: -0.18914094 | AK82: -0.10392206 | AL82: -0.0092544573 | AM82: -0.011000359 | AN82: 0.056096221 | AO82: 0.16364898 | AP82: 0.30487046 | AQ82: 0.3911672 | AR82: 0.54267035 | AS82: 0.59948319 | AT82: 0.63049059 | AU82: 0.706086 | AV82: 0.73471079 | AW82: 0.76325772 | AX82: 0.78593137 | AY82: 0.78954496 | AZ82: 0.71066788 | BA82: 0.71644405 | BB82: 0.64684129 | BC82: 0.55703543 | BD82: 0.59220782 | BE82: 0.53369903 | BF82: 0.60806281 | BG82: 0.70497379 | BH82: 0.83813685 | BI82: 1.002748 | BJ82: 1.3953353 | BK82: 1.4969535 | BL82: 1.6290601 | BM82: 1.6412823 | BN82: 1.5753033 | BO82: 1.572208 | BP82: 1.6169171 | BQ82: 1.2661077 | BR82: 1.3408547 | BS82: 1.2737275 | BT82: 1.2855464 | BU82: 1.3041573 | BV82: 1.2386322 | BW82: 1.1340572 | BX82: 0.99212092 | BY82: 0.90504138 | BZ82: 0.74015112 | CA82: 0.7096527 | CB82: 0.47087248 | CC82: 0.32785207 | CD82: 0.36029722 | CE82: 0.40976471 | CF82: 0.52177002 | CG82: 0.62894911 | CH82: 0.70367022 | CI82: 0.75658837 | CJ82: 1.250414 | CK82: 1.1376039 | CL82: 1.0794789 | CM82: 1.0990162 | CN82: 1.010004 | CO82: 0.94175395 | CP82: 0.89651989 | CQ82: 0.85177783 | CR82: 0.88014705 | CS82: 0.96641673 | CT82: 1.0624839 | CU82: 0.94952004 | CV82: 0.9100413 | CW82: 0.88914463 | CX82: 0.82342367 | CY82: 0.79686276 | CZ82: 0.81240711 | DA82: 0.75269811 | DB82: 0.82056664 | DC82: 0.86103434 | DD82: 0.93290571 | DE82: 1.0686342 | DF82: 1.1557233 | DG82: 1.2040782 | DH82: 1.1515176 | DI82: 1.0621965 | DJ82: 1.074055 | DK82: 1.2531716 | DL82: 1.542458 | DM82: 1.9252992 | DN82: 1.7661851 | DO82: 2.3267181 | DP82: 2.2303928 | DQ82: 2.8777211 | DR82: 3.0098108 | DS82: 2.9559609 | DT82: 2.855947 | DU82: 2.8751967 | DV82: 2.7610048 | DW82: 2.7449853 | DX82: 3.032533 | DY82: 3.0230045 | DZ82: 3.1356568 | EA82: 3.3186459 | EB82: 2.0254183 | EC82: 2.0398931 | ED82: 1.8298665 | EE82: 2.0132033 | EF82: 2.291237 | EG82: 1.7174377 | EH82: 0.98489238 | EI82: 0.74687264 | EJ82: 0.45664428 | EK82: 0.14493549 | EL82: -0.12141331 | EM82: -0.31782409 | EN82: -0.2555981 | EO82: -0.15799469 | EP82: -0.059625093 | EQ82: 0.14375707 | ER82: 0.94231784 | ES82: 1.2483473 | ET82: 1.7435997 | EU82: 1.8869095 | EV82: 2.1137271 | EW82: 2.070647 | EX82: 2.0845628 | EY82: 1.9264554 | EZ82: 1.7718963 | FA82: 1.652931 | FB82: 1.5973623 | FC82: 1.4619657 | FD82: 1.2454213 | FE82: 1.2257249 | FF82: -0.0085620582 | FG82: 0.25166316 | FH82: 0.5789906 | FI82: 0.60334222 | FJ82: 0.70428396 | FK82: 0.74864811 | FL82: 0.78089033 | FM82: 0.76570219 | FN82: 0.82046714 | FO82: 0.69594461 | FP82: 0.71456262 | FQ82: 0.63833245 | FR82: 0.72025232 | FS82: 0.55084145 | FT82: 0.73620209 | FU82: 0.77045891 | FV82: 0.5556338 | FW82: 0.25462019 | FX82: 0.38537796 | FY82: 0.64853879 | FZ82: 0.65028381 | GA82: 0.76152435 | GB82: 0.72465303 | GC82: 0.5577261 | GD82: 0.58615611 | GE82: 0.60809736 | GF82: 0.11097721 | GG82: 0.11946413 | GH82: 0.36431873 | GI82: 0.3153196 | GJ82: 0.0056767606 | GK82: -0.24136933 | GL82: -0.14412951 | GM82: -0.1325301 | GN82: 0.12677397 | GO82: 0.095011725 | GP82: 0.07393774 | GQ82: 0.22611622 | GR82: 0.32414751 | GS82: 0.96467883 | GT82: 0.86145446 | GU82: 1.0521677
A83: (Cartera irregular - Previsiones) / PN | B83: 4.8038826 | C83: 1.6179718 | D83: 0.26792298 | E83: 1.6537818 | F83: 2.2806183 | G83: 5.4990358 | H83: 8.9631287 | I83: 7.8948674 | J83: 7.0464031 | K83: 6.3742569 | L83: 6.0833576 | M83: 4.717141 | N83: 4.5252723 | O83: 3.6746702 | P83: 3.3742171 | Q83: -0.14285406 | R83: -0.65062512 | S83: -1.3625909 | T83: -1.6288737 | U83: -1.9104543 | V83: -1.9562486 | W83: -2.0558165 | X83: -2.2751239 | Y83: -2.4156256 | Z83: -2.3350547 | AA83: -2.3219961 | AB83: -2.1816474 | AC83: -2.4656752 | AD83: -2.511557 | AE83: -2.361208 | AF83: -2.1373824 | AG83: -1.9817909 | AH83: -1.7930173 | AI83: -1.3083237 | AJ83: -0.75752313 | AK83: -0.44578944 | AL83: -0.039678021 | AM83: -0.047536701 | AN83: 0.24305904 | AO83: 0.70593534 | AP83: 1.3232961 | AQ83: 1.7015946 | AR83: 2.3714905 | AS83: 2.6388431 | AT83: 2.7873428 | AU83: 3.1160386 | AV83: 3.2108498 | AW83: 3.4949907 | AX83: 3.6488672 | AY83: 3.6490002 | AZ83: 3.2956352 | BA83: 3.3515609 | BB83: 3.0577368 | BC83: 2.6551404 | BD83: 2.8337475 | BE83: 2.5701917 | BF83: 2.912779 | BG83: 3.2809703 | BH83: 3.8225645 | BI83: 4.4780201 | BJ83: 6.1185389 | BK83: 6.3216592 | BL83: 6.6132038 | BM83: 6.6222116 | BN83: 6.1888507 | BO83: 6.1509265 | BP83: 6.1011799 | BQ83: 4.6072909 | BR83: 4.8000473 | BS83: 4.5359898 | BT83: 4.5077014 | BU83: 4.8554089 | BV83: 4.5980043 | BW83: 4.1000663 | BX83: 3.5553948 | BY83: 3.2961246 | BZ83: 2.7560562 | CA83: 2.5700001 | CB83: 1.7548391 | CC83: 1.1966641 | CD83: 1.3175941 | CE83: 1.5179663 | CF83: 2.0295413 | CG83: 2.6614462 | CH83: 3.0271439 | CI83: 3.2690236 | CJ83: 5.4526562 | CK83: 5.2009287 | CL83: 5.2065106 | CM83: 5.0446058 | CN83: 4.9150653 | CO83: 4.9463859 | CP83: 4.7365392 | CQ83: 4.6111715 | CR83: 5.4855067 | CS83: 6.1005819 | CT83: 6.8313486 | CU83: 6.3175365 | CV83: 6.1565652 | CW83: 6.1745332 | CX83: 5.9336671 | CY83: 5.8768026 | CZ83: 5.9833155 | DA83: 5.4302181 | DB83: 5.7171716 | DC83: 6.0538539 | DD83: 6.7169415 | DE83: 7.6533625 | DF83: 8.5276465 | DG83: 8.9131211 | DH83: 8.3167193 | DI83: 8.0803519 | DJ83: 8.299357 | DK83: 9.5201777 | DL83: 11.324436 | DM83: 15.141811 | DN83: 13.63326 | DO83: 16.405949 | DP83: 15.906051 | DQ83: 19.790415 | DR83: 20.579513 | DS83: 19.102837 | DT83: 17.645335 | DU83: 18.453339 | DV83: 16.456724 | DW83: 16.191127 | DX83: 17.136755 | DY83: 16.571543 | DZ83: 16.827024 | EA83: 17.488566 | EB83: 10.697592 | EC83: 10.47567 | ED83: 9.3620978 | EE83: 10.19377 | EF83: 11.558679 | EG83: 8.5304305 | EH83: 4.9362434 | EI83: 3.617146 | EJ83: 2.2493467 | EK83: 0.71677038 | EL83: -0.59563512 | EM83: -1.531707 | EN83: -1.2367737 | EO83: -0.78009719 | EP83: -0.30046618 | EQ83: 0.70601079 | ER83: 4.5432974 | ES83: 6.0262124 | ET83: 8.6132105 | EU83: 9.2405828 | EV83: 10.364258 | EW83: 10.148716 | EX83: 9.7303432 | EY83: 9.1015275 | EZ83: 8.023719 | FA83: 7.3726803 | FB83: 7.2812662 | FC83: 6.7829221 | FD83: 5.5500755 | FE83: 5.3056429 | FF83: -0.038250588 | FG83: 1.0973384 | FH83: 2.3755228 | FI83: 2.4804729 | FJ83: 2.6357084 | FK83: 3.311981 | FL83: 3.4478391 | FM83: 3.5331407 | FN83: 3.7590863 | FO83: 3.2395527 | FP83: 3.1686607 | FQ83: 2.8806101 | FR83: 3.3340065 | FS83: 2.465469 | FT83: 3.1860658 | FU83: 3.2707281 | FV83: 2.1581695 | FW83: 1.0001216 | FX83: 1.4543463 | FY83: 2.2850133 | FZ83: 2.523704 | GA83: 3.1862359 | GB83: 3.0334054 | GC83: 2.7451187 | GD83: 2.8762337 | GE83: 3.0869728 | GF83: 0.61043883 | GG83: 0.65529154 | GH83: 2.0224973 | GI83: 1.8057729 | GJ83: 0.032824221 | GK83: -1.4673592 | GL83: -0.9202898 | GM83: -0.86433351 | GN83: 0.81501456 | GO83: 0.6515731 | GP83: 0.4946324 | GQ83: 1.5049843 | GR83: 2.2037549 | GS83: 6.2372736 | GT83: 5.3458621 | GU83: 6.381966
A84: Al sector privado no financiero | B84: 36.549884 | C84: 16.287935 | D84: 7.582623 | E84: 6.7088603 | F84: 5.5679701 | G84: 6.8108212 | H84: 9.507798 | I84: 11.66853 | J84: 11.259178 | K84: 10.874547 | L84: 10.747063 | M84: 9.8932414 | N84: 9.7493057 | O84: 6.8881535 | P84: 6.5568582 | Q84: 6.2141684 | R84: 5.6642092 | S84: 5.1615426 | T84: 4.8766505 | U84: 4.5634605 | V84: 4.3700045 | W84: 4.3159655 | X84: 4.0504374 | Y84: 3.7937162 | Z84: 3.6315476 | AA84: 3.3193491 | AB84: 3.2312915 | AC84: 3.0112791 | AD84: 2.8517663 | AE84: 2.8078564 | AF84: 2.8117145 | AG84: 2.7919945 | AH84: 2.8634232 | AI84: 3.0297801 | AJ84: 3.2186665 | AK84: 3.3667223 | AL84: 3.5372351 | AM84: 3.490181 | AN84: 3.5550903 | AO84: 3.5771427 | AP84: 3.6133964 | AQ84: 3.5736579 | AR84: 3.6134595 | AS84: 3.6877823 | AT84: 3.7703082 | AU84: 3.9081442 | AV84: 3.9707976 | AW84: 4.03114 | AX84: 4.0800629 | AY84: 4.1373577 | AZ84: 4.1238855 | BA84: 4.124384 | BB84: 3.7365861 | BC84: 3.6584439 | BD84: 3.6815989 | BE84: 3.5521942 | BF84: 3.7022021 | BG84: 3.786946 | BH84: 4.017637 | BI84: 4.3653176 | BJ84: 4.82425 | BK84: 5.0095611 | BL84: 5.2411039 | BM84: 5.385822 | BN84: 5.3531538 | BO84: 5.4924084 | BP84: 5.5954427 | BQ84: 5.2968621 | BR84: 5.5561589 | BS84: 5.4271662 | BT84: 5.6081071 | BU84: 5.7700918 | BV84: 5.7367381 | BW84: 5.7077682 | BX84: 5.634875 | BY84: 5.5387647 | BZ84: 5.211055 | CA84: 5.1257096 | CB84: 4.880053 | CC84: 4.790258 | CD84: 4.8023968 | CE84: 4.7457876 | CF84: 4.5672439 | CG84: 4.6031735 | CH84: 4.5605267 | CI84: 4.5858919 | CJ84: 5.0516354 | CK84: 4.8375331 | CL84: 4.6639555 | CM84: 4.566816 | CN84: 4.2161419 | CO84: 3.9437748 | CP84: 3.9260831 | CQ84: 3.9062073 | CR84: 4.0040543 | CS84: 4.2324836 | CT84: 4.3964037 | CU84: 4.2817552 | CV84: 4.2717224 | CW84: 4.2579988 | CX84: 4.1574224 | CY84: 4.1474018 | CZ84: 4.2219097 | DA84: 4.1908019 | DB84: 4.4524109 | DC84: 4.5712041 | DD84: 4.6127274 | DE84: 4.7524096 | DF84: 4.8364747 | DG84: 4.9238257 | DH84: 4.9172857 | DI84: 4.7497982 | DJ84: 4.8456625 | DK84: 5.1237245 | DL84: 5.5341523 | DM84: 6.2378792 | DN84: 6.2419394 | DO84: 7.0221615 | DP84: 7.5104981 | DQ84: 7.8172815 | DR84: 8.3024615 | DS84: 8.0266265 | DT84: 7.888479 | DU84: 8.0908113 | DV84: 8.2677259 | DW84: 7.9674562 | DX84: 8.2751621 | DY84: 8.2093348 | DZ84: 8.2025811 | EA84: 8.2224431 | EB84: 6.799322 | EC84: 6.9157365 | ED84: 6.8032939 | EE84: 6.9551235 | EF84: 7.472813 | EG84: 6.6062166 | EH84: 5.6399298 | EI84: 5.2281123 | EJ84: 4.7241412 | EK84: 4.2273144 | EL84: 3.927591 | EM84: 3.7110415 | EN84: 3.700687 | EO84: 3.7601938 | EP84: 3.7872491 | EQ84: 4.0031571 | ER84: 5.0972122 | ES84: 5.540963 | ET84: 5.9488307 | EU84: 6.0130876 | EV84: 6.4666562 | EW84: 6.598697 | EX84: 6.6771983 | EY84: 6.3409051 | EZ84: 5.9655813 | FA84: 5.6572321 | FB84: 5.4689184 | FC84: 5.2228678 | FD84: 5.1039056 | FE84: 5.1161088 | FF84: 4.8814404 | FG84: 4.8144123 | FH84: 4.4356492 | FI84: 3.751615 | FJ84: 3.9563946 | FK84: 3.9003531 | FL84: 3.8685284 | FM84: 3.7280352 | FN84: 3.8196569 | FO84: 3.5412517 | FP84: 3.6567785 | FQ84: 3.5416209 | FR84: 3.4490012 | FS84: 3.2650364 | FT84: 3.506188 | FU84: 3.4922297 | FV84: 3.3704467 | FW84: 3.2307133 | FX84: 3.4585328 | FY84: 4.3178155 | FZ84: 4.3202662 | GA84: 4.2975994 | GB84: 4.500571 | GC84: 4.1579282 | GD84: 4.4759876 | GE84: 4.7203398 | GF84: 4.8211507 | GG84: 3.507489 | GH84: 3.6260335 | GI84: 3.8109011 | GJ84: 3.8670954 | GK84: 3.8919956 | GL84: 4.2468683 | GM84: 4.3863358 | GN84: 4.5677442 | GO84: 4.4941826 | GP84: 4.9030667 | GQ84: 5.2952328 | GR84: 5.1467382 | GS84: 5.6592519 | GT84: 5.9196348 | GU84: 6.305081
